Workbook

Sheet CHECKING
A3: StandardCommodityCode | B3: Translated Part Description (English)
A4: ALM- | B4: 5 275/14 RICAluminum Disc Alloy 99.5 275mm x 1.4mm Replacement Part [cite: 2] | C4: =_xlfn.TRANSLATE(B4,"it","yue") -> 5 275/14 RICAluminium Disc Alloy 99.5 275mm x 1.4mm 替換零件 [引用：2]
B5: 5 280/14 RICAluminum Disc Alloy 99.5 280mm x 1.4mm Replacement Part [cite: 2] | C5: =_xlfn.TRANSLATE(B5,"it","yue") -> 5 280/14 RICAluminium Disc Alloy 99.5 280mm x 1.4mm 替換零件 [引用：2]
B6: 5 315/14 RICAluminum Disc Alloy 99.5 315mm x 1.4mm Replacement Part [cite: 2] | C6: =_xlfn.TRANSLATE(B6,"it","yue") -> 5 315/14 RICAluminium Disc Alloy 99.5 315mm x 1.4mm 替換零件 [引用：2]
B7: 5 390/14 RICAluminum Disc Alloy 99.5 390mm x 1.4mm Replacement Part [cite: 2] | C7: =_xlfn.TRANSLATE(B7,"it","yue") -> 5 390/14 RICAluminium Disc Alloy 99.5 390mm x 1.4mm 替換零件 [引用：2]
B8: Aluminum Disc Alloy 1200 265mm x 2.2mm Replacement Part [cite: 1] | C8: =_xlfn.TRANSLATE(B8,"it","yue") -> 鋁碟合金 1200 265mm x 2.2mm 替換零件 [引用：1]
B9: Aluminum Disc Alloy 1200 410mm x 2.2mm Replacement Part [cite: 1] | C9: =_xlfn.TRANSLATE(B9,"it","yue") -> 鋁碟合金 1200 410mm x 2.2mm 替換零件 [引用：1]
B10: Aluminum Disc Alloy 4006 215mm x 3.6mm Replacement Part [cite: 1 2] | C10: =_xlfn.TRANSLATE(B10,"it","yue") -> 鋁碟合金 4006 215mm x 3.6mm 替換零件 [引用：1 2]
B11: Aluminum Disc Alloy 4006 225mm x 2.9mm Replacement Part [cite: 1] | C11: =_xlfn.TRANSLATE(B11,"it","yue") -> 鋁碟合金 4006 225mm x 2.9mm 替換零件 [引用：1]
B12: Aluminum Disc Alloy 4006 235mm x 2.9mm Replacement Part [cite: 1] | C12: =_xlfn.TRANSLATE(B12,"it","yue") -> 鋁碟合金 4006 235mm x 2.9mm 替換零件 [引用：1]
B13: Aluminum Disc Alloy 4006 235mm x 3.6mm Replacement Part [cite: 2] | C13: =_xlfn.TRANSLATE(B13,"it","yue") -> 鋁碟合金 4006 235mm x 3.6mm 替換零件 [引用：2]
B14: Aluminum Disc Alloy 4006 260mm x 3.6mm Replacement Part [cite: 2] | C14: =_xlfn.TRANSLATE(B14,"it","yue") -> 鋁碟合金 4006 260mm x 3.6mm 替換零件 [引用：2]
B15: Aluminum Disc Alloy 4006 265mm x 2.9mm Replacement Part [cite: 2] | C15: =_xlfn.TRANSLATE(B15,"it","yue") -> 鋁碟合金 4006 265mm x 2.9mm 替換零件 [引用：2]
B16: Aluminum Disc Alloy 4006 265mm x 3.2mm Replacement Part [cite: 2] | C16: =_xlfn.TRANSLATE(B16,"it","yue") -> 鋁碟合金 4006 265mm x 3.2mm 替換零件 [引用：2]
... B64: SHAPED AL. 99.5 324x324x26 ANNEALED | C64: =_xlfn.TRANSLATE(B64,"it","yue") -> 形狀 AL. 99.5 324x324x26 退火
A65: ALM- Total | C65: =_xlfn.TRANSLATE(B65,"it","yue")
A66: BAG- | B66: BAG TYPE 40X55 C/WARNING 35 LINGUE | C66: =_xlfn.TRANSLATE(B66,"it","yue") -> 袋型 40X55 C/警告 35種語言
B67: POLY BAG 26X40 PERFORATED RED PRINT MEYER HESTAN | C67: =_xlfn.TRANSLATE(B67,"it","yue") -> POLY BAG 26X40 PERFORATED RED PRINT MEYER HESTAN
B68: POLY BAG 26X40 PERFORATED REGENERATED 100% MADE IN | C68: =_xlfn.TRANSLATE(B68,"it","yue") -> POLY BAG 26X40 穿孔再生 100% 製造
B69: POLY BAG 40X50 PERFORATED RED PRINT MEYER HESTAN | C69: =_xlfn.TRANSLATE(B69,"it","yue") -> POLY BAG 40X50 PERFORATED RED PRINT MEYER HESTAN
B70: POLY BAG 40X50 PERFORATED REGENERATED 100% MADE IN | C70: =_xlfn.TRANSLATE(B70,"it","yue") -> POLY BAG 40X50 穿孔再生 100% 製造
B71: POLY BAG 40X60 PERFORATED RED PRINT MEYER HESTAN | C71: =_xlfn.TRANSLATE(B71,"it","yue") -> POLY BAG 40X60 穿孔紅色印花 MEYER HESTAN
B72: POLY BAG 40X60 PERFORATED REGENERATED 100% MADE IN | C72: =_xlfn.TRANSLATE(B72,"it","yue") -> POLY BAG 40X60 穿孔再生 100% 製造
B73: POLY BAG 40X80 PERFORATED REGENERATED 100% MADE IN | C73: =_xlfn.TRANSLATE(B73,"it","yue") -> POLY BAG 40X80 穿孔再生 100% 製造
B74: POLY BAG 50X54 PERFORATED RED PRINT MEYER HESTAN | C74: =_xlfn.TRANSLATE(B74,"it","yue") -> POLY BAG 50X54 穿孔紅色印花 MEYER HESTAN
B75: POLY BAG 50X54 PERFORATED REGENERATED 100% MADE IN | C75: =_xlfn.TRANSLATE(B75,"it","yue") -> POLY BAG 50X54 穿孔再生 100% 製造
B76: POLY BAG 50X70 PERFORATED RED PRINT MEYER HESTAN | C76: =_xlfn.TRANSLATE(B76,"it","yue") -> POLY BAG 50X70 PERFORATED RED PRINT MEYER HESTAN
B77: POLY BAG 50X70 PERFORATED REGENERATED 100% MADE IN | C77: =_xlfn.TRANSLATE(B77,"it","yue") -> POLY BAG 50X70 穿孔再生 100% 製造
B78: POLY BAG 60X60 PERFORATED RED PRINT MEYER HESTAN | C78: =_xlfn.TRANSLATE(B78,"it","yue") -> POLY BAG 60X60 PERFORATED RED PRINT MEYER HESTAN
... B89: Punched Bag 45x45 cm Punched on Both Sides | C89: =_xlfn.TRANSLATE(B89,"it","yue") -> 沙袋 45x45 厘米，兩面打孔
A90: BAG- Total | C90: =_xlfn.TRANSLATE(B90,"it","yue")
A91: BHRE | B91: LEAFLET MEHRZER PREMIUM DIA.BLACK IND.56X90 W/WIRE ELASTIC | C91: =_xlfn.TRANSLATE(B91,"it","yue") -> LEAFLET MEHRZER PREMIUM DIA. 黑色 IND.56X90 帶鋼絲
A92: BHRE Total | C92: =_xlfn.TRANSLATE(B92,"it","yue")
A93: BOX- | B93: BOX 0147/027 CM59X25,5X26 | C93: =_xlfn.TRANSLATE(B93,"it","yue") -> BOX 0147/027 CM59X25,5X26
B94: BOX 0195/007 CM48X32,5X27 | C94: =_xlfn.TRANSLATE(B94,"it","yue") -> BOX 0195/007 CM48X32,5X27
B95: BOX 0346/016*CM47X30,5X18 | C95: =_xlfn.TRANSLATE(B95,"it","yue") -> BOX 0346/016*CM47X30,5X18
B96: BOX 0567/000 CM39X38,5X19 | C96: =_xlfn.TRANSLATE(B96,"it","yue") -> BOX 0567/000 CM39X38,5X19
B97: BOX 0696/035*CM39X22,5X11 | C97: =_xlfn.TRANSLATE(B97,"it","yue") -> BOX 0696/035*CM39X22,5X11
B98: BOX 0709/065*CM45X28,5X12 | C98: =_xlfn.TRANSLATE(B98,"it","yue") -> BOX 0709/065*CM45X28,5X12
B99: BOX 1235/162 CM39X22,5X24 | C99: =_xlfn.TRANSLATE(B99,"it","yue") -> BOX 1235/162 CM39X22,5X24
B100: BOX 1235/185 CM39X22,5X24 | C100: =_xlfn.TRANSLATE(B100,"it","yue") -> BOX 1235/185 CM39X22,5X24
B101: BOX 1235/188 CM39X22,5X24 | C101: =_xlfn.TRANSLATE(B101,"it","yue") -> BOX 1235/188 CM39X22,5X24
B102: BOX 1819/000 CM37X26X45 | C102: =_xlfn.TRANSLATE(B102,"it","yue") -> BOX 1819/000 CM37X26X45
B103: BOX 1971/227 CM47X31X24 | C103: =_xlfn.TRANSLATE(B103,"it","yue") -> BOX 1971/227 CM47X31X24
B104: BOX 2745/000 CM26X26X11 | C104: =_xlfn.TRANSLATE(B104,"it","yue") -> BOX 2745/000 CM26X26X11
B105: BOX 3120/000 CM65,0X44,0X28,5 | C105: =_xlfn.TRANSLATE(B105,"it","yue") -> BOX 3120/000 CM65,0X44,0X28,5
... B182: LITHO BOX 7794 NOSTROCHEF 8 PCS E. 3801088000176 | C182: =_xlfn.TRANSLATE(B182,"it","yue") -> 石版盒 7794 NOSTROCHEF 8 PCS E. 3801088000176
A183: BOX- Total | C183: =_xlfn.TRANSLATE(B183,"it","yue")
A184: CBS- | B184: CARDBOARD RING D.100 H.45 TH. 3 MM | C184: =_xlfn.TRANSLATE(B184,"it","yue") -> 紙板戒指 D.100 H.45 TH. 3毫米
B185: Die-cut Divider for Flexo Box 7804-7805 7pc Set | C185: =_xlfn.TRANSLATE(B185,"it","yue") -> Die-cut Divider for Flexo Box 7804-7805 7件套
B186: DIVIDER CARDBOARDCM116X79 T.1 | C186: =_xlfn.TRANSLATE(B186,"it","yue") -> 分隔器CARDBOARDCM116X79 T.1
B187: DIVIDER CARDBOARDCM12X12 T.5 | C187: =_xlfn.TRANSLATE(B187,"it","yue") -> 分隔CARDBOARDCM12X12 T.5
B188: DIVIDER DIE-CUT HOUSING MNC FRYPAN 20 DECO | C188: =_xlfn.TRANSLATE(B188,"it","yue") -> DIVIDER DIE-CUT HOUSING MNC FRYPAN 20 DECO
B189: DIVIDER DIE-CUT HOUSING MNC FRYPAN 24 DECO | C189: =_xlfn.TRANSLATE(B189,"it","yue") -> DIVIDER DIE-CUT HOUSING MNC FRYPAN 24 DECO
B190: DIVIDER DIE-CUT HOUSING MNC FRYPAN 28 DECO | C190: =_xlfn.TRANSLATE(B190,"it","yue") -> DIVIDER DIE-CUT HOUSING MNC FRYPAN 28 DECO
B191: DIVIDER DIE-CUT HOUSING MNC WOK.28 DECO | C191: =_xlfn.TRANSLATE(B191,"it","yue") -> DIVIDER DIE-CUT HOUSING MNC WOK.28 DECO
B192: DIVIDER DIE-CUT SEP.PAN H28/LID X TIMA HOLE Ø 45 mm | C192: =_xlfn.TRANSLATE(B192,"it","yue") -> DIVIDER 模切 9 月 平底鍋 H28/蓋子 X TIMA 孔 Ø 45 毫米
B193: DIVIDER DIE-CUT SINGLE CLAMSHELL X LID AC Ø18Ø20 BOX CAN.7789 | C193: =_xlfn.TRANSLATE(B193,"it","yue") -> DIVIDER DIE-CUT SINGLE CLAMSHELL X LID AC Ø18Ø20 BOX CAN.7789
B194: DIVIDER DIE-CUT SINGLE HOUSING SEPARATOR 125Ø 20+24 BOX CAN.7781 | C194: =_xlfn.TRANSLATE(B194,"it","yue") -> 分隔模切單殼分離器 125Ø 20+24 BOX CAN.7781
B195: DIVIDER DIE-CUT SINGLE HOUSING SEPARATOR 125Ø28/125Ø28+C.BOX CAN.7785 | C195: =_xlfn.TRANSLATE(B195,"it","yue") -> 分隔模切單殼分離器 125Ø28/125Ø28+C.BOX CAN.7785
B196: DIVIDER DIE-CUT SINGLE HOUSING SEPARATOR A FRYPAN 125Ø24- 30 BOX CAN.7789 | C196: =_xlfn.TRANSLATE(B196,"it","yue") -> DIVIDER DIE-CUT SINGLE HOUSING SEPARATOR A FRYPAN 125Ø24- 30 BOX CAN.7789
... B213: STRIP FUS.GLASS LID B.SI.20 038970 | C213: =_xlfn.TRANSLATE(B213,"it","yue") -> 脫煙火。 玻璃蓋 B.SI.20 038970
A214: CBS- Total | C214: =_xlfn.TRANSLATE(B214,"it","yue")
A215: CDM- | B215: 5-Ply Disc SS304/AL/SS439 265mm x 2.7mm Total Thickness 2.7mm [cite: 1] | C215: =_xlfn.TRANSLATE(B215,"it","yue") -> 5 層圓盤 SS304/AL/SS439 265mm x 2.7mm 總厚度 2.7mm [引用：1]
B216: 5-Ply Disc SS304/AL/SS439 300mm x 2.3mm Total Thickness 2.3mm [cite: 1] | C216: =_xlfn.TRANSLATE(B216,"it","yue") -> 5 層圓盤 SS304/AL/SS439 300mm x 2.3mm 總厚度 2.3mm [引用：1]
B217: 5-Ply Disc SS304/AL/SS439 335mm x 2.7mm Total Thickness 2.7mm [cite: 1] | C217: =_xlfn.TRANSLATE(B217,"it","yue") -> 5-Ply Disc SS304/AL/SS439 335mm x 2.7mm 總厚度 2.7mm [引用：1]
B218: 5-Ply Disc SS304/AL/SS439 365mm x 2.3mm Total Thickness 2.3mm [cite: 1] | C218: =_xlfn.TRANSLATE(B218,"it","yue") -> 5 層圓盤 SS304/AL/SS439 365mm x 2.3mm 總厚度 2.3mm [引用：1]
B219: 5-Ply Disc SS304/AL/SS439 375mm x 2.3mm Total Thickness 2.3mm [cite: 1] | C219: =_xlfn.TRANSLATE(B219,"it","yue") -> 5-Ply Disc SS304/AL/SS439 375mm x 2.3mm 總厚度2.3mm [引用：1]
B220: 5-Ply Disc SS304/AL/SS439 380mm x 2.3mm Total Thickness 2.3mm [cite: 1] | C220: =_xlfn.TRANSLATE(B220,"it","yue") -> 5 層圓盤 SS304/AL/SS439 380mm x 2.3mm 總厚度 2.3mm [引用：1]
B221: 5-Ply Disc SS304/AL/SS439 385mm x 2.7mm Total Thickness 2.7mm [cite: 1] | C221: =_xlfn.TRANSLATE(B221,"it","yue") -> 5-Ply Disc SS304/AL/SS439 385mm x 2.7mm 總厚度 2.7mm [引用：1]
B222: 5-Ply Disc SS304/AL/SS439 470mm x 2.3mm Total Thickness 2.3mm [cite: 1] | C222: =_xlfn.TRANSLATE(B222,"it","yue") -> 5 層圓盤 SS304/AL/SS439 470mm x 2.3mm 總厚度 2.3mm [引用：1]
A223: CDM- Total | C223: =_xlfn.TRANSLATE(B223,"it","yue")
A224: FILM | B224: Punched Strip 120x80 cm | C224: =_xlfn.TRANSLATE(B224,"it","yue") -> 打孔條 120x80 厘米
B225: REEL PLT1 POLY THERMO FLAT MM800X750 MT 35 MY NO LOGO | C225: =_xlfn.TRANSLATE(B225,"it","yue") -> REEL PLT1 POLY THERMO FLAT MM800X750 MT 35 MY NO LOGO
B226: Stretch Film Roll Height 50cm Pre-stretched | C226: =_xlfn.TRANSLATE(B226,"it","yue") -> 拉伸膜卷高50厘米預拉伸
B227: STRISCIA BOCC. 75x60 BOLLA MAXI D.25 | C227: =_xlfn.TRANSLATE(B227,"it","yue") -> STRISCIA BOCC。 75x60 MAXI BUBBLE D.25
A228: FILM Total | C228: =_xlfn.TRANSLATE(B228,"it","yue")
A229: FLAN | B229: FERRULE AR 0400 18/24 R60 F90 A 0° | C229: =_xlfn.TRANSLATE(B229,"it","yue") -> 套圈 AR 0400 18/24 R60 F90 A 0°
B230: FERRULE L1500 12/26 R34 F60 A-8° | C230: =_xlfn.TRANSLATE(B230,"it","yue") -> 套圈 L1500 12/26 R34 F60 A-8°
B231: FERRULE L1500 16/17 R999 F75 A 0° | C231: =_xlfn.TRANSLATE(B231,"it","yue") -> 套圈 L1500 16/17 R999 F75 A 0°
B232: FERRULE P3600 15/20 FR.100 C36/334 | C232: =_xlfn.TRANSLATE(B232,"it","yue") -> 套圈 P3600 15/20 FR.100 C36/334
A233: FLAN Total | C233: =_xlfn.TRANSLATE(B233,"it","yue")
A234: GLID | B234: Glass Lid 18cm SS304 Rim with Steam Vent Type AGlass Lid | C234: =_xlfn.TRANSLATE(B234,"it","yue") -> 玻璃蓋 18cm SS304 輪圈連蒸汽通風口型 AGlass 蓋
B235: Glass Lid 20cm Flat Rim Silicone Steam Vent StandardGlass Lid | C235: =_xlfn.TRANSLATE(B235,"it","yue") -> Glass Lid 20cm Flat Rim Silicone Steam Vent StandardGlass Lid
B236: Glass Lid 20cm SS304 Rim with Steam Vent Type AGlass Lid | C236: =_xlfn.TRANSLATE(B236,"it","yue") -> 玻璃蓋 20cm SS304 輪圈連蒸汽通風口型 AGlass 蓋
B237: Glass Lid 24cm Flat Rim Silicone Steam Vent StandardGlass Lid | C237: =_xlfn.TRANSLATE(B237,"it","yue") -> 玻璃蓋 24cm 平邊矽膠蒸汽通風口標準玻璃蓋
B238: Glass Lid 24cm SS304 Rim with Steam Vent Type AGlass Lid | C238: =_xlfn.TRANSLATE(B238,"it","yue") -> 玻璃蓋 24cm SS304 輪圈連蒸汽通風口 AGlass 蓋
B239: Glass Lid 26cm SS304 Rim with Steam Vent Type AGlass Lid | C239: =_xlfn.TRANSLATE(B239,"it","yue") -> 玻璃蓋 26cm SS304 輪圈連蒸汽通風口型 AGlass 蓋
B240: Glass Lid 28cm Flat Rim Silicone Steam Vent StandardGlass Lid | C240: =_xlfn.TRANSLATE(B240,"it","yue") -> 玻璃蓋 28cm 平邊矽膠蒸氣通風口標準玻璃蓋
B241: Glass Lid 28cm SS304 Rim with Steam Vent Type AGlass Lid | C241: =_xlfn.TRANSLATE(B241,"it","yue") -> 玻璃蓋 28cm SS304 輪圈連蒸汽通風口型 AGlass 蓋
B242: Glass Lid 30cm SS304 Rim with Steam Vent Type AGlass Lid | C242: =_xlfn.TRANSLATE(B242,"it","yue") -> 玻璃蓋 30cm SS304 輪圈連蒸汽通風口型 AGlass 蓋
B243: Glass Lid 32cm Flat Rim Silicone Steam Vent StandardGlass Lid | C243: =_xlfn.TRANSLATE(B243,"it","yue") -> 玻璃蓋 32cm 平邊矽膠蒸氣通風口標準玻璃蓋
B244: Glass Lid Borosilicate Low Profile 24cmGlass Lid | C244: =_xlfn.TRANSLATE(B244,"it","yue") -> 玻璃蓋硼矽酸鹽薄型24cm玻璃蓋
B245: Glass Lid Borosilicate Low Profile 28cmGlass Lid | C245: =_xlfn.TRANSLATE(B245,"it","yue") -> 玻璃蓋硼矽酸鹽薄型28厘米玻璃蓋
A246: GLID Total | C246: =_xlfn.TRANSLATE(B246,"it","yue")
A247: HDL- | B247: 1-5 SI Handle 16cm Saucepan (6.5mm hole) | C247: =_xlfn.TRANSLATE(B247,"it","yue") -> 1-5 SI 手柄 16 厘米平底鍋 （6.5 毫米孔）
B248: 1-5 SI Handle 20cm Saucepan (6.5mm hole) | C248: =_xlfn.TRANSLATE(B248,"it","yue") -> 1-5 SI 手柄 20 厘米平底鍋 （6.5 毫米孔）
B249: 1-5 SI Handle 20cm Skillet (6.5mm hole) | C249: =_xlfn.TRANSLATE(B249,"it","yue") -> 1-5 SI 手柄 20 厘米平底鍋 （6.5 毫米孔）
B250: 1-5 SI Handle 24cm Saucier (6.5mm hole) | C250: =_xlfn.TRANSLATE(B250,"it","yue") -> 1-5 SI 手柄 24cm Saucier （6.5mm 孔）
B251: 1-5 SI Handle 26cm Saute (6.5mm hole) | C251: =_xlfn.TRANSLATE(B251,"it","yue") -> 1-5 SI 手柄 26cm 炒 （6.5mm 孔）
...

Sheet Sheet1
A3: Row Labels | B3: Sum of Quantity | C3: Count of Quantity2
A4: Jan | B4: 1615590.4 | C4: 339
A5: Feb | B5: 1904686.6 | C5: 264
A6: Grand Total | B6: 3520277 | C6: 603

Sheet TVS order 28022026
A1: Purchase Order Number | B1: Purchase Order Date | C1: Purchase order issue date | D1: Vendor ID | E1: VendorName | F1: Vendor_Invoice_No | G1: Invoice Date | H1: REF_NO | I1: Item Code | J1: Part Description | K1: Commodity Italian | L1: Commodity English | M1: Division | N1: Quantity | O1: Unit | P1: PO_Price_PO CUR | Q1: PO UNIT PRICE PO_CUR | R1: Total_PO_Price_PO CUR | S1: Translated Part Description (English) | T1: Unified Commodity Code
A2: OF0040028 | B2: 45635.7 | D2: F600456 | E2: ALMESAN ALUMINYUM SAN.VE TIC. A.S | F2: 26AFF000045 | G2: 46081 | I2: 000040235029R | J2: DISCO AL.4006 235/29 RIC | K2: alluminio | L2: =VLOOKUP(K2,'COMM ITY- ENG'!A:B,2,FALSE) -> aluminium | N2: 1006 | O2: kg | Q2: =+R2/N2 -> 3.455 | R2: 3475.73 | S2: =IFERROR(VLOOKUP(J2,'DESC ITY - ENG'!B:C,2,FALSE),VLOOKUP(I2,'DESC ITY - ENG'!A:C,3,FALSE)) -> Aluminum Disc Alloy 4006 235mm x 2.9mm Replacement Part [cite: 1] | T2: =VLOOKUP(S2,'DESC ITY - ENG'!C:D,2,FALSE) -> ALM- | U2: =_xlfn.TRANSLATE(S2,"en","zh-cht") -> 鋁製圓盤合金 4006 235mm x 2.9mm 替換零件 [引用：1] | V2: =VLOOKUP(T2,'STANDARD COMM'!A:D,3,FALSE) -> Metal | W2: =_xlfn.TRANSLATE(O2,"it","en") -> kg
A3: OF0040028 | B3: 45635.7 | D3: F600456 | E3: ALMESAN ALUMINYUM SAN.VE TIC. A.S | F3: 26AFF000045 | G3: 46081 | I3: 000040265029R | J3: DISCO AL.4006 265/29 RIC | K3: alluminio | L3: =VLOOKUP(K3,'COMM ITY- ENG'!A:B,2,FALSE) -> aluminium | N3: 1050 | O3: kg | Q3: =+R3/N3 -> 3.455 | R3: 3627.75 | S3: =IFERROR(VLOOKUP(J3,'DESC ITY - ENG'!B:C,2,FALSE),VLOOKUP(I3,'DESC ITY - ENG'!A:C,3,FALSE)) -> Aluminum Disc Alloy 4006 265mm x 2.9mm Replacement Part [cite: 2] | T3: =VLOOKUP(S3,'DESC ITY - ENG'!C:D,2,FALSE) -> ALM- | U3: =_xlfn.TRANSLATE(S3,"en","zh-cht") -> 鋁製圓盤合金 4006 265mm x 2.9mm 替換零件 [引用：2] | V3: =VLOOKUP(T3,'STANDARD COMM'!A:D,3,FALSE) -> Metal | W3: =_xlfn.TRANSLATE(O3,"it","en") -> kg
A4: OF0040028 | B4: 45635.7 | D4: F600456 | E4: ALMESAN ALUMINYUM SAN.VE TIC. A.S | F4: 26AFF000045 | G4: 46081 | I4: 000040265032R | J4: DISCO AL.4006 265/32 RIC | K4: alluminio | L4: =VLOOKUP(K4,'COMM ITY- ENG'!A:B,2,FALSE) -> aluminium | N4: 3050 | O4: kg | Q4: =+R4/N4 -> 3.455 | R4: 10537.75 | S4: =IFERROR(VLOOKUP(J4,'DESC ITY - ENG'!B:C,2,FALSE),VLOOKUP(I4,'DESC ITY - ENG'!A:C,3,FALSE)) -> Aluminum Disc Alloy 4006 265mm x 3.2mm Replacement Part [cite: 2] | T4: =VLOOKUP(S4,'DESC ITY - ENG'!C:D,2,FALSE) -> ALM- | U4: =_xlfn.TRANSLATE(S4,"en","zh-cht") -> 鋁碟合金 4006 265mm x 3.2mm 替換零件 [引用：2] | V4: =VLOOKUP(T4,'STANDARD COMM'!A:D,3,FALSE) -> Metal | W4: =_xlfn.TRANSLATE(O4,"it","en") -> kg
A5: OF0040028 | B5: 45670.414 | D5: F600456 | E5: ALMESAN ALUMINYUM SAN.VE TIC. A.S | F5: 26AFF000045 | G5: 46081 | I5: 000040300029R | J5: DISCO AL.4006 300/29 RIC | K5: alluminio | L5: =VLOOKUP(K5,'COMM ITY- ENG'!A:B,2,FALSE) -> aluminium | N5: 3050 | O5: kg | Q5: =+R5/N5 -> 3.455 | R5: 10537.75 | S5: =IFERROR(VLOOKUP(J5,'DESC ITY - ENG'!B:C,2,FALSE),VLOOKUP(I5,'DESC ITY - ENG'!A:C,3,FALSE)) -> Aluminum Disc Alloy 4006 300mm x 2.9mm Replacement Part [cite: 2] | T5: =VLOOKUP(S5,'DESC ITY - ENG'!C:D,2,FALSE) -> ALM- | U5: =_xlfn.TRANSLATE(S5,"en","zh-cht") -> 鋁製圓盤合金 4006 300mm x 2.9mm 替換零件 [引用：2] | V5: =VLOOKUP(T5,'STANDARD COMM'!A:D,3,FALSE) -> Metal | W5: =_xlfn.TRANSLATE(O5,"it","en") -> kg
A6: OF0040028 | B6: 45642.711 | D6: F600456 | E6: ALMESAN ALUMINYUM SAN.VE TIC. A.S | F6: 26AFF000045 | G6: 46081 | I6: 000040325036R | J6: DISCO AL.4006 325/36 RIC | K6: alluminio | L6: =VLOOKUP(K6,'COMM ITY- ENG'!A:B,2,FALSE) -> aluminium | N6: 2100 | O6: kg | Q6: =+R6/N6 -> 3.455 | R6: 7255.5 | S6: =IFERROR(VLOOKUP(J6,'DESC ITY - ENG'!B:C,2,FALSE),VLOOKUP(I6,'DESC ITY - ENG'!A:C,3,FALSE)) -> Aluminum Disc Alloy 4006 325mm x 3.6mm Replacement Part [cite: 2] | T6: =VLOOKUP(S6,'DESC ITY - ENG'!C:D,2,FALSE) -> ALM- | U6: =_xlfn.TRANSLATE(S6,"en","zh-cht") -> 鋁碟合金 4006 325mm x 3.6mm 替換零件 [引用：2] | V6: =VLOOKUP(T6,'STANDARD COMM'!A:D,3,FALSE) -> Metal | W6: =_xlfn.TRANSLATE(O6,"it","en") -> kg
A7: OF0040028 | B7: 45629.658 | D7: F600456 | E7: ALMESAN ALUMINYUM SAN.VE TIC. A.S | F7: 26AFF000045 | G7: 46081 | I7: 000040335024R | J7: DISCO AL.4006 335/24 RIC | K7: alluminio | L7: =VLOOKUP(K7,'COMM ITY- ENG'!A:B,2,FALSE) -> aluminium | N7: 6100 | O7: kg | Q7: =+R7/N7 -> 3.455 | R7: 21075.5 | S7: =IFERROR(VLOOKUP(J7,'DESC ITY - ENG'!B:C,2,FALSE),VLOOKUP(I7,'DESC ITY - ENG'!A:C,3,FALSE)) -> Aluminum Disc Alloy 4006 335mm x 2.4mm Replacement Part [cite: 2] | T7: =VLOOKUP(S7,'DESC ITY - ENG'!C:D,2,FALSE) -> ALM- | U7: =_xlfn.TRANSLATE(S7,"en","zh-cht") -> 鋁製圓盤合金 4006 335mm x 2.4mm 替換零件 [引用：2] | V7: =VLOOKUP(T7,'STANDARD COMM'!A:D,3,FALSE) -> Metal | W7: =_xlfn.TRANSLATE(O7,"it","en") -> kg
A8: OF0040028 | B8: 45629.658 | D8: F600456 | E8: ALMESAN ALUMINYUM SAN.VE TIC. A.S | F8: 26AFF000045 | G8: 46081 | I8: 000040335029R | J8: DISCO AL.4006 335/29 RIC | K8: alluminio | L8: =VLOOKUP(K8,'COMM ITY- ENG'!A:B,2,FALSE) -> aluminium | N8: 950 | O8: kg | Q8: =+R8/N8 -> 3.455 | R8: 3282.25 | S8: =IFERROR(VLOOKUP(J8,'DESC ITY - ENG'!B:C,2,FALSE),VLOOKUP(I8,'DESC ITY - ENG'!A:C,3,FALSE)) -> Aluminum Disc Alloy 4006 335mm x 2.9mm Replacement Part [cite: 2] | T8: =VLOOKUP(S8,'DESC ITY - ENG'!C:D,2,FALSE) -> ALM- | U8: =_xlfn.TRANSLATE(S8,"en","zh-cht") -> 鋁製圓盤合金 4006 335mm x 2.9mm 替換零件 [引用：2] | V8: =VLOOKUP(T8,'STANDARD COMM'!A:D,3,FALSE) -> Metal | W8: =_xlfn.TRANSLATE(O8,"it","en") -> kg
A9: OF0040028 | B9: 45642.711 | D9: F600456 | E9: ALMESAN ALUMINYUM SAN.VE TIC. A.S | F9: 26AFF000045 | G9: 46081 | I9: 000040335032R | J9: DISCO AL.4006 335/32 RIC | K9: alluminio | L9: =VLOOKUP(K9,'COMM ITY- ENG'!A:B,2,FALSE) -> aluminium | N9: 1550 | O9: kg | Q9: =+R9/N9 -> 3.455 | R9: 5355.25 | S9: =IFERROR(VLOOKUP(J9,'DESC ITY - ENG'!B:C,2,FALSE),VLOOKUP(I9,'DESC ITY - ENG'!A:C,3,FALSE)) -> Aluminum Disc Alloy 4006 335mm x 3.2mm Replacement Part [cite: 2] | T9: =VLOOKUP(S9,'DESC ITY - ENG'!C:D,2,FALSE) -> ALM- | U9: =_xlfn.TRANSLATE(S9,"en","zh-cht") -> 鋁製圓盤合金 4006 335mm x 3.2mm 替換零件 [引用：2] | V9: =VLOOKUP(T9,'STANDARD COMM'!A:D,3,FALSE) -> Metal | W9: =_xlfn.TRANSLATE(O9,"it","en") -> kg
A10: OF0040028 | B10: 45607.417 | D10: F600456 | E10: ALMESAN ALUMINYUM SAN.VE TIC. A.S | F10: 26AFF000045 | G10: 46081 | I10: 000040355032R | J10: DISCO AL.4006 355/32 RIC | K10: alluminio | L10: =VLOOKUP(K10,'COMM ITY- ENG'!A:B,2,FALSE) -> aluminium | N10: 1526 | O10: kg | Q10: =+R10/N10 -> 3.455 | R10: 5272.33 | S10: =IFERROR(VLOOKUP(J10,'DESC ITY - ENG'!B:C,2,FALSE),VLOOKUP(I10,'DESC ITY - ENG'!A:C,3,FALSE)) -> Aluminum Disc Alloy 4006 355mm x 3.2mm Replacement Part [cite: 2] | T10: =VLOOKUP(S10,'DESC ITY - ENG'!C:D,2,FALSE) -> ALM- | U10: =_xlfn.TRANSLATE(S10,"en","zh-cht") -> 鋁製圓盤合金 4006 355mm x 3.2mm 替換零件 [引用：2] | V10: =VLOOKUP(T10,'STANDARD COMM'!A:D,3,FALSE) -> Metal | W10: =_xlfn.TRANSLATE(O10,"it","en") -> kg
A11: OF0040028 | B11: 45624.677 | D11: F600456 | E11: ALMESAN ALUMINYUM SAN.VE TIC. A.S | F11: 26AFF000045 | G11: 46081 | I11: 000040355036R | J11: DISCO AL.4006 355/36 RIC | K11: alluminio | L11: =VLOOKUP(K11,'COMM ITY- ENG'!A:B,2,FALSE) -> aluminium | N11: 2016 | O11: kg | Q11: =+R11/N11 -> 3.455 | R11: 6965.28 | S11: =IFERROR(VLOOKUP(J11,'DESC ITY - ENG'!B:C,2,FALSE),VLOOKUP(I11,'DESC ITY - ENG'!A:C,3,FALSE)) -> Aluminum Disc Alloy 4006 355mm x 3.6mm Replacement Part [cite: 2] | T11: =VLOOKUP(S11,'DESC ITY - ENG'!C:D,2,FALSE) -> ALM- | U11: =_xlfn.TRANSLATE(S11,"en","zh-cht") -> 鋁製圓盤合金 4006 355mm x 3.6mm 替換零件 [引用：2] | V11: =VLOOKUP(T11,'STANDARD COMM'!A:D,3,FALSE) -> Metal | W11: =_xlfn.TRANSLATE(O11,"it","en") -> kg
A12: OF0040028 | B12: 45642.711 | D12: F600456 | E12: ALMESAN ALUMINYUM SAN.VE TIC. A.S | F12: 26AFF000045 | G12: 46081 | I12: 000040370036R | J12: DISCO AL.4006 370/36 RIC | K12: alluminio | L12: =VLOOKUP(K12,'COMM ITY- ENG'!A:B,2,FALSE) -> aluminium | N12: 1550 | O12: kg | Q12: =+R12/N12 -> 3.455 | R12: 5355.25 | S12: =IFERROR(VLOOKUP(J12,'DESC ITY - ENG'!B:C,2,FALSE),VLOOKUP(I12,'DESC ITY - ENG'!A:C,3,FALSE)) -> Aluminum Disc Alloy 4006 370mm x 3.6mm Replacement Part [cite: 2] | T12: =VLOOKUP(S12,'DESC ITY - ENG'!C:D,2,FALSE) -> ALM- | U12: =_xlfn.TRANSLATE(S12,"en","zh-cht") -> 鋁製圓盤合金 4006 370mm x 3.6mm 替換零件 [引用：2] | V12: =VLOOKUP(T12,'STANDARD COMM'!A:D,3,FALSE) -> Metal | W12: =_xlfn.TRANSLATE(O12,"it","en") -> kg
A13: OF0040028 | B13: 45629.658 | D13: F600456 | E13: ALMESAN ALUMINYUM SAN.VE TIC. A.S | F13: 26AFF000045 | G13: 46081 | I13: 000040385036R | J13: DISCO AL.4006 385/36 RIC | K13: alluminio | L13: =VLOOKUP(K13,'COMM ITY- ENG'!A:B,2,FALSE) -> aluminium | N13: 1550 | O13: kg | Q13: =+R13/N13 -> 3.455 | R13: 5355.25 | S13: =IFERROR(VLOOKUP(J13,'DESC ITY - ENG'!B:C,2,FALSE),VLOOKUP(I13,'DESC ITY - ENG'!A:C,3,FALSE)) -> Aluminum Disc Alloy 4006 385mm x 3.6mm Replacement Part [cite: 2] | T13: =VLOOKUP(S13,'DESC ITY - ENG'!C:D,2,FALSE) -> ALM- | U13: =_xlfn.TRANSLATE(S13,"en","zh-cht") -> 鋁製圓盤合金 4006 385mm x 3.6mm 替換零件 [引用：2] | V13: =VLOOKUP(T13,'STANDARD COMM'!A:D,3,FALSE) -> Metal | W13: =_xlfn.TRANSLATE(O13,"it","en") -> kg
... A72: OF0039875 | B72: 45632.698 | D72: F600780 | E72: GULBAK BAKALIT METAL VE TEKSTIL SAN. ve TIC. LTD. STI | F72: 26AFF000056 | G72: 46081 | I72: 000281710001 | J72: MANICO AC.SOLE CORTO C/LOGO MC AISI 430 SABBIATO PAD.279 20 | K72: manigliame | L72: =VLOOKUP(K72,'COMM ITY- ENG'!A:B,2,FALSE) -> handles | N72: 5000 | O72: NR | Q72: =+R72/N72 -> 1.137 | R72: 5685 | S72: =IFERROR(VLOOKUP(J72,'DESC ITY - ENG'!B:C,2,FALSE),VLOOKUP(I72,'DESC ITY - ENG'!A:C,3,FALSE)) -> Steel Handle AC.SOLE Short w/Logo MC AISI 430 Pan 279-20 Sandblasted [cite: 4] | T72: =VLOOKUP(S72,'DESC ITY - ENG'!C:D,2,FALSE) -> SHDL | U72: =_xlfn.TRANSLATE(S72,"en","zh-cht") -> 鋼柄冷氣。鞋底短管附標誌 MC AISI 430 Pan 279-20 噴砂處理 [引用：4] | V72: =VLOOKUP(T72,'STANDARD COMM'!A:D,3,FALSE) -> Fittings | W72: =_xlfn.TRANSLATE(O72,"it","en") -> NR
B73: 45645.653 | D73: F600780 | E73: GULBAK BAKALIT METAL VE TEKSTIL SAN. ve TIC. LTD. STI | F73: 26AFF000056 | G73: 46081 | I73: 000281710001 | J73: MANICO AC.SOLE CORTO C/LOGO MC AISI 430 SABBIATO PAD.279 20 | K73: manigliame | L73: =VLOOKUP(K73,'COMM ITY- ENG'!A:B,2,FALSE) -> handles | N73: 2000 | O73: NR | Q73: =+R73/N73 -> 1.137 | R73: 2274 | S73: =IFERROR(VLOOKUP(J73,'DESC ITY - ENG'!B:C,2,FALSE),VLOOKUP(I73,'DESC ITY - ENG'!A:C,3,FALSE)) -> Steel Handle AC.SOLE Short w/Logo MC AISI 430 Pan 279-20 Sandblasted [cite: 4] | T73: =VLOOKUP(S73,'DESC ITY - ENG'!C:D,2,FALSE) -> SHDL | U73: =_xlfn.TRANSLATE(S73,"en","zh-cht") -> 鋼柄冷氣。鞋底短管附標誌 MC AISI 430 Pan 279-20 噴砂處理 [引用：4] | V73: =VLOOKUP(T73,'STANDARD COMM'!A:D,3,FALSE) -> Fittings | W73: =_xlfn.TRANSLATE(O73,"it","en") -> NR
A74: OF0039875 | B74: 45667.611 | D74: F600780 | E74: GULBAK BAKALIT METAL VE TEKSTIL SAN. ve TIC. LTD. STI | F74: 26AFF000056 | G74: 46081 | I74: 000281710003 | J74: MANICO AC.SOLE CORTO C/LOGO MC AISI 430 SABBIATO CAS.433 16 | K74: manigliame | L74: =VLOOKUP(K74,'COMM ITY- ENG'!A:B,2,FALSE) -> handles | N74: 10000 | O74: NR | Q74: =+R74/N74 -> 1.137 | R74: 11370 | S74: =IFERROR(VLOOKUP(J74,'DESC ITY - ENG'!B:C,2,FALSE),VLOOKUP(I74,'DESC ITY - ENG'!A:C,3,FALSE)) -> Steel Handle AC.SOLE Short w/Logo MC AISI 430 Casserole 433-16 Sandblasted [cite: 4] | T74: =VLOOKUP(S74,'DESC ITY - ENG'!C:D,2,FALSE) -> SHDL | U74: =_xlfn.TRANSLATE(S74,"en","zh-cht") -> 鋼柄冷氣。獨角短褲附標誌 MC AISI 430 砂鍋 433-16 砂磨 [引用：4] | V74: =VLOOKUP(T74,'STANDARD COMM'!A:D,3,FALSE) -> Fittings | W74: =_xlfn.TRANSLATE(O74,"it","en") -> NR
B75: 45635.558 | D75: F600780 | E75: GULBAK BAKALIT METAL VE TEKSTIL SAN. ve TIC. LTD. STI | F75: 26AFF000056 | G75: 46081 | I75: 000281710003 | J75: MANICO AC.SOLE CORTO C/LOGO MC AISI 430 SABBIATO CAS.433 16 | K75: manigliame | L75: =VLOOKUP(K75,'COMM ITY- ENG'!A:B,2,FALSE) -> handles | N75: 6000 | O75: NR | Q75: =+R75/N75 -> 1.137 | R75: 6822 | S75: =IFERROR(VLOOKUP(J75,'DESC ITY - ENG'!B:C,2,FALSE),VLOOKUP(I75,'DESC ITY - ENG'!A:C,3,FALSE)) -> Steel Handle AC.SOLE Short w/Logo MC AISI 430 Casserole 433-16 Sandblasted [cite: 4] | T75: =VLOOKUP(S75,'DESC ITY - ENG'!C:D,2,FALSE) -> SHDL | U75: =_xlfn.TRANSLATE(S75,"en","zh-cht") -> 鋼柄冷氣。獨角短褲附標誌 MC AISI 430 砂鍋 433-16 砂磨 [引用：4] | V75: =VLOOKUP(T75,'STANDARD COMM'!A:D,3,FALSE) -> Fittings | W75: =_xlfn.TRANSLATE(O75,"it","en") -> NR
A76: OF0039875 | B76: 45635.558 | D76: F600780 | E76: GULBAK BAKALIT METAL VE TEKSTIL SAN. ve TIC. LTD. STI | F76: 26AFF000056 | G76: 46081 | I76: 000281710005 | J76: MANICO AC.SOLE LUNGO C/LOGO MC AISI 430 SABBIATO PAD.279 30 | K76: manigliame | L76: =VLOOKUP(K76,'COMM ITY- ENG'!A:B,2,FALSE) -> handles | N76: 20000 | O76: NR | Q76: =+R76/N76 -> 1.227 | R76: 24540 | S76: =IFERROR(VLOOKUP(J76,'DESC ITY - ENG'!B:C,2,FALSE),VLOOKUP(I76,'DESC ITY - ENG'!A:C,3,FALSE)) -> Steel Handle AC.SOLE Long w/Logo MC AISI 430 Pan 279-30 Sandblasted [cite: 4] | T76: =VLOOKUP(S76,'DESC ITY - ENG'!C:D,2,FALSE) -> HDL- | U76: =_xlfn.TRANSLATE(S76,"en","zh-cht") -> 鋼柄冷氣。鞋底長款，附 MC 標誌 AISI 430 Pan 279-30 噴砂處理 [引用：4] | V76: =VLOOKUP(T76,'STANDARD COMM'!A:D,3,FALSE) -> Fittings | W76: =_xlfn.TRANSLATE(O76,"it","en") -> NR
B77: 45666.665 | D77: F600780 | E77: GULBAK BAKALIT METAL VE TEKSTIL SAN. ve TIC. LTD. STI | F77: 26AFF000056 | G77: 46081 | I77: 000281710005 | J77: MANICO AC.SOLE LUNGO C/LOGO MC AISI 430 SABBIATO PAD.279 30 | K77: manigliame | L77: =VLOOKUP(K77,'COMM ITY- ENG'!A:B,2,FALSE) -> handles | N77: 15000 | O77: NR | Q77: =+R77/N77 -> 1.227 | R77: 18405 | S77: =IFERROR(VLOOKUP(J77,'DESC ITY - ENG'!B:C,2,FALSE),VLOOKUP(I77,'DESC ITY - ENG'!A:C,3,FALSE)) -> Steel Handle AC.SOLE Long w/Logo MC AISI 430 Pan 279-30 Sandblasted [cite: 4] | T77: =VLOOKUP(S77,'DESC ITY - ENG'!C:D,2,FALSE) -> HDL- | U77: =_xlfn.TRANSLATE(S77,"en","zh-cht") -> 鋼柄冷氣。鞋底長款，附 MC 標誌 AISI 430 Pan 279-30 噴砂處理 [引用：4] | V77: =VLOOKUP(T77,'STANDARD COMM'!A:D,3,FALSE) -> Fittings | W77: =_xlfn.TRANSLATE(O77,"it","en") -> NR
A78: OF0039114 | B78: 45674.484 | D78: F506075 | E78: HEBEI BOZHENG GLASSWORK CO.LTD. | F78: 26AFF000036 | G78: 46081 | I78: 000700042002 | J78: COP.VET.20 PIAT.BOR./SF.VAP.SIL.STD | K78: accessori finiti | L78: =VLOOKUP(K78,'COMM ITY- ENG'!A:B,2,FALSE) -> finished accessories | N78: 4020 | O78: NR | Q78: =+R78/N78 -> 0.88849254 | R78: 3571.74 | S78: =IFERROR(VLOOKUP(J78,'DESC ITY - ENG'!B:C,2,FALSE),VLOOKUP(I78,'DESC ITY - ENG'!A:C,3,FALSE)) -> Glass Lid 20cm Flat Rim Silicone Steam Vent StandardGlass Lid | T78: =VLOOKUP(S78,'DESC ITY - ENG'!C:D,2,FALSE) -> GLID | U78: =_xlfn.TRANSLATE(S78,"en","zh-cht") -> 玻璃蓋 20公分平緣矽膠蒸汽通風口 標準玻璃蓋 | V78: =VLOOKUP(T78,'STANDARD COMM'!A:D,3,FALSE) -> Lid | W78: =_xlfn.TRANSLATE(O78,"it","en") -> NR
A79: OF0039114 | B79: 45667.693 | D79: F506075 | E79: HEBEI BOZHENG GLASSWORK CO.LTD. | F79: 26AFF000036 | G79: 46081 | I79: 000700044002 | J79: COP.VET.24 PIAT.BOR./SF.VAP.SIL.STD | K79: accessori finiti | L79: =VLOOKUP(K79,'COMM ITY- ENG'!A:B,2,FALSE) -> finished accessories | N79: 3000 | O79: NR | Q79: =+R79/N79 -> 1.0316033 | R79: 3094.81 | S79: =IFERROR(VLOOKUP(J79,'DESC ITY - ENG'!B:C,2,FALSE),VLOOKUP(I79,'DESC ITY - ENG'!A:C,3,FALSE)) -> Glass Lid 24cm Flat Rim Silicone Steam Vent StandardGlass Lid | T79: =VLOOKUP(S79,'DESC ITY - ENG'!C:D,2,FALSE) -> GLID | U79: =_xlfn.TRANSLATE(S79,"en","zh-cht") -> 玻璃蓋 24公分平緣矽膠蒸汽排氣口 標準玻璃蓋 | V79: =VLOOKUP(T79,'STANDARD COMM'!A:D,3,FALSE) -> Lid | W79: =_xlfn.TRANSLATE(O79,"it","en") -> NR
A80: OF0039114 | B80: 45667.693 | D80: F506075 | E80: HEBEI BOZHENG GLASSWORK CO.LTD. | F80: 26AFF000036 | G80: 46081 | I80: 000700046002 | J80: COP.VET.28 PIAT.BOR./SF.VAP.SIL.STD | K80: accessori finiti | L80: =VLOOKUP(K80,'COMM ITY- ENG'!A:B,2,FALSE) -> finished accessories | N80: 3000 | O80: NR | Q80: =+R80/N80 -> 1.1772733 | R80: 3531.82 | S80: =IFERROR(VLOOKUP(J80,'DESC ITY - ENG'!B:C,2,FALSE),VLOOKUP(I80,'DESC ITY - ENG'!A:C,3,FALSE)) -> Glass Lid 28cm Flat Rim Silicone Steam Vent StandardGlass Lid | T80: =VLOOKUP(S80,'DESC ITY - ENG'!C:D,2,FALSE) -> GLID | U80: =_xlfn.TRANSLATE(S80,"en","zh-cht") -> 玻璃蓋 28公分平緣矽膠蒸汽通風口 標準玻璃蓋 | V80: =VLOOKUP(T80,'STANDARD COMM'!A:D,3,FALSE) -> Lid | W80: =_xlfn.TRANSLATE(O80,"it","en") -> NR
A81: OF0039114 | B81: 45629.658 | D81: F506075 | E81: HEBEI BOZHENG GLASSWORK CO.LTD. | F81: 26AFF000036 | G81: 46081 | I81: 000700050002 | J81: COP.VET.32 PIAT.BOR./SF.VAP.SIL.STD | K81: accessori finiti | L81: =VLOOKUP(K81,'COMM ITY- ENG'!A:B,2,FALSE) -> finished accessories | N81: 1005 | O81: NR | Q81: =+R81/N81 -> 1.396209 | R81: 1403.19 | S81: =IFERROR(VLOOKUP(J81,'DESC ITY - ENG'!B:C,2,FALSE),VLOOKUP(I81,'DESC ITY - ENG'!A:C,3,FALSE)) -> Glass Lid 32cm Flat Rim Silicone Steam Vent StandardGlass Lid | T81: =VLOOKUP(S81,'DESC ITY - ENG'!C:D,2,FALSE) -> GLID | U81: =_xlfn.TRANSLATE(S81,"en","zh-cht") -> 玻璃蓋 32公分平緣矽膠蒸汽通風口 標準玻璃蓋 | V81: =VLOOKUP(T81,'STANDARD COMM'!A:D,3,FALSE) -> Lid | W81: =_xlfn.TRANSLATE(O81,"it","en") -> NR
A82: OF0039114 | B82: 45642.711 | D82: F506075 | E82: HEBEI BOZHENG GLASSWORK CO.LTD. | F82: 26AFF000036 | G82: 46081 | I82: 000700704005 | J82: COP.VET 18 C/BORDO AC.304 C/F.VAP.A | K82: accessori finiti | L82: =VLOOKUP(K82,'COMM ITY- ENG'!A:B,2,FALSE) -> finished accessories | N82: 5010 | O82: NR | Q82: =+R82/N82 -> 0.32626347 | R82: 1634.58 | S82: =IFERROR(VLOOKUP(J82,'DESC ITY - ENG'!B:C,2,FALSE),VLOOKUP(I82,'DESC ITY - ENG'!A:C,3,FALSE)) -> Glass Lid 18cm SS304 Rim with Steam Vent Type AGlass Lid | T82: =VLOOKUP(S82,'DESC ITY - ENG'!C:D,2,FALSE) -> GLID | U82: =_xlfn.TRANSLATE(S82,"en","zh-cht") -> 玻璃蓋 18公分 SS304 輪圈，配有蒸汽通風型玻璃蓋 | V82: =VLOOKUP(T82,'STANDARD COMM'!A:D,3,FALSE) -> Lid | W82: =_xlfn.TRANSLATE(O82,"it","en") -> NR
A83: OF0039114 | B83: 45607.417 | D83: F506075 | E83: HEBEI BOZHENG GLASSWORK CO.LTD. | F83: 26AFF000036 | G83: 46081 | I83: 000700705005 | J83: COP.VET 20 C/BORDO AC.304 C/F.VAP.A | K83: accessori finiti | L83: =VLOOKUP(K83,'COMM ITY- ENG'!A:B,2,FALSE) -> finished accessories | N83: 4020 | O83: NR | Q83: =+R83/N83 -> 0.36289303 | R83: 1458.83 | S83: =IFERROR(VLOOKUP(J83,'DESC ITY - ENG'!B:C,2,FALSE),VLOOKUP(I83,'DESC ITY - ENG'!A:C,3,FALSE)) -> Glass Lid 20cm SS304 Rim with Steam Vent Type AGlass Lid | T83: =VLOOKUP(S83,'DESC ITY - ENG'!C:D,2,FALSE) -> GLID | U83: =_xlfn.TRANSLATE(S83,"en","zh-cht") -> 玻璃蓋 20公分 SS304 輪緣，配有蒸汽通風式 AGlass 蓋 | V83: =VLOOKUP(T83,'STANDARD COMM'!A:D,3,FALSE) -> Lid | W83: =_xlfn.TRANSLATE(O83,"it","en") -> NR
A84: OF0039114 | B84: 45629.658 | D84: F506075 | E84: HEBEI BOZHENG GLASSWORK CO.LTD. | F84: 26AFF000036 | G84: 46081 | I84: 000700707006 | J84: COP.VET 24 C/BORDO AC.304 C/F.VAP.A | K84: accessori finiti | L84: =VLOOKUP(K84,'COMM ITY- ENG'!A:B,2,FALSE) -> finished accessories | N84: 16000 | O84: NR | Q84: =+R84/N84 -> 0.43615312 | R84: 6978.45 | S84: =IFERROR(VLOOKUP(J84,'DESC ITY - ENG'!B:C,2,FALSE),VLOOKUP(I84,'DESC ITY - ENG'!A:C,3,FALSE)) -> Glass Lid 24cm SS304 Rim with Steam Vent Type AGlass Lid | T84: =VLOOKUP(S84,'DESC ITY - ENG'!C:D,2,FALSE) -> GLID | U84: =_xlfn.TRANSLATE(S84,"en","zh-cht") -> 玻璃蓋 24cm SS304 輪緣，配有蒸汽通風型玻璃蓋 | V84: =VLOOKUP(T84,'STANDARD COMM'!A:D,3,FALSE) -> Lid | W84: =_xlfn.TRANSLATE(O84,"it","en") -> NR
A85: OF0039114 | B85: 45642.711 | D85: F506075 | E85: HEBEI BOZHENG GLASSWORK CO.LTD. | F85: 26AFF000036 | G85: 46081 | I85: 000700708005 | J85: COP.VET 26 C/BORDO AC.304 C/F.VAP.A | K85: accessori finiti | L85: =VLOOKUP(K85,'COMM ITY- ENG'!A:B,2,FALSE) -> finished accessories | N85: 2000 | O85: NR | Q85: =+R85/N85 -> 0.49834 | R85: 996.68 | S85: =IFERROR(VLOOKUP(J85,'DESC ITY - ENG'!B:C,2,FALSE),VLOOKUP(I85,'DESC ITY - ENG'!A:C,3,FALSE)) -> Glass Lid 26cm SS304 Rim with Steam Vent Type AGlass Lid | T85: =VLOOKUP(S85,'DESC ITY - ENG'!C:D,2,FALSE) -> GLID | U85: =_xlfn.TRANSLATE(S85,"en","zh-cht") -> 玻璃蓋 26cm SS304 輪緣，配有蒸汽通風型玻璃蓋 | V85: =VLOOKUP(T85,'STANDARD COMM'!A:D,3,FALSE) -> Lid | W85: =_xlfn.TRANSLATE(O85,"it","en") -> NR
A86: OF0039114 | B86: 45629.658 | D86: F506075 | E86: HEBEI BOZHENG GLASSWORK CO.LTD. | F86: 26AFF000036 | G86: 46081 | I86: 000700709005 | J86: COP.VET.28 C/BORDO AC.304.C/F.VAP.A | K86: accessori finiti | L86: =VLOOKUP(K86,'COMM ITY- ENG'!A:B,2,FALSE) -> finished accessories | N86: 7000 | O86: NR | Q86: =+R86/N86 -> 0.54093143 | R86: 3786.52 | S86: =IFERROR(VLOOKUP(J86,'DESC ITY - ENG'!B:C,2,FALSE),VLOOKUP(I86,'DESC ITY - ENG'!A:C,3,FALSE)) -> Glass Lid 28cm SS304 Rim with Steam Vent Type AGlass Lid | T86: =VLOOKUP(S86,'DESC ITY - ENG'!C:D,2,FALSE) -> GLID | U86: =_xlfn.TRANSLATE(S86,"en","zh-cht") -> 玻璃蓋 28cm SS304 輪圈，配有蒸汽通風型玻璃蓋 | V86: =VLOOKUP(T86,'STANDARD COMM'!A:D,3,FALSE) -> Lid | W86: =_xlfn.TRANSLATE(O86,"it","en") -> NR
A87: OF0039114 | B87: 45642.711 | D87: F506075 | E87: HEBEI BOZHENG GLASSWORK CO.LTD. | F87: 26AFF000036 | G87: 46081 | I87: 000700710005 | J87: COP.VET.30 C/BORDO AC.304.C/F.VAP.A | K87: accessori finiti | L87: =VLOOKUP(K87,'COMM ITY- ENG'!A:B,2,FALSE) -> finished accessories | N87: 1005 | O87: NR | Q87: =+R87/N87 -> 0.61930348 | R87: 622.4 | S87: =IFERROR(VLOOKUP(J87,'DESC ITY - ENG'!B:C,2,FALSE),VLOOKUP(I87,'DESC ITY - ENG'!A:C,3,FALSE)) -> Glass Lid 30cm SS304 Rim with Steam Vent Type AGlass Lid | T87: =VLOOKUP(S87,'DESC ITY - ENG'!C:D,2,FALSE) -> GLID | U87: =_xlfn.TRANSLATE(S87,"en","zh-cht") -> 玻璃蓋 30cm SS304 輪圈，配有蒸汽通風型 AGlass 蓋 | V87: =VLOOKUP(T87,'STANDARD COMM'!A:D,3,FALSE) -> Lid | W87: =_xlfn.TRANSLATE(O87,"it","en") -> NR
A88: OF0040239 | B88: 45583.663 | D88: F502408 | E88: ILAG INDUSTRIELACK AG | F88: 26AFF000050 | G88: 46081 | I88: 003040104002 | J88: PRIMER 1213-009 DURIT PROTECT PRO BLACK | K88: prodotti chimici | L88: =VLOOKUP(K88,'COMM ITY- ENG'!A:B,2,FALSE) -> chemical products | N88: 502 | O88: kg | Q88: =+R88/N88 -> 16.2 | R88: 8132.4 | S88: =IFERROR(VLOOKUP(J88,'DESC ITY - ENG'!B:C,2,FALSE),VLOOKUP(I88,'DESC ITY - ENG'!A:C,3,FALSE)) -> Coating Durit Protect Pro Black Primer 1213-009 | T88: =VLOOKUP(S88,'DESC ITY - ENG'!C:D,2,FALSE) -> INM- | U88: =_xlfn.TRANSLATE(S88,"en","zh-cht") -> 塗層 Durit Protect Pro 黑色底漆 1213-009 | V88: =VLOOKUP(T88,'STANDARD COMM'!A:D,3,FALSE) -> Coating | W88: =_xlfn.TRANSLATE(O88,"it","en") -> kg
A89: OF0040035 | B89: 45666.5 | D89: F600467 | E89: IMF INDUSTRIE MARCHIGIANE FILTRI SRL | F89: 26AFI000496 | G89: 46081 | I89: 0002A0127TS4 | J89: DISCO AC.127/040 C/F 3MM+TAGLI STRETTI+FORO CENTRALE 38mm | K89: acciaio | L89: =VLOOKUP(K89,'COMM ITY- ENG'!A:B,2,FALSE) -> steel | N89: 9700 | O89: NR | Q89: =+R89/N89 -> 0.1449 | R89: 1405.53 | S89: =IFERROR(VLOOKUP(J89,'DESC ITY - ENG'!B:C,2,FALSE),VLOOKUP(I89,'DESC ITY - ENG'!A:C,3,FALSE)) -> Steel Disc AC.127/040 3.0mm Narrow Slots + 38mm Center Hole [cite: 1] | T89: =VLOOKUP(S89,'DESC ITY - ENG'!C:D,2,FALSE) -> SM-- | U89: =_xlfn.TRANSLATE(S89,"en","zh-cht") -> 鋼盤 AC.127/040 3.0mm 窄槽 + 38mm 中心孔 [引用：1] | V89: =VLOOKUP(T89,'STANDARD COMM'!A:D,3,FALSE) -> Metal | W89: =_xlfn.TRANSLATE(O89,"it","en") -> NR
... A135: OF0039874 | B135: 45642.711 | D135: F600732 | E135: MUTLU METAL DIS TICARET LTD.STI | F135: 26AFF000046 | G135: 46081 | I135: 000281710002 | J135: MANICO AC.SOLE CORTO C/LOGO MC AISI 430 SABBIATO PAD.279 24 | K135: manigliame | L135: =VLOOKUP(K135,'COMM ITY- ENG'!A:B,2,FALSE) -> handles | N135: 10000 | O135: NR | Q135: =+R135/N135 -> 1.19 | R135: 11900 | S135: =IFERROR(VLOOKUP(J135,'DESC ITY - ENG'!B:C,2,FALSE),VLOOKUP(I135,'DESC ITY - ENG'!A:C,3,FALSE)) -> Steel Handle AC.SOLE Short w/Logo MC AISI 430 Pan 279-24 Sandblasted [cite: 4] | T135: =VLOOKUP(S135,'DESC ITY - ENG'!C:D,2,FALSE) -> SHDL | U135: =_xlfn.TRANSLATE(S135,"en","zh-cht") -> 鋼柄冷氣。獨短帶標誌 MC AISI 430 Pan 279-24 噴砂處理 [引用：4] | V135: =VLOOKUP(T135,'STANDARD COMM'!A:D,3,FALSE) -> Fittings | W135: =_xlfn.TRANSLATE(O135,"it","en") -> NR
B136: 45642.711 | D136: F600732 | E136: MUTLU METAL DIS TICARET LTD.STI | F136: 26AFF000046 | G136: 46081 | I136: 000281710002 | J136: MANICO AC.SOLE CORTO C/LOGO MC AISI 430 SABBIATO PAD.279 24 | K136: manigliame | L136: =VLOOKUP(K136,'COMM ITY- ENG'!A:B,2,FALSE) -> handles | N136: 9292 | O136: NR | Q136: =+R136/N136 -> 1.19 | R136: 11057.48 | S136: =IFERROR(VLOOKUP(J136,'DESC ITY - ENG'!B:C,2,FALSE),VLOOKUP(I136,'DESC ITY - ENG'!A:C,3,FALSE)) -> Steel Handle AC.SOLE Short w/Logo MC AISI 430 Pan 279-24 Sandblasted [cite: 4] | T136: =VLOOKUP(S136,'DESC ITY - ENG'!C:D,2,FALSE) -> SHDL | U136: =_xlfn.TRANSLATE(S136,"en","zh-cht") -> 鋼柄冷氣。獨短帶標誌 MC AISI 430 Pan 279-24 噴砂處理 [引用：4] | V136: =VLOOKUP(T136,'STANDARD COMM'!A:D,3,FALSE) -> Fittings | W136: =_xlfn.TRANSLATE(O136,"it","en") -> NR
A137: OF0039874 | B137: 45629.658 | D137: F600732 | E137: MUTLU METAL DIS TICARET LTD.STI | F137: 26AFF000046 | G137: 46081 | I137: 000281710006 | J137: MANICO AC.SOLE LUNGO C/LOGO MC AISI 430 SABBIATO TEG.379 26 | K137: manigliame | L137: =VLOOKUP(K137,'COMM ITY- ENG'!A:B,2,FALSE) -> handles | N137: 10010 | O137: NR | Q137: =+R137/N137 -> 1.29 | R137: 12912.9 | S137: =IFERROR(VLOOKUP(J137,'DESC ITY - ENG'!B:C,2,FALSE),VLOOKUP(I137,'DESC ITY - ENG'!A:C,3,FALSE)) -> Steel Handle AC.SOLE Long w/Logo MC AISI 430 Skillet 379-26 Sandblasted [cite: 4 5] | T137: =VLOOKUP(S137,'DESC ITY - ENG'!C:D,2,FALSE) -> HDL- | U137: =_xlfn.TRANSLATE(S137,"en","zh-cht") -> 鋼柄冷氣。鞋底長款，配 MC 標誌 MC AISI 430 Skillet 379-26 噴砂 [引用：4 5] | V137: =VLOOKUP(T137,'STANDARD COMM'!A:D,3,FALSE) -> Fittings | W137: =_xlfn.TRANSLATE(O137,"it","en") -> NR
A138: OF0039874 | B138: 45642.711 | D138: F600732 | E138: MUTLU METAL DIS TICARET LTD.STI | F138: 26AFF000046 | G138: 46081 | I138: 000320380001 | J138: POMOLO AC.SOLE C/LOGO MC AISI 430 SABBIATO | K138: manigliame | L138: =VLOOKUP(K138,'COMM ITY- ENG'!A:B,2,FALSE) -> handles | N138: 3960 | O138: NR | Q138: =+R138/N138 -> 1.15 | R138: 4554 | S138: =IFERROR(VLOOKUP(J138,'DESC ITY - ENG'!B:C,2,FALSE),VLOOKUP(I138,'DESC ITY - ENG'!A:C,3,FALSE)) -> Steel Knob AC.SOLE w/Logo MC AISI 430 Sandblasted [cite: 5] | T138: =VLOOKUP(S138,'DESC ITY - ENG'!C:D,2,FALSE) -> KNOB | U138: =_xlfn.TRANSLATE(S138,"en","zh-cht") -> 鋼旋鈕冷氣。唯一配件 MC 標誌 AISI 430 砂燒 [引用：5] | V138: =VLOOKUP(T138,'STANDARD COMM'!A:D,3,FALSE) -> Fittings | W138: =_xlfn.TRANSLATE(O138,"it","en") -> NR
A139: OF0039874 | B139: 45601.461 | D139: F600732 | E139: MUTLU METAL DIS TICARET LTD.STI | F139: 26AFF000052 | G139: 46081 | I139: 000281710002 | J139: MANICO AC.SOLE CORTO C/LOGO MC AISI 430 SABBIATO PAD.279 24 | K139: manigliame | L139: =VLOOKUP(K139,'COMM ITY- ENG'!A:B,2,FALSE) -> handles | N139: 708 | O139: NR | Q139: =+R139/N139 -> 1.19 | R139: 842.52 | S139: =IFERROR(VLOOKUP(J139,'DESC ITY - ENG'!B:C,2,FALSE),VLOOKUP(I139,'DESC ITY - ENG'!A:C,3,FALSE)) -> Steel Handle AC.SOLE Short w/Logo MC AISI 430 Pan 279-24 Sandblasted [cite: 4] | T139: =VLOOKUP(S139,'DESC ITY - ENG'!C:D,2,FALSE) -> SHDL | U139: =_xlfn.TRANSLATE(S139,"en","zh-cht") -> 鋼柄冷氣。獨短帶標誌 MC AISI 430 Pan 279-24 噴砂處理 [引用：4] | V139: =VLOOKUP(T139,'STANDARD COMM'!A:D,3,FALSE) -> Fittings | W139: =_xlfn.TRANSLATE(O139,"it","en") -> NR
A140: OF0040251 | B140: 45601.461 | D140: F600732 | E140: MUTLU METAL DIS TICARET LTD.STI | F140: 26AFF000052 | G140: 46081 | I140: 000281710002 | J140: MANICO AC.SOLE CORTO C/LOGO MC AISI 430 SABBIATO PAD.279 24 | K140: manigliame | L140: =VLOOKUP(K140,'COMM ITY- ENG'!A:B,2,FALSE) -> handles | N140: 3387 | O140: NR | Q140: =+R140/N140 -> 1.19 | R140: 4030.53 | S140: =IFERROR(VLOOKUP(J140,'DESC ITY - ENG'!B:C,2,FALSE),VLOOKUP(I140,'DESC ITY - ENG'!A:C,3,FALSE)) -> Steel Handle AC.SOLE Short w/Logo MC AISI 430 Pan 279-24 Sandblasted [cite: 4] | T140: =VLOOKUP(S140,'DESC ITY - ENG'!C:D,2,FALSE) -> SHDL | U140: =_xlfn.TRANSLATE(S140,"en","zh-cht") -> 鋼柄冷氣。獨短帶標誌 MC AISI 430 Pan 279-24 噴砂處理 [引用：4] | V140: =VLOOKUP(T140,'STANDARD COMM'!A:D,3,FALSE) -> Fittings | W140: =_xlfn.TRANSLATE(O140,"it","en") -> NR
A141: OF0039874 | B141: 45593.687 | D141: F600732 | E141: MUTLU METAL DIS TICARET LTD.STI | F141: 26AFF000052 | G141: 46081 | I141: 000281710006 | J141: MANICO AC.SOLE LUNGO C/LOGO MC AISI 430 SABBIATO TEG.379 26 | K141: manigliame | L141: =VLOOKUP(K141,'COMM ITY- ENG'!A:B,2,FALSE) -> handles | N141: 15015 | O141: NR | Q141: =+R141/N141 -> 1.29 | R141: 19369.35 | S141: =IFERROR(VLOOKUP(J141,'DESC ITY - ENG'!B:C,2,FALSE),VLOOKUP(I141,'DESC ITY - ENG'!A:C,3,FALSE)) -> Steel Handle AC.SOLE Long w/Logo MC AISI 430 Skillet 379-26 Sandblasted [cite: 4 5] | T141: =VLOOKUP(S141,'DESC ITY - ENG'!C:D,2,FALSE) -> HDL- | U141: =_xlfn.TRANSLATE(S141,"en","zh-cht") -> 鋼柄冷氣。鞋底長款，配 MC 標誌 MC AISI 430 Skillet 379-26 噴砂 [引用：4 5] | V141: =VLOOKUP(T141,'STANDARD COMM'!A:D,3,FALSE) -> Fittings | W141: =_xlfn.TRANSLATE(O141,"it","en") -> NR
A142: OF0040154 | B142: 45618.468 | D142: F600732 | E142: MUTLU METAL DIS TICARET LTD.STI | F142: 26AFF000052 | G142: 46081 | I142: 000281710007 | J142: MANIGLIA AC.SOLE C/LOGO MC AISI 430 SABBIATA CAS.480 20 | K142: manigliame | L142: =VLOOKUP(K142,'COMM ITY- ENG'!A:B,2,FALSE) -> handles | N142: 6552 | O142: NR | Q142: =+R142/N142 -> 0.91 | R142: 5962.32 | S142: =IFERROR(VLOOKUP(J142,'DESC ITY - ENG'!B:C,2,FALSE),VLOOKUP(I142,'DESC ITY - ENG'!A:C,3,FALSE)) -> Steel Side Handle AC.SOLE w/Logo MC AISI 430 Casserole 480-20 Sandblasted [cite: 5] | T142: =VLOOKUP(S142,'DESC ITY - ENG'!C:D,2,FALSE) -> SHDL | U142: =_xlfn.TRANSLATE(S142,"en","zh-cht") -> 鋼製側把冷氣。鞋底配標誌 MC AISI 430 砂鍋 480-20 砂磨 [引用：5] | V142: =VLOOKUP(T142,'STANDARD COMM'!A:D,3,FALSE) -> Fittings | W142: =_xlfn.TRANSLATE(O142,"it","en") -> NR
A143: OF0039874 | B143: 45639.624 | D143: F600732 | E143: MUTLU METAL DIS TICARET LTD.STI | F143: 26AFF000052 | G143: 46081 | I143: 000320380001 | J143: POMOLO AC.SOLE C/LOGO MC AISI 430 SABBIATO | K143: manigliame | L143: =VLOOKUP(K143,'COMM ITY- ENG'!A:B,2,FALSE) -> handles | N143: 4670 | O143: NR | Q143: =+R143/N143 -> 1.15 | R143: 5370.5 | S143: =IFERROR(VLOOKUP(J143,'DESC ITY - ENG'!B:C,2,FALSE),VLOOKUP(I143,'DESC ITY - ENG'!A:C,3,FALSE)) -> Steel Knob AC.SOLE w/Logo MC AISI 430 Sandblasted [cite: 5] | T143: =VLOOKUP(S143,'DESC ITY - ENG'!C:D,2,FALSE) -> KNOB | U143: =_xlfn.TRANSLATE(S143,"en","zh-cht") -> 鋼旋鈕冷氣。唯一配件 MC 標誌 AISI 430 砂燒 [引用：5] | V143: =VLOOKUP(T143,'STANDARD COMM'!A:D,3,FALSE) -> Fittings | W143: =_xlfn.TRANSLATE(O143,"it","en") -> NR
A144: OF0040154 | B144: 45639.624 | D144: F600732 | E144: MUTLU METAL DIS TICARET LTD.STI | F144: 26AFF000052 | G144: 46081 | I144: 000320380001 | J144: POMOLO AC.SOLE C/LOGO MC AISI 430 SABBIATO | K144: manigliame | L144: =VLOOKUP(K144,'COMM ITY- ENG'!A:B,2,FALSE) -> handles | N144: 3250 | O144: NR | Q144: =+R144/N144 -> 1.15 | R144: 3737.5 | S144: =IFERROR(VLOOKUP(J144,'DESC ITY - ENG'!B:C,2,FALSE),VLOOKUP(I144,'DESC ITY - ENG'!A:C,3,FALSE)) -> Steel Knob AC.SOLE w/Logo MC AISI 430 Sandblasted [cite: 5] | T144: =VLOOKUP(S144,'DESC ITY - ENG'!C:D,2,FALSE) -> KNOB | U144: =_xlfn.TRANSLATE(S144,"en","zh-cht") -> 鋼旋鈕冷氣。唯一配件 MC 標誌 AISI 430 砂燒 [引用：5] | V144: =VLOOKUP(T144,'STANDARD COMM'!A:D,3,FALSE) -> Fittings | W144: =_xlfn.TRANSLATE(O144,"it","en") -> NR
A145: OF0039276 | B145: 45618.468 | D145: F506013 | E145: NINGBO CITY BEILUN HECHENG METAL PRODUCTS CO.LTD | F145: 26AFF000043 | G145: 46081 | I145: 0002A0125TS5 | J145: DISCO AC.125/040 C/F 2,5 MM+TAGLI STRETTI+FO.CENTRALE 36,5mm | K145: acciaio | L145: =VLOOKUP(K145,'COMM ITY- ENG'!A:B,2,FALSE) -> steel | N145: 30000 | O145: NR | Q145: =+R145/N145 -> 0.097964 | R145: 2938.92 | S145: =IFERROR(VLOOKUP(J145,'DESC ITY - ENG'!B:C,2,FALSE),VLOOKUP(I145,'DESC ITY - ENG'!A:C,3,FALSE)) -> 5 MM+TAGLI STRETTI+FO.CENTRALE 365mmSteel Disc AC.125/040 2.5mm Narrow Slots + 36.5mm Center Hole [cite: 1] | T145: =VLOOKUP(S145,'DESC ITY - ENG'!C:D,2,FALSE) -> SSM- | U145: =_xlfn.TRANSLATE(S145,"en","zh-cht") -> 5毫米+塔格利鏈條+FO。CENTRALE 365mm鋼盤 AC.125/040 2.5mm 窄槽 + 36.5mm 中心孔 [引用：1] | V145: =VLOOKUP(T145,'STANDARD COMM'!A:D,3,FALSE) -> Metal | W145: =_xlfn.TRANSLATE(O145,"it","en") -> NR
A146: OF0039276 | B146: 45630.454 | D146: F506013 | E146: NINGBO CITY BEILUN HECHENG METAL PRODUCTS CO.LTD | F146: 26AFF000043 | G146: 46081 | I146: 0002A0135TS5 | J146: DISCO AC.135/040 C/F 2,5 MM+TAGLI STRETTI+FO.CENTRALE 36,5mm | K146: acciaio | L146: =VLOOKUP(K146,'COMM ITY- ENG'!A:B,2,FALSE) -> steel | N146: 15000 | O146: NR | Q146: =+R146/N146 -> 0.10648267 | R146: 1597.24 | S146: =IFERROR(VLOOKUP(J146,'DESC ITY - ENG'!B:C,2,FALSE),VLOOKUP(I146,'DESC ITY - ENG'!A:C,3,FALSE)) -> 5 MM+TAGLI STRETTI+FO.CENTRALE 365mmSteel Disc AC.135/040 2.5mm Narrow Slots + 36.5mm Center Hole [cite: 1] | T146: =VLOOKUP(S146,'DESC ITY - ENG'!C:D,2,FALSE) -> SSM- | U146: =_xlfn.TRANSLATE(S146,"en","zh-cht") -> 5毫米+塔格利鏈條+FO。CENTRALE 365mm鋼盤 AC.135/040 2.5mm 窄槽 + 36.5mm 中心孔 [引用：1] | V146: =VLOOKUP(T146,'STANDARD COMM'!A:D,3,FALSE) -> Metal | W146: =_xlfn.TRANSLATE(O146,"it","en") -> NR
A147: OF0039276 | B147: 45618.468 | D147: F506013 | E147: NINGBO CITY BEILUN HECHENG METAL PRODUCTS CO.LTD | F147: 26AFF000043 | G147: 46081 | I147: 0002A0155TS5 | J147: DISCO AC.155/040 C/F 2,5 MM+TAGLI STRETTI+FORO CENTRALE 50mm | K147: acciaio | L147: =VLOOKUP(K147,'COMM ITY- ENG'!A:B,2,FALSE) -> steel | N147: 20000 | O147: NR | Q147: =+R147/N147 -> 0.130335 | R147: 2606.7 | S147: =IFERROR(VLOOKUP(J147,'DESC ITY - ENG'!B:C,2,FALSE),VLOOKUP(I147,'DESC ITY - ENG'!A:C,3,FALSE)) -> 5 MM+TAGLI STRETTI+FORO CENTRALE 50mmSteel Disc AC.155/040 2.5mm Narrow Slots + 50mm Center Hole [cite: 1] | T147: =VLOOKUP(S147,'DESC ITY - ENG'!C:D,2,FALSE) -> SSM- | U147: =_xlfn.TRANSLATE(S147,"en","zh-cht") -> 5毫米+塔格利STRETTI+FORO CENTRALE鋼盤50毫米AC.155/040 2.5毫米窄槽+50毫米中心孔【引用：1】 | V147: =VLOOKUP(T147,'STANDARD COMM'!A:D,3,FALSE) -> Metal | W147: =_xlfn.TRANSLATE(O147,"it","en") -> NR
A148: OF0039276 | B148: 45630.454 | D148: F506013 | E148: NINGBO CITY BEILUN HECHENG METAL PRODUCTS CO.LTD | F148: 26AFF000043 | G148: 46081 | I148: 0002A0165TS5 | J148: DISCO AC.165/040 C/F 2,5 MM+TAGLI STRETTI+FORO CENTRALE 50mm | K148: acciaio | L148: =VLOOKUP(K148,'COMM ITY- ENG'!A:B,2,FALSE) -> steel | N148: 15000 | O148: NR | Q148: =+R148/N148 -> 0.14311267 | R148: 2146.69 | S148: =IFERROR(VLOOKUP(J148,'DESC ITY - ENG'!B:C,2,FALSE),VLOOKUP(I148,'DESC ITY - ENG'!A:C,3,FALSE)) -> Steel Disc AC.165/040 2.5mm Narrow Slots + 50mm Center Hole [cite: 1] | T148: =VLOOKUP(S148,'DESC ITY - ENG'!C:D,2,FALSE) -> SM-- | U148: =_xlfn.TRANSLATE(S148,"en","zh-cht") -> 鋼盤 AC.165/040 2.5mm 窄槽 + 50mm 中心孔 [引用：1] | V148: =VLOOKUP(T148,'STANDARD COMM'!A:D,3,FALSE) -> Metal | W148: =_xlfn.TRANSLATE(O148,"it","en") -> NR
... A168: OF0039918 | B168: 45642.711 | D168: F013344 | E168: VITINOX SAS DI GUGLIELMELLI R.& C. | F168: 26AFI000488 | G168: 46081 | I168: 000450626001 | J168: RIBATTINO AC.6X12 MADE IN | K168: accessori x manigl. | L168: =VLOOKUP(K168,'COMM ITY- ENG'!A:B,2,FALSE) -> accessories for handles | N168: 100000 | O168: NR | Q168: =+R168/N168 -> 0.0646 | R168: 6460 | S168: =IFERROR(VLOOKUP(J168,'DESC ITY - ENG'!B:C,2,FALSE),VLOOKUP(I168,'DESC ITY - ENG'!A:C,3,FALSE)) -> Steel Rivet 6x12 mm | T168: =VLOOKUP(S168,'DESC ITY - ENG'!C:D,2,FALSE) -> RIV- | U168: =_xlfn.TRANSLATE(S168,"en","zh-cht") -> 鋼鉚釘 6x12 毫米 | V168: =VLOOKUP(T168,'STANDARD COMM'!A:D,3,FALSE) -> Fastener | W168: =_xlfn.TRANSLATE(O168,"it","en") -> NR
B169: 45680.639 | D169: F013344 | E169: VITINOX SAS DI GUGLIELMELLI R.& C. | F169: 26AFI000488 | G169: 46081 | I169: 000450626001 | J169: RIBATTINO AC.6X12 MADE IN | K169: accessori x manigl. | L169: =VLOOKUP(K169,'COMM ITY- ENG'!A:B,2,FALSE) -> accessories for handles | N169: 3000 | O169: NR | Q169: =+R169/N169 -> 0.0646 | R169: 193.8 | S169: =IFERROR(VLOOKUP(J169,'DESC ITY - ENG'!B:C,2,FALSE),VLOOKUP(I169,'DESC ITY - ENG'!A:C,3,FALSE)) -> Steel Rivet 6x12 mm | T169: =VLOOKUP(S169,'DESC ITY - ENG'!C:D,2,FALSE) -> RIV- | U169: =_xlfn.TRANSLATE(S169,"en","zh-cht") -> 鋼鉚釘 6x12 毫米 | V169: =VLOOKUP(T169,'STANDARD COMM'!A:D,3,FALSE) -> Fastener | W169: =_xlfn.TRANSLATE(O169,"it","en") -> NR
B170: 45707.403 | D170: F013344 | E170: VITINOX SAS DI GUGLIELMELLI R.& C. | F170: 26AFI000488 | G170: 46081 | I170: 000450626001 | J170: RIBATTINO AC.6X12 MADE IN | K170: accessori x manigl. | L170: =VLOOKUP(K170,'COMM ITY- ENG'!A:B,2,FALSE) -> accessories for handles | N170: 100000 | O170: NR | Q170: =+R170/N170 -> 0.0646 | R170: 6460 | S170: =IFERROR(VLOOKUP(J170,'DESC ITY - ENG'!B:C,2,FALSE),VLOOKUP(I170,'DESC ITY - ENG'!A:C,3,FALSE)) -> Steel Rivet 6x12 mm | T170: =VLOOKUP(S170,'DESC ITY - ENG'!C:D,2,FALSE) -> RIV- | U170: =_xlfn.TRANSLATE(S170,"en","zh-cht") -> 鋼鉚釘 6x12 毫米 | V170: =VLOOKUP(T170,'STANDARD COMM'!A:D,3,FALSE) -> Fastener | W170: =_xlfn.TRANSLATE(O170,"it","en") -> NR
A171: OF0040417 | B171: 45623.416 | D171: F015428 | E171: WÜRTH SRL | F171: 26AFI000429 | G171: 46081 | I171: 009000001001 | J171: GUANTO COT.FILO CONTINUO PZ.12 D/U 1997611736 | K171: materiali di consumo | L171: =VLOOKUP(K171,'COMM ITY- ENG'!A:B,2,FALSE) -> consumable materials | N171: 864 | O171: NR | Q171: =+R171/N171 -> 0.44 | R171: 380.16 | S171: =IFERROR(VLOOKUP(J171,'DESC ITY - ENG'!B:C,2,FALSE),VLOOKUP(I171,'DESC ITY - ENG'!A:C,3,FALSE)) -> Cotton Gloves Continuous Filament 12 pcs Unisex | T171: =VLOOKUP(S171,'DESC ITY - ENG'!C:D,2,FALSE) -> MISC | U171: =_xlfn.TRANSLATE(S171,"en","zh-cht") -> 棉手套 連續線 12 件 中性 | V171: =VLOOKUP(T171,'STANDARD COMM'!A:D,3,FALSE) -> Misc | W171: =_xlfn.TRANSLATE(O171,"it","en") -> NR
A172: OF0040417 | B172: 45624.677 | D172: F015428 | E172: WÜRTH SRL | F172: 26AFI000465 | G172: 46081 | I172: 009000010054 | J172: GUANTO SPANDEXBLACK 11939 TAG. L | K172: materiali di consumo | L172: =VLOOKUP(K172,'COMM ITY- ENG'!A:B,2,FALSE) -> consumable materials | N172: 1440 | O172: NR | Q172: =+R172/N172 -> 0.86 | R172: 1238.4 | S172: =IFERROR(VLOOKUP(J172,'DESC ITY - ENG'!B:C,2,FALSE),VLOOKUP(I172,'DESC ITY - ENG'!A:C,3,FALSE)) -> Spandex Black Gloves Style 11939 Size Large | T172: =VLOOKUP(S172,'DESC ITY - ENG'!C:D,2,FALSE) -> MISC | U172: =_xlfn.TRANSLATE(S172,"en","zh-cht") -> 11939 年彈性黑手套款式 大號 | V172: =VLOOKUP(T172,'STANDARD COMM'!A:D,3,FALSE) -> Misc | W172: =_xlfn.TRANSLATE(O172,"it","en") -> NR
A173: OF0038908 | B173: 45688.668 | D173: F010036 | E173: BBC PLASTIK SRL | F173: 26AFI000263 | G173: 46071 | I173: 001110033001 | J173: BUSTA BOCC.27X30 | K173: accessori di confez. | L173: =VLOOKUP(K173,'COMM ITY- ENG'!A:B,2,FALSE) -> packaging accessories | N173: 3000 | O173: NR | Q173: =+R173/N173 -> 0.0316 | R173: 94.8 | S173: =IFERROR(VLOOKUP(J173,'DESC ITY - ENG'!B:C,2,FALSE),VLOOKUP(I173,'DESC ITY - ENG'!A:C,3,FALSE)) -> Punched Bag 27x30 cm | T173: =VLOOKUP(S173,'DESC ITY - ENG'!C:D,2,FALSE) -> BAG- | U173: =_xlfn.TRANSLATE(S173,"en","zh-cht") -> 沙包 27x30 公分 | V173: =VLOOKUP(T173,'STANDARD COMM'!A:D,3,FALSE) -> Plastic | W173: =_xlfn.TRANSLATE(O173,"it","en") -> NR
A174: OF0039395 | B174: 45688.668 | D174: F010036 | E174: BBC PLASTIK SRL | F174: 26AFI000263 | G174: 46071 | I174: 001110077002 | J174: BUSTA BOCC.35X35 SU ENTRAMBI I LATI | K174: accessori di confez. | L174: =VLOOKUP(K174,'COMM ITY- ENG'!A:B,2,FALSE) -> packaging accessories | N174: 6400 | O174: NR | Q174: =+R174/N174 -> 0.0478 | R174: 305.92 | S174: =IFERROR(VLOOKUP(J174,'DESC ITY - ENG'!B:C,2,FALSE),VLOOKUP(I174,'DESC ITY - ENG'!A:C,3,FALSE)) -> Punched Bag 35x35 cm Punched on Both Sides | T174: =VLOOKUP(S174,'DESC ITY - ENG'!C:D,2,FALSE) -> BAG- | U174: =_xlfn.TRANSLATE(S174,"en","zh-cht") -> 沙包 35x35 公分，兩邊都有打孔 | V174: =VLOOKUP(T174,'STANDARD COMM'!A:D,3,FALSE) -> Plastic | W174: =_xlfn.TRANSLATE(O174,"it","en") -> NR
A175: OF0039818 | B175: 45610.893 | D175: F010036 | E175: BBC PLASTIK SRL | F175: 26AFI000263 | G175: 46071 | I175: 001110077002 | J175: BUSTA BOCC.35X35 SU ENTRAMBI I LATI | K175: accessori di confez. | L175: =VLOOKUP(K175,'COMM ITY- ENG'!A:B,2,FALSE) -> packaging accessories | N175: 12800 | O175: NR | Q175: =+R175/N175 -> 0.0478 | R175: 611.84 | S175: =IFERROR(VLOOKUP(J175,'DESC ITY - ENG'!B:C,2,FALSE),VLOOKUP(I175,'DESC ITY - ENG'!A:C,3,FALSE)) -> Punched Bag 35x35 cm Punched on Both Sides | T175: =VLOOKUP(S175,'DESC ITY - ENG'!C:D,2,FALSE) -> BAG- | U175: =_xlfn.TRANSLATE(S175,"en","zh-cht") -> 沙包 35x35 公分，兩邊都有打孔 | V175: =VLOOKUP(T175,'STANDARD COMM'!A:D,3,FALSE) -> Plastic | W175: =_xlfn.TRANSLATE(O175,"it","en") -> NR
A176: OF0040264 | B176: 45639.624 | D176: F010036 | E176: BBC PLASTIK SRL | F176: 26AFI000263 | G176: 46071 | I176: 001110077002 | J176: BUSTA BOCC.35X35 SU ENTRAMBI I LATI | K176: accessori di confez. | L176: =VLOOKUP(K176,'COMM ITY- ENG'!A:B,2,FALSE) -> packaging accessories | N176: 14400 | O176: NR | Q176: =+R176/N176 -> 0.0478 | R176: 688.32 | S176: =IFERROR(VLOOKUP(J176,'DESC ITY - ENG'!B:C,2,FALSE),VLOOKUP(I176,'DESC ITY - ENG'!A:C,3,FALSE)) -> Punched Bag 35x35 cm Punched on Both Sides | T176: =VLOOKUP(S176,'DESC ITY - ENG'!C:D,2,FALSE) -> BAG- | U176: =_xlfn.TRANSLATE(S176,"en","zh-cht") -> 沙包 35x35 公分，兩邊都有打孔 | V176: =VLOOKUP(T176,'STANDARD COMM'!A:D,3,FALSE) -> Plastic | W176: =_xlfn.TRANSLATE(O176,"it","en") -> NR
A177: OF0040264 | B177: 45666.355 | D177: F010036 | E177: BBC PLASTIK SRL | F177: 26AFI000263 | G177: 46071 | I177: 001110077004 | J177: BUSTA BOCC.35X40 DOPPIA C/WARNING 35 LINGUE | K177: accessori di confez. | L177: =VLOOKUP(K177,'COMM ITY- ENG'!A:B,2,FALSE) -> packaging accessories | N177: 5850 | O177: NR | Q177: =+R177/N177 -> 0.062 | R177: 362.7 | S177: =IFERROR(VLOOKUP(J177,'DESC ITY - ENG'!B:C,2,FALSE),VLOOKUP(I177,'DESC ITY - ENG'!A:C,3,FALSE)) -> Punched Bag 35x40 cm Double Layer with 35-Language Warning | T177: =VLOOKUP(S177,'DESC ITY - ENG'!C:D,2,FALSE) -> BAG- | U177: =_xlfn.TRANSLATE(S177,"en","zh-cht") -> 沙包35x40公分雙層，附35種語言警告 | V177: =VLOOKUP(T177,'STANDARD COMM'!A:D,3,FALSE) -> Plastic | W177: =_xlfn.TRANSLATE(O177,"it","en") -> NR
A178: OF0035853 | B178: 45639.624 | D178: F010036 | E178: BBC PLASTIK SRL | F178: 26AFI000263 | G178: 46071 | I178: 001110100002 | J178: BUSTA BOCC.40X40 SU ENTRAMBI I LATI VERSIONE GR55+HD | K178: accessori di confez. | L178: =VLOOKUP(K178,'COMM ITY- ENG'!A:B,2,FALSE) -> packaging accessories | N178: 7800 | O178: NR | Q178: =+R178/N178 -> 0.056 | R178: 436.8 | S178: =IFERROR(VLOOKUP(J178,'DESC ITY - ENG'!B:C,2,FALSE),VLOOKUP(I178,'DESC ITY - ENG'!A:C,3,FALSE)) -> Punched Bag 40x40 cm Punched on Both Sides Version GR55+HD | T178: =VLOOKUP(S178,'DESC ITY - ENG'!C:D,2,FALSE) -> BAG- | U178: =_xlfn.TRANSLATE(S178,"en","zh-cht") -> 沙包 40x40 公分，兩面皆有打孔版本 GR55+HD | V178: =VLOOKUP(T178,'STANDARD COMM'!A:D,3,FALSE) -> Plastic | W178: =_xlfn.TRANSLATE(O178,"it","en") -> NR
A179: OF0037622 | B179: 45610.63 | D179: F010036 | E179: BBC PLASTIK SRL | F179: 26AFI000263 | G179: 46071 | I179: 001110100002 | J179: BUSTA BOCC.40X40 SU ENTRAMBI I LATI VERSIONE GR55+HD | K179: accessori di confez. | L179: =VLOOKUP(K179,'COMM ITY- ENG'!A:B,2,FALSE) -> packaging accessories | N179: 800 | O179: NR | Q179: =+R179/N179 -> 0.056 | R179: 44.8 | S179: =IFERROR(VLOOKUP(J179,'DESC ITY - ENG'!B:C,2,FALSE),VLOOKUP(I179,'DESC ITY - ENG'!A:C,3,FALSE)) -> Punched Bag 40x40 cm Punched on Both Sides Version GR55+HD | T179: =VLOOKUP(S179,'DESC ITY - ENG'!C:D,2,FALSE) -> BAG- | U179: =_xlfn.TRANSLATE(S179,"en","zh-cht") -> 沙包 40x40 公分，兩面皆有打孔版本 GR55+HD | V179: =VLOOKUP(T179,'STANDARD COMM'!A:D,3,FALSE) -> Plastic | W179: =_xlfn.TRANSLATE(O179,"it","en") -> NR
A180: OF0039064 | B180: 45639.624 | D180: F010036 | E180: BBC PLASTIK SRL | F180: 26AFI000263 | G180: 46071 | I180: 001110100002 | J180: BUSTA BOCC.40X40 SU ENTRAMBI I LATI VERSIONE GR55+HD | K180: accessori di confez. | L180: =VLOOKUP(K180,'COMM ITY- ENG'!A:B,2,FALSE) -> packaging accessories | N180: 400 | O180: NR | Q180: =+R180/N180 -> 0.056 | R180: 22.4 | S180: =IFERROR(VLOOKUP(J180,'DESC ITY - ENG'!B:C,2,FALSE),VLOOKUP(I180,'DESC ITY - ENG'!A:C,3,FALSE)) -> Punched Bag 40x40 cm Punched on Both Sides Version GR55+HD | T180: =VLOOKUP(S180,'DESC ITY - ENG'!C:D,2,FALSE) -> BAG- | U180: =_xlfn.TRANSLATE(S180,"en","zh-cht") -> 沙包 40x40 公分，兩面皆有打孔版本 GR55+HD | V180: =VLOOKUP(T180,'STANDARD COMM'!A:D,3,FALSE) -> Plastic | W180: =_xlfn.TRANSLATE(O180,"it","en") -> NR
A181: OF0039818 | B181: 45688.639 | D181: F010036 | E181: BBC PLASTIK SRL | F181: 26AFI000263 | G181: 46071 | I181: 001110100002 | J181: BUSTA BOCC.40X40 SU ENTRAMBI I LATI VERSIONE GR55+HD | K181: accessori di confez. | L181: =VLOOKUP(K181,'COMM ITY- ENG'!A:B,2,FALSE) -> packaging accessories | N181: 19800 | O181: NR | Q181: =+R181/N181 -> 0.056 | R181: 1108.8 | S181: =IFERROR(VLOOKUP(J181,'DESC ITY - ENG'!B:C,2,FALSE),VLOOKUP(I181,'DESC ITY - ENG'!A:C,3,FALSE)) -> Punched Bag 40x40 cm Punched on Both Sides Version GR55+HD | T181: =VLOOKUP(S181,'DESC ITY - ENG'!C:D,2,FALSE) -> BAG- | U181: =_xlfn.TRANSLATE(S181,"en","zh-cht") -> 沙包 40x40 公分，兩面皆有打孔版本 GR55+HD | V181: =VLOOKUP(T181,'STANDARD COMM'!A:D,3,FALSE) -> Plastic | W181: =_xlfn.TRANSLATE(O181,"it","en") -> NR
A182: OF0039190 | B182: 45610.63 | D182: F010036 | E182: BBC PLASTIK SRL | F182: 26AFI000263 | G182: 46071 | I182: 001110106004 | J182: BUSTA BOCC.40X55 SU ENTRAMBI I LATI SENZA MARCATURA | K182: accessori di confez. | L182: =VLOOKUP(K182,'COMM ITY- ENG'!A:B,2,FALSE) -> packaging accessories | N182: 2200 | O182: NR | Q182: =+R182/N182 -> 0.0825 | R182: 181.5 | S182: =IFERROR(VLOOKUP(J182,'DESC ITY - ENG'!B:C,2,FALSE),VLOOKUP(I182,'DESC ITY - ENG'!A:C,3,FALSE)) -> Punched Bag 40x55 cm Punched on Both Sides No Marking | T182: =VLOOKUP(S182,'DESC ITY - ENG'!C:D,2,FALSE) -> BAG- | U182: =_xlfn.TRANSLATE(S182,"en","zh-cht") -> 沙包 40x55 公分，兩邊都打孔，無標記 | V182: =VLOOKUP(T182,'STANDARD COMM'!A:D,3,FALSE) -> Plastic | W182: =_xlfn.TRANSLATE(O182,"it","en") -> NR
... A208: OF0039822 | B208: 45680.57 | D208: F010077 | E208: CARBOCROM SRL CON UNICO SOCIO | F208: 26AFI000266 | G208: 46071 | I208: 002490001001 | J208: MONARCH 800 | K208: prodotti chimici | L208: =VLOOKUP(K208,'COMM ITY- ENG'!A:B,2,FALSE) -> chemical products | N208: 400 | O208: kg | Q208: =+R208/N208 -> 8.99 | R208: 3596 | S208: =IFERROR(VLOOKUP(J208,'DESC ITY - ENG'!B:C,2,FALSE),VLOOKUP(I208,'DESC ITY - ENG'!A:C,3,FALSE)) -> Carbon Black Monarch 800 | T208: =VLOOKUP(S208,'DESC ITY - ENG'!C:D,2,FALSE) -> INM- | U208: =_xlfn.TRANSLATE(S208,"en","zh-cht") -> 碳黑君主800 | V208: =VLOOKUP(T208,'STANDARD COMM'!A:D,3,FALSE) -> Coating | W208: =_xlfn.TRANSLATE(O208,"it","en") -> kg
A209: OF0039884 | D209: F600439 | E209: CARTON SRL | F209: 26AFI000267 | G209: 46071 | I209: 002030160001 | J209: STRISCIA CARTA BUL.52X27,5 GR90 STD FSC+LOGHI | K209: accessori di confez. | L209: =VLOOKUP(K209,'COMM ITY- ENG'!A:B,2,FALSE) -> packaging accessories | N209: 25000 | O209: NR | Q209: =+R209/N209 -> 0.017 | R209: 425 | S209: =IFERROR(VLOOKUP(J209,'DESC ITY - ENG'!B:C,2,FALSE),VLOOKUP(I209,'DESC ITY - ENG'!A:C,3,FALSE)) -> 5 GR90 STD FSC+LOGHIPaper Strip 52x27.5 cm 90g Standard FSC with Logos | T209: =VLOOKUP(S209,'DESC ITY - ENG'!C:D,2,FALSE) -> PAP- | U209: =_xlfn.TRANSLATE(S209,"en","zh-cht") -> 5 GR90 STD FSC+LOGHIPaper strip 52x27.5 cm 90g 標準 FSC 附標誌 | V209: =VLOOKUP(T209,'STANDARD COMM'!A:D,3,FALSE) -> Paper Material | W209: =_xlfn.TRANSLATE(O209,"it","en") -> NR
A210: OF0039884 | D210: F600439 | E210: CARTON SRL | F210: 26AFI000267 | G210: 46071 | I210: 002030161001 | J210: STRISCIA CARTA BUL.60X36,5 GR90 STD FSC+LOGHI | K210: accessori di confez. | L210: =VLOOKUP(K210,'COMM ITY- ENG'!A:B,2,FALSE) -> packaging accessories | N210: 30000 | O210: NR | Q210: =+R210/N210 -> 0.025 | R210: 750 | S210: =IFERROR(VLOOKUP(J210,'DESC ITY - ENG'!B:C,2,FALSE),VLOOKUP(I210,'DESC ITY - ENG'!A:C,3,FALSE)) -> 5 GR90 STD FSC+LOGHIPaper Strip 61X36.5 cm 90g Standard FSC with Logos | T210: =VLOOKUP(S210,'DESC ITY - ENG'!C:D,2,FALSE) -> PAP- | U210: =_xlfn.TRANSLATE(S210,"en","zh-cht") -> 5 GR90 STD FSC+LOGHIPaper strip 61X36.5 公分 90g 標準 FSC 附標誌 | V210: =VLOOKUP(T210,'STANDARD COMM'!A:D,3,FALSE) -> Paper Material | W210: =_xlfn.TRANSLATE(O210,"it","en") -> NR
A211: OF0039882 | B211: 45680.57 | D211: F014441 | E211: COOPERATIVA ALBANESI SCRL | F211: 26AFI000268 | G211: 46071 | I211: 000390103024 | J211: VITE 5MAX14 AC.AUTOM.ZIG.C/TORX T25 | K211: accessori x manigl. | L211: =VLOOKUP(K211,'COMM ITY- ENG'!A:B,2,FALSE) -> accessories for handles | N211: 23800 | O211: NR | Q211: =+R211/N211 -> 0.041 | R211: 975.8 | S211: =IFERROR(VLOOKUP(J211,'DESC ITY - ENG'!B:C,2,FALSE),VLOOKUP(I211,'DESC ITY - ENG'!A:C,3,FALSE)) -> 5x14 Auto Steel Knurled Screw w/ Torx T25 | T211: =VLOOKUP(S211,'DESC ITY - ENG'!C:D,2,FALSE) -> SCR- | U211: =_xlfn.TRANSLATE(S211,"en","zh-cht") -> 5x14 自動鋼製滾花螺絲，搭配 Torx T25 | V211: =VLOOKUP(T211,'STANDARD COMM'!A:D,3,FALSE) -> Fastener | W211: =_xlfn.TRANSLATE(O211,"it","en") -> NR
A212: OF0039767 | D212: F014441 | E212: COOPERATIVA ALBANESI SCRL | F212: 26AFI000268 | G212: 46071 | I212: 000390111001 | J212: VITE 5MAX16 AC TCB T9,5 C./TORX T25 | K212: accessori x manigl. | L212: =VLOOKUP(K212,'COMM ITY- ENG'!A:B,2,FALSE) -> accessories for handles | N212: 20000 | O212: NR | Q212: =+R212/N212 -> 0.0354 | R212: 708 | S212: =IFERROR(VLOOKUP(J212,'DESC ITY - ENG'!B:C,2,FALSE),VLOOKUP(I212,'DESC ITY - ENG'!A:C,3,FALSE)) -> Screw 5x16 mm Steel Cylindrical Button Head Torx T25 | T212: SCR- | U212: =_xlfn.TRANSLATE(S212,"en","zh-cht") -> 螺絲 5x16 毫米鋼製圓柱形按鈕頭 Torx T25 | V212: =VLOOKUP(T212,'STANDARD COMM'!A:D,3,FALSE) -> Fastener | W212: =_xlfn.TRANSLATE(O212,"it","en") -> NR
A213: OF0039502 | D213: F014441 | E213: COOPERATIVA ALBANESI SCRL | F213: 26AFI000268 | G213: 46071 | I213: 000390111024 | J213: VITE 5MAX16 ZN B.AUTOM.ZIG.C/TO.T25 | K213: accessori x manigl. | L213: =VLOOKUP(K213,'COMM ITY- ENG'!A:B,2,FALSE) -> accessories for handles | N213: 4044 | O213: NR | Q213: =+R213/N213 -> 0.01810089 | R213: 73.2 | S213: =IFERROR(VLOOKUP(J213,'DESC ITY - ENG'!B:C,2,FALSE),VLOOKUP(I213,'DESC ITY - ENG'!A:C,3,FALSE)) -> Screw 5x16 mm Steel Cylindrical Button Head Torx T25 | T213: SCR- | U213: =_xlfn.TRANSLATE(S213,"en","zh-cht") -> 螺絲 5x16 毫米鋼製圓柱形按鈕頭 Torx T25 | V213: =VLOOKUP(T213,'STANDARD COMM'!A:D,3,FALSE) -> Fastener | W213: =_xlfn.TRANSLATE(O213,"it","en") -> NR
A214: OF0039767 | B214: 45680.57 | D214: F014441 | E214: COOPERATIVA ALBANESI SCRL | F214: 26AFI000268 | G214: 46071 | I214: 000390115002 | J214: VITE 5MAX18 AC TCB T9,5 C./TORX T25 | K214: accessori x manigl. | L214: =VLOOKUP(K214,'COMM ITY- ENG'!A:B,2,FALSE) -> accessories for handles | N214: 20000 | O214: NR | Q214: =+R214/N214 -> 0.037 | R214: 740 | S214: =IFERROR(VLOOKUP(J214,'DESC ITY - ENG'!B:C,2,FALSE),VLOOKUP(I214,'DESC ITY - ENG'!A:C,3,FALSE)) -> Screw 5x16 mm Zinc Plated Self-Locking Knurled Torx T25 | T214: SCR- | U214: =_xlfn.TRANSLATE(S214,"en","zh-cht") -> 螺絲 5x16 毫米鍍鋅自鎖式刻紋 Torx T25 | V214: =VLOOKUP(T214,'STANDARD COMM'!A:D,3,FALSE) -> Fastener | W214: =_xlfn.TRANSLATE(O214,"it","en") -> NR
A215: OF0039767 | B215: 45680.57 | D215: F014441 | E215: COOPERATIVA ALBANESI SCRL | F215: 26AFI000268 | G215: 46071 | I215: 000390115006 | J215: VITE 5MAX18 AC.AUTOM.ZIG.C/TORX T25 | K215: accessori x manigl. | L215: =VLOOKUP(K215,'COMM ITY- ENG'!A:B,2,FALSE) -> accessories for handles | N215: 109400 | O215: NR | Q215: =+R215/N215 -> 0.037 | R215: 4047.8 | S215: =IFERROR(VLOOKUP(J215,'DESC ITY - ENG'!B:C,2,FALSE),VLOOKUP(I215,'DESC ITY - ENG'!A:C,3,FALSE)) -> Screw 5x18 mm Steel Self-Locking Knurled Torx T25 | T215: SCR- | U215: =_xlfn.TRANSLATE(S215,"en","zh-cht") -> 螺絲 5x18 毫米鋼製自鎖滾紋 T25 | V215: =VLOOKUP(T215,'STANDARD COMM'!A:D,3,FALSE) -> Fastener | W215: =_xlfn.TRANSLATE(O215,"it","en") -> NR
A216: OF0040240 | B216: 45680.57 | D216: F600081 | E216: DN CHEMICALS SRL | F216: 26AFI000269 | G216: 46071 | I216: 002460033001 | J216: DILUENTE NITRO CISTERNA | K216: prodotti chimici | L216: =VLOOKUP(K216,'COMM ITY- ENG'!A:B,2,FALSE) -> chemical products | N216: 779 | O216: kg | Q216: =+R216/N216 -> 2.1341463 | R216: 1662.5 | S216: =IFERROR(VLOOKUP(J216,'DESC ITY - ENG'!B:C,2,FALSE),VLOOKUP(I216,'DESC ITY - ENG'!A:C,3,FALSE)) -> Nitro Thinner Bulk TankNitro Thinner | T216: =VLOOKUP(S216,'DESC ITY - ENG'!C:D,2,FALSE) -> MISC | U216: =_xlfn.TRANSLATE(S216,"en","zh-cht") -> 硝化稀釋劑散裝槽硝化纖維稀釋劑 | V216: =VLOOKUP(T216,'STANDARD COMM'!A:D,3,FALSE) -> Misc | W216: =_xlfn.TRANSLATE(O216,"it","en") -> kg
A217: OF0040240 | B217: 45680.57 | D217: F600081 | E217: DN CHEMICALS SRL | F217: 26AFI000269 | G217: 46071 | I217: 009290028001 | J217: DILUENTE NITRO X PULIZIA LATTA | K217: materiali di consumo | L217: =VLOOKUP(K217,'COMM ITY- ENG'!A:B,2,FALSE) -> consumable materials | N217: 676.5 | O217: kg | Q217: =+R217/N217 -> 2.3780488 | R217: 1608.75 | S217: =IFERROR(VLOOKUP(J217,'DESC ITY - ENG'!B:C,2,FALSE),VLOOKUP(I217,'DESC ITY - ENG'!A:C,3,FALSE)) -> Nitro Thinner for Cleaning Tin CanNitro Thinner for Cleaning | T217: =VLOOKUP(S217,'DESC ITY - ENG'!C:D,2,FALSE) -> MISC | U217: =_xlfn.TRANSLATE(S217,"en","zh-cht") -> 用於清潔錫罐的硝化纖維稀釋劑用於清潔 | V217: =VLOOKUP(T217,'STANDARD COMM'!A:D,3,FALSE) -> Misc | W217: =_xlfn.TRANSLATE(O217,"it","en") -> kg
A218: OF0040372 | B218: 45580.643 | D218: F600081 | E218: DN CHEMICALS SRL | F218: 26AFI000327 | G218: 46071 | I218: 002460033001 | J218: DILUENTE NITRO CISTERNA | K218: prodotti chimici | L218: =VLOOKUP(K218,'COMM ITY- ENG'!A:B,2,FALSE) -> chemical products | N218: 779 | O218: kg | Q218: =+R218/N218 -> 2.1341463 | R218: 1662.5 | S218: =IFERROR(VLOOKUP(J218,'DESC ITY - ENG'!B:C,2,FALSE),VLOOKUP(I218,'DESC ITY - ENG'!A:C,3,FALSE)) -> Nitro Thinner Bulk TankNitro Thinner | T218: =VLOOKUP(S218,'DESC ITY - ENG'!C:D,2,FALSE) -> MISC | U218: =_xlfn.TRANSLATE(S218,"en","zh-cht") -> 硝化稀釋劑散裝槽硝化纖維稀釋劑 | V218: =VLOOKUP(T218,'STANDARD COMM'!A:D,3,FALSE) -> Misc | W218: =_xlfn.TRANSLATE(O218,"it","en") -> kg
A219: OF0040372 | B219: 45607.478 | D219: F600081 | E219: DN CHEMICALS SRL | F219: 26AFI000327 | G219: 46071 | I219: 009290028001 | J219: DILUENTE NITRO X PULIZIA LATTA | K219: materiali di consumo | L219: =VLOOKUP(K219,'COMM ITY- ENG'!A:B,2,FALSE) -> consumable materials | N219: 676.5 | O219: kg | Q219: =+R219/N219 -> 2.3780488 | R219: 1608.75 | S219: =IFERROR(VLOOKUP(J219,'DESC ITY - ENG'!B:C,2,FALSE),VLOOKUP(I219,'DESC ITY - ENG'!A:C,3,FALSE)) -> Nitro Thinner for Cleaning Tin CanNitro Thinner for Cleaning | T219: =VLOOKUP(S219,'DESC ITY - ENG'!C:D,2,FALSE) -> MISC | U219: =_xlfn.TRANSLATE(S219,"en","zh-cht") -> 用於清潔錫罐的硝化纖維稀釋劑用於清潔 | V219: =VLOOKUP(T219,'STANDARD COMM'!A:D,3,FALSE) -> Misc | W219: =_xlfn.TRANSLATE(O219,"it","en") -> kg
A220: OF0040015 | B220: 45642.488 | D220: F014073 | E220: DOTT.ALESSANDRO VIVALDA SRL | F220: 26AFI000328 | G220: 46071 | I220: 002490123019 | J220: EDELSTEIN Sunstone Champagne | K220: prodotti chimici | L220: =VLOOKUP(K220,'COMM ITY- ENG'!A:B,2,FALSE) -> chemical products | N220: 25 | O220: kg | Q220: =+R220/N220 -> 110 | R220: 2750 | S220: =IFERROR(VLOOKUP(J220,'DESC ITY - ENG'!B:C,2,FALSE),VLOOKUP(I220,'DESC ITY - ENG'!A:C,3,FALSE)) -> EDELSTEIN Sunstone Champagne | T220: =VLOOKUP(S220,'DESC ITY - ENG'!C:D,2,FALSE) -> INM- | U220: =_xlfn.TRANSLATE(S220,"en","zh-cht") -> EDELSTEIN 太陽石香檳 | V220: =VLOOKUP(T220,'STANDARD COMM'!A:D,3,FALSE) -> Coating | W220: =_xlfn.TRANSLATE(O220,"it","en") -> kg
A221: OF0040015 | B221: 45567.433 | D221: F014073 | E221: DOTT.ALESSANDRO VIVALDA SRL | F221: 26AFI000328 | G221: 46071 | I221: 002490143001 | J221: OSSIDO DI CROMO VERDE GN | K221: prodotti chimici | L221: =VLOOKUP(K221,'COMM ITY- ENG'!A:B,2,FALSE) -> chemical products | N221: 25 | O221: kg | Q221: =+R221/N221 -> 12.5 | R221: 312.5 | S221: =IFERROR(VLOOKUP(J221,'DESC ITY - ENG'!B:C,2,FALSE),VLOOKUP(I221,'DESC ITY - ENG'!A:C,3,FALSE)) -> Chromium Oxide Green GN | T221: =VLOOKUP(S221,'DESC ITY - ENG'!C:D,2,FALSE) -> INM- | U221: =_xlfn.TRANSLATE(S221,"en","zh-cht") -> 氧化鉻綠色GN | V221: =VLOOKUP(T221,'STANDARD COMM'!A:D,3,FALSE) -> Coating | W221: =_xlfn.TRANSLATE(O221,"it","en") -> kg
A222: OF0040373 | B222: 45607.478 | D222: F014073 | E222: DOTT.ALESSANDRO VIVALDA SRL | F222: 26AFI000328 | G222: 46071 | I222: 002490171001 | J222: BIOSSIDO DI TITANIO RC 833 (ex TR92) | K222: prodotti chimici | L222: =VLOOKUP(K222,'COMM ITY- ENG'!A:B,2,FALSE) -> chemical products | N222: 50 | O222: kg | Q222: =+R222/N222 -> 4.4 | R222: 220 | S222: =IFERROR(VLOOKUP(J222,'DESC ITY - ENG'!B:C,2,FALSE),VLOOKUP(I222,'DESC ITY - ENG'!A:C,3,FALSE)) -> Titanium Dioxide RC 833 (formerly TR92) | T222: =VLOOKUP(S222,'DESC ITY - ENG'!C:D,2,FALSE) -> INM- | U222: =_xlfn.TRANSLATE(S222,"en","zh-cht") -> 二氧化鈦 RC 833（前稱 TR92） | V222: =VLOOKUP(T222,'STANDARD COMM'!A:D,3,FALSE) -> Coating | W222: =_xlfn.TRANSLATE(O222,"it","en") -> kg
A223: OF0040341 | B223: 45680.57 | D223: F015068 | E223: ECOPROJECT TECHNOLOGIES SRL | F223: 26AFI000309 | G223: 46071 | I223: 009430043002 | J223: CARBONE PROWASTE 7119/S 20KG | K223: materiali di consumo | L223: =VLOOKUP(K223,'COMM ITY- ENG'!A:B,2,FALSE) -> consumable materials | N223: 4000 | O223: kg | Q223: =+R223/N223 -> 2 | R223: 8000 | S223: =IFERROR(VLOOKUP(J223,'DESC ITY - ENG'!B:C,2,FALSE),VLOOKUP(I223,'DESC ITY - ENG'!A:C,3,FALSE)) -> Carbon Prowaste 7119/S 20kg BagCarbon | T223: =VLOOKUP(S223,'DESC ITY - ENG'!C:D,2,FALSE) -> MISC | U223: =_xlfn.TRANSLATE(S223,"en","zh-cht") -> 碳廢棄物 7119/S 20公斤 BagCarbon | V223: =VLOOKUP(T223,'STANDARD COMM'!A:D,3,FALSE) -> Misc | W223: =_xlfn.TRANSLATE(O223,"it","en") -> kg
A224: OF0040341 | B224: 45680.57 | D224: F015068 | E224: ECOPROJECT TECHNOLOGIES SRL | F224: 26AFI000309 | G224: 46071 | I224: 009430043006 | J224: COAGULANTE PROWASTE 9124 ECOPROJ. | K224: materiali di consumo | L224: =VLOOKUP(K224,'COMM ITY- ENG'!A:B,2,FALSE) -> consumable materials | N224: 1200 | O224: kg | Q224: =+R224/N224 -> 2.05 | R224: 2460 | S224: =IFERROR(VLOOKUP(J224,'DESC ITY - ENG'!B:C,2,FALSE),VLOOKUP(I224,'DESC ITY - ENG'!A:C,3,FALSE)) -> Coagulant Prowaste 9124 EcoprojCoagulant | T224: =VLOOKUP(S224,'DESC ITY - ENG'!C:D,2,FALSE) -> MISC | U224: =_xlfn.TRANSLATE(S224,"en","zh-cht") -> 凝血劑 Prowaste 9124 EcoprojCoagulant | V224: =VLOOKUP(T224,'STANDARD COMM'!A:D,3,FALSE) -> Misc | W224: =_xlfn.TRANSLATE(O224,"it","en") -> kg
A225: OF0040235 | B225: 45680.57 | D225: F010134 | E225: EIGENMANN & VERONELLI SPA | F225: 26AFI000312 | G225: 46071 | I225: 002340514003 | J225: ACEMATT OK-390 opacizzante | K225: prodotti chimici | L225: =VLOOKUP(K225,'COMM ITY- ENG'!A:B,2,FALSE) -> chemical products | N225: 20 | O225: kg | Q225: =+R225/N225 -> 11.5 | R225: 230 | S225: =IFERROR(VLOOKUP(J225,'DESC ITY - ENG'!B:C,2,FALSE),VLOOKUP(I225,'DESC ITY - ENG'!A:C,3,FALSE)) -> Acematt OK-390 Matting Agent | T225: =VLOOKUP(S225,'DESC ITY - ENG'!C:D,2,FALSE) -> INM- | U225: =_xlfn.TRANSLATE(S225,"en","zh-cht") -> Acematt OK-390 打結劑 | V225: =VLOOKUP(T225,'STANDARD COMM'!A:D,3,FALSE) -> Coating | W225: =_xlfn.TRANSLATE(O225,"it","en") -> kg
A226: OF0040243 | B226: 45666.598 | D226: F600481 | E226: KRAHN ITALIA SPA | F226: 26AFI000332 | G226: 46071 | I226: 002490018001 | J226: MEARLIN SPARKLE GOLD 9212P | K226: prodotti chimici | L226: =VLOOKUP(K226,'COMM ITY- ENG'!A:B,2,FALSE) -> chemical products | N226: 50 | O226: kg | Q226: =+R226/N226 -> 24.8 | R226: 1240 | S226: =IFERROR(VLOOKUP(J226,'DESC ITY - ENG'!B:C,2,FALSE),VLOOKUP(I226,'DESC ITY - ENG'!A:C,3,FALSE)) -> Pigment Mearlin Sparkle Gold 9212P | T226: =VLOOKUP(S226,'DESC ITY - ENG'!C:D,2,FALSE) -> INM- | U226: =_xlfn.TRANSLATE(S226,"en","zh-cht") -> 顏料 Mearlin 閃耀金色 9212P | V226: =VLOOKUP(T226,'STANDARD COMM'!A:D,3,FALSE) -> Coating | W226: =_xlfn.TRANSLATE(O226,"it","en") -> kg
A227: OF0039909 | B227: 45665.343 | D227: F010233 | E227: LA TERMOPLASTIC-F.B.M. SRL | F227: 26AFI000260 | G227: 46071 | I227: 000110534001 | J227: GHIERA P15 15,5/28 R15/827 FR100 | K227: manigliame | L227: =VLOOKUP(K227,'COMM ITY- ENG'!A:B,2,FALSE) -> handles | N227: 5680 | O227: NR | Q227: =+R227/N227 -> 0.1045 | R227: 593.56 | S227: =IFERROR(VLOOKUP(J227,'DESC ITY - ENG'!B:C,2,FALSE),VLOOKUP(I227,'DESC ITY - ENG'!A:C,3,FALSE)) -> 5/33 R15/295 FR100Ring Nut P15 15.5/33mm R15/295 FR100 [cite: 4] | T227: =VLOOKUP(S227,'DESC ITY - ENG'!C:D,2,FALSE) -> NUT- | U227: =_xlfn.TRANSLATE(S227,"en","zh-cht") -> 5/33 R15/295 FR100環形螺母 P15 15.5/33mm R15/295 FR100 [引用：4] | V227: =VLOOKUP(T227,'STANDARD COMM'!A:D,3,FALSE) -> Fastener | W227: =_xlfn.TRANSLATE(O227,"it","en") -> NR
... A340: OF0039943 | B340: 45618.468 | D340: F015859 | E340: F.LLI GIOVANNINI SRL | F340: 26AFI000257 | G340: 46053 | I340: 001513484571 | J340: BOX 3484/571* CM39X22,5X15,5 | K340: cartoni e casse | L340: =VLOOKUP(K340,'COMM ITY- ENG'!A:B,2,FALSE) -> cartons and boxes | N340: 989 | O340: NR | Q340: =+R340/N340 -> 0.35899899 | R340: 355.05 | S340: =IFERROR(VLOOKUP(J340,'DESC ITY - ENG'!B:C,2,FALSE),VLOOKUP(I340,'DESC ITY - ENG'!A:C,3,FALSE)) -> BOX 3484/571* CM39X22,5X15,5 | T340: =VLOOKUP(S340,'DESC ITY - ENG'!C:D,2,FALSE) -> BOX- | U340: =_xlfn.TRANSLATE(S340,"en","zh-cht") -> 郵箱3484/571* CM39X22,5X15,5 | V340: =VLOOKUP(T340,'STANDARD COMM'!A:D,3,FALSE) -> Paper Material | W340: =_xlfn.TRANSLATE(O340,"it","en") -> NR
A341: OF0039768 | B341: 45618.468 | D341: F015859 | E341: F.LLI GIOVANNINI SRL | F341: 26AFI000257 | G341: 46053 | I341: 001513484641 | J341: BOX 3484/641 CM39X22,5X15,5 | K341: cartoni e casse | L341: =VLOOKUP(K341,'COMM ITY- ENG'!A:B,2,FALSE) -> cartons and boxes | N341: 255 | O341: NR | Q341: =+R341/N341 -> 0.48901961 | R341: 124.7 | S341: =IFERROR(VLOOKUP(J341,'DESC ITY - ENG'!B:C,2,FALSE),VLOOKUP(I341,'DESC ITY - ENG'!A:C,3,FALSE)) -> BOX 3484/641 CM39X22,5X15,5 | T341: =VLOOKUP(S341,'DESC ITY - ENG'!C:D,2,FALSE) -> BOX- | U341: =_xlfn.TRANSLATE(S341,"en","zh-cht") -> 郵箱3484/641 CM39X22,5X15,5 | V341: =VLOOKUP(T341,'STANDARD COMM'!A:D,3,FALSE) -> Paper Material
A342: OF0039472 | B342: 45618.468 | D342: F015859 | E342: F.LLI GIOVANNINI SRL | F342: 26AFI000257 | G342: 46053 | I342: 001513484650 | J342: BOX 3484/650 CM39X22,5X15,5 | K342: cartoni e casse | L342: =VLOOKUP(K342,'COMM ITY- ENG'!A:B,2,FALSE) -> cartons and boxes | N342: 256 | O342: NR | Q342: =+R342/N342 -> 0.49 | R342: 125.44 | S342: =IFERROR(VLOOKUP(J342,'DESC ITY - ENG'!B:C,2,FALSE),VLOOKUP(I342,'DESC ITY - ENG'!A:C,3,FALSE)) -> BOX 3484/650 CM39X22,5X15,5 | T342: =VLOOKUP(S342,'DESC ITY - ENG'!C:D,2,FALSE) -> BOX- | U342: =_xlfn.TRANSLATE(S342,"en","zh-cht") -> 箱子3484/650 CM39X22,5X15,5 | V342: =VLOOKUP(T342,'STANDARD COMM'!A:D,3,FALSE) -> Paper Material
A343: OF0039943 | B343: 45630.442 | D343: F015859 | E343: F.LLI GIOVANNINI SRL | F343: 26AFI000257 | G343: 46053 | I343: 001513484650 | J343: BOX 3484/650 CM39X22,5X15,5 | K343: cartoni e casse | L343: =VLOOKUP(K343,'COMM ITY- ENG'!A:B,2,FALSE) -> cartons and boxes | N343: 256 | O343: NR | Q343: =+R343/N343 -> 0.48898438 | R343: 125.18 | S343: =IFERROR(VLOOKUP(J343,'DESC ITY - ENG'!B:C,2,FALSE),VLOOKUP(I343,'DESC ITY - ENG'!A:C,3,FALSE)) -> BOX 3484/650 CM39X22,5X15,5 | T343: =VLOOKUP(S343,'DESC ITY - ENG'!C:D,2,FALSE) -> BOX- | U343: =_xlfn.TRANSLATE(S343,"en","zh-cht") -> 箱子3484/650 CM39X22,5X15,5 | V343: =VLOOKUP(T343,'STANDARD COMM'!A:D,3,FALSE) -> Paper Material
A344: OF0039593 | B344: 45666.409 | D344: F015859 | E344: F.LLI GIOVANNINI SRL | F344: 26AFI000257 | G344: 46053 | I344: 001513484652 | J344: BOX 3484/652 CM39X22,5X15,5 | K344: cartoni e casse | L344: =VLOOKUP(K344,'COMM ITY- ENG'!A:B,2,FALSE) -> cartons and boxes | N344: 256 | O344: NR | Q344: =+R344/N344 -> 0.48898438 | R344: 125.18 | S344: =IFERROR(VLOOKUP(J344,'DESC ITY - ENG'!B:C,2,FALSE),VLOOKUP(I344,'DESC ITY - ENG'!A:C,3,FALSE)) -> BOX 3484/652 CM39X22,5X15,5 | T344: =VLOOKUP(S344,'DESC ITY - ENG'!C:D,2,FALSE) -> BOX- | U344: =_xlfn.TRANSLATE(S344,"en","zh-cht") -> 郵箱3484/652 CM39X22,5X15,5 | V344: =VLOOKUP(T344,'STANDARD COMM'!A:D,3,FALSE) -> Paper Material
A345: OF0039405 | B345: 45645.574 | D345: F015859 | E345: F.LLI GIOVANNINI SRL | F345: 26AFI000257 | G345: 46053 | I345: 001513486183 | J345: BOX 3486/183*CM47X30,5X15 | K345: cartoni e casse | L345: =VLOOKUP(K345,'COMM ITY- ENG'!A:B,2,FALSE) -> cartons and boxes | N345: 1749 | O345: NR | Q345: =+R345/N345 -> 0.44 | R345: 769.56 | S345: =IFERROR(VLOOKUP(J345,'DESC ITY - ENG'!B:C,2,FALSE),VLOOKUP(I345,'DESC ITY - ENG'!A:C,3,FALSE)) -> BOX 3486/183*CM47X30,5X15 | T345: =VLOOKUP(S345,'DESC ITY - ENG'!C:D,2,FALSE) -> BOX- | U345: =_xlfn.TRANSLATE(S345,"en","zh-cht") -> 郵箱3486/183*CM47X30,5X15 | V345: =VLOOKUP(T345,'STANDARD COMM'!A:D,3,FALSE) -> Paper Material
A346: OF0039593 | B346: 45646.423 | D346: F015859 | E346: F.LLI GIOVANNINI SRL | F346: 26AFI000257 | G346: 46053 | I346: 001513486194 | J346: BOX 3486/194 CM47X30,5X15 | K346: cartoni e casse | L346: =VLOOKUP(K346,'COMM ITY- ENG'!A:B,2,FALSE) -> cartons and boxes | N346: 357 | O346: NR | Q346: =+R346/N346 -> 0.6210084 | R346: 221.7 | S346: =IFERROR(VLOOKUP(J346,'DESC ITY - ENG'!B:C,2,FALSE),VLOOKUP(I346,'DESC ITY - ENG'!A:C,3,FALSE)) -> BOX 3486/194 CM47X30,5X15 | T346: =VLOOKUP(S346,'DESC ITY - ENG'!C:D,2,FALSE) -> BOX- | U346: =_xlfn.TRANSLATE(S346,"en","zh-cht") -> 箱號3486/194 CM47X30,5X15 | V346: =VLOOKUP(T346,'STANDARD COMM'!A:D,3,FALSE) -> Paper Material
A347: OF0039768 | B347: 45646.423 | D347: F015859 | E347: F.LLI GIOVANNINI SRL | F347: 26AFI000257 | G347: 46053 | I347: 001513486194 | J347: BOX 3486/194 CM47X30,5X15 | K347: cartoni e casse | L347: =VLOOKUP(K347,'COMM ITY- ENG'!A:B,2,FALSE) -> cartons and boxes | N347: 194 | O347: NR | Q347: =+R347/N347 -> 0.68097938 | R347: 132.11 | S347: =IFERROR(VLOOKUP(J347,'DESC ITY - ENG'!B:C,2,FALSE),VLOOKUP(I347,'DESC ITY - ENG'!A:C,3,FALSE)) -> BOX 3486/194 CM47X30,5X15 | T347: =VLOOKUP(S347,'DESC ITY - ENG'!C:D,2,FALSE) -> BOX- | U347: =_xlfn.TRANSLATE(S347,"en","zh-cht") -> 箱號3486/194 CM47X30,5X15 | V347: =VLOOKUP(T347,'STANDARD COMM'!A:D,3,FALSE) -> Paper Material
A348: OF0039768 | B348: 45646.423 | D348: F015859 | E348: F.LLI GIOVANNINI SRL | F348: 26AFI000257 | G348: 46053 | I348: 001513495010 | J348: BOX 3495/010 CM49X28,5X19 T.GIAPP. | K348: cartoni e casse | L348: =VLOOKUP(K348,'COMM ITY- ENG'!A:B,2,FALSE) -> cartons and boxes | N348: 255 | O348: NR | Q348: =+R348/N348 -> 0.638 | R348: 162.69 | S348: =IFERROR(VLOOKUP(J348,'DESC ITY - ENG'!B:C,2,FALSE),VLOOKUP(I348,'DESC ITY - ENG'!A:C,3,FALSE)) -> BOX 3495/010 CM49X28,5X19 T.GIAPP. | T348: =VLOOKUP(S348,'DESC ITY - ENG'!C:D,2,FALSE) -> BOX- | U348: =_xlfn.TRANSLATE(S348,"en","zh-cht") -> 郵箱3495/010 CM49X28,5X19 T.GIAPP。 | V348: =VLOOKUP(T348,'STANDARD COMM'!A:D,3,FALSE) -> Paper Material
A349: OF0039472 | B349: 45646.423 | D349: F015859 | E349: F.LLI GIOVANNINI SRL | F349: 26AFI000257 | G349: 46053 | I349: 001513742000 | J349: BOX 3742/000 CM39X38,5X15 | K349: cartoni e casse | L349: =VLOOKUP(K349,'COMM ITY- ENG'!A:B,2,FALSE) -> cartons and boxes | N349: 1020 | O349: NR | Q349: =+R349/N349 -> 0.53 | R349: 540.6 | S349: =IFERROR(VLOOKUP(J349,'DESC ITY - ENG'!B:C,2,FALSE),VLOOKUP(I349,'DESC ITY - ENG'!A:C,3,FALSE)) -> BOX 3742/000 CM39X38,5X15 | T349: =VLOOKUP(S349,'DESC ITY - ENG'!C:D,2,FALSE) -> BOX- | U349: =_xlfn.TRANSLATE(S349,"en","zh-cht") -> 郵箱3742/000 CM39X38,5X15 | V349: =VLOOKUP(T349,'STANDARD COMM'!A:D,3,FALSE) -> Paper Material
A350: OF0039768 | B350: 45646.423 | D350: F015859 | E350: F.LLI GIOVANNINI SRL | F350: 26AFI000257 | G350: 46053 | I350: 001513742000 | J350: BOX 3742/000 CM39X38,5X15 | K350: cartoni e casse | L350: =VLOOKUP(K350,'COMM ITY- ENG'!A:B,2,FALSE) -> cartons and boxes | N350: 2025 | O350: NR | Q350: =+R350/N350 -> 0.53 | R350: 1073.25 | S350: =IFERROR(VLOOKUP(J350,'DESC ITY - ENG'!B:C,2,FALSE),VLOOKUP(I350,'DESC ITY - ENG'!A:C,3,FALSE)) -> BOX 3742/000 CM39X38,5X15 | T350: =VLOOKUP(S350,'DESC ITY - ENG'!C:D,2,FALSE) -> BOX- | U350: =_xlfn.TRANSLATE(S350,"en","zh-cht") -> 郵箱3742/000 CM39X38,5X15 | V350: =VLOOKUP(T350,'STANDARD COMM'!A:D,3,FALSE) -> Paper Material
A351: OF0039943 | B351: 45646.423 | D351: F015859 | E351: F.LLI GIOVANNINI SRL | F351: 26AFI000257 | G351: 46053 | I351: 001513742000 | J351: BOX 3742/000 CM39X38,5X15 | K351: cartoni e casse | L351: =VLOOKUP(K351,'COMM ITY- ENG'!A:B,2,FALSE) -> cartons and boxes | N351: 596 | O351: NR | Q351: =+R351/N351 -> 0.53 | R351: 315.88 | S351: =IFERROR(VLOOKUP(J351,'DESC ITY - ENG'!B:C,2,FALSE),VLOOKUP(I351,'DESC ITY - ENG'!A:C,3,FALSE)) -> BOX 3742/000 CM39X38,5X15 | T351: =VLOOKUP(S351,'DESC ITY - ENG'!C:D,2,FALSE) -> BOX- | U351: =_xlfn.TRANSLATE(S351,"en","zh-cht") -> 郵箱3742/000 CM39X38,5X15 | V351: =VLOOKUP(T351,'STANDARD COMM'!A:D,3,FALSE) -> Paper Material
A352: OF0039768 | B352: 45646.423 | D352: F015859 | E352: F.LLI GIOVANNINI SRL | F352: 26AFI000257 | G352: 46053 | I352: 001513742249 | J352: BOX 3742/249* CM39X38,5X15 | K352: cartoni e casse | L352: =VLOOKUP(K352,'COMM ITY- ENG'!A:B,2,FALSE) -> cartons and boxes | N352: 720 | O352: NR | Q352: =+R352/N352 -> 0.589 | R352: 424.08 | S352: =IFERROR(VLOOKUP(J352,'DESC ITY - ENG'!B:C,2,FALSE),VLOOKUP(I352,'DESC ITY - ENG'!A:C,3,FALSE)) -> BOX 3742/249* CM39X38,5X15 | T352: =VLOOKUP(S352,'DESC ITY - ENG'!C:D,2,FALSE) -> BOX- | U352: =_xlfn.TRANSLATE(S352,"en","zh-cht") -> 第3742/249號箱 CM39X38,5X15 | V352: =VLOOKUP(T352,'STANDARD COMM'!A:D,3,FALSE) -> Paper Material
... A378: OF0040018 | B378: 45621.455 | D378: F600882 | E378: GENERAL ABRASIVI SRL | F378: 26AFI000096 | G378: 46053 | I378: 002495000001 | J378: POLVERE DI TITANIO X RIPORTO K614 | K378: prodotti chimici | L378: =VLOOKUP(K378,'COMM ITY- ENG'!A:B,2,FALSE) -> chemical products | N378: 1000 | O378: kg | Q378: =+R378/N378 -> 9.25 | R378: 9250 | S378: =IFERROR(VLOOKUP(J378,'DESC ITY - ENG'!B:C,2,FALSE),VLOOKUP(I378,'DESC ITY - ENG'!A:C,3,FALSE)) -> Titanium Powder for Hardfacing/Overlay K614 | T378: =VLOOKUP(S378,'DESC ITY - ENG'!C:D,2,FALSE) -> INM- | U378: =_xlfn.TRANSLATE(S378,"en","zh-cht") -> 用於硬面/疊加的鈦粉 K614 | V378: =VLOOKUP(T378,'STANDARD COMM'!A:D,3,FALSE) -> Coating
A379: OF0039832 | B379: 45546.654 | D379: F600113 | E379: GUJARAT FLUOROCHEMICALS GMBH | F379: 26AFC000011 | G379: 46053 | I379: 002370001007 | J379: INOFLON AD9400EX PTFE DISP. (T. TF 5135) | K379: prodotti chimici | L379: =VLOOKUP(K379,'COMM ITY- ENG'!A:B,2,FALSE) -> chemical products | N379: 1500 | O379: kg | Q379: =+R379/N379 -> 10.75 | R379: 16125 | S379: =IFERROR(VLOOKUP(J379,'DESC ITY - ENG'!B:C,2,FALSE),VLOOKUP(I379,'DESC ITY - ENG'!A:C,3,FALSE)) -> PTFE Dispersion Inoflon AD9400EX (equiv. TF 5135) | T379: INM- | U379: =_xlfn.TRANSLATE(S379,"en","zh-cht") -> PTFE 分散依諾氟AD9400EX（等效 TF 5135） | V379: =VLOOKUP(T379,'STANDARD COMM'!A:D,3,FALSE) -> Coating
A380: OF0039832 | B380: 45559.363 | D380: F600113 | E380: GUJARAT FLUOROCHEMICALS GMBH | F380: 26AFC000011 | G380: 46053 | I380: 002370064004 | J380: INOFLON PFA 8900EX (T. PFA 6900GZ) | K380: prodotti chimici | L380: =VLOOKUP(K380,'COMM ITY- ENG'!A:B,2,FALSE) -> chemical products | N380: 80 | O380: kg | Q380: =+R380/N380 -> 23.28 | R380: 1862.4 | S380: =IFERROR(VLOOKUP(J380,'DESC ITY - ENG'!B:C,2,FALSE),VLOOKUP(I380,'DESC ITY - ENG'!A:C,3,FALSE)) -> PFA Coating Inoflon 8900EX (equiv. PFA 6900GZ) | T380: INM- | U380: =_xlfn.TRANSLATE(S380,"en","zh-cht") -> PFA 塗層 Inoflon 8900EX（相當於 PFA 6900GZ） | V380: =VLOOKUP(T380,'STANDARD COMM'!A:D,3,FALSE) -> Coating
A381: OF0039469 | B381: 45628.693 | D381: F600780 | E381: GULBAK BAKALIT METAL VE TEKSTIL SAN. ve TIC. LTD. STI | F381: 26AFF000015 | G381: 46053 | I381: 000281710001 | J381: MANICO AC.SOLE CORTO C/LOGO MC AISI 430 SABBIATO PAD.279 20 | K381: manigliame | L381: =VLOOKUP(K381,'COMM ITY- ENG'!A:B,2,FALSE) -> handles | N381: 4500 | O381: NR | Q381: =+R381/N381 -> 1.137 | R381: 5116.5 | S381: =IFERROR(VLOOKUP(J381,'DESC ITY - ENG'!B:C,2,FALSE),VLOOKUP(I381,'DESC ITY - ENG'!A:C,3,FALSE)) -> Steel Handle AC.SOLE Short w/Logo MC AISI 430 Pan 279-20 Sandblasted [cite: 4] | T381: =VLOOKUP(S381,'DESC ITY - ENG'!C:D,2,FALSE) -> SHDL | U381: =_xlfn.TRANSLATE(S381,"en","zh-cht") -> 鋼柄冷氣。鞋底短管附標誌 MC AISI 430 Pan 279-20 噴砂處理 [引用：4] | V381: =VLOOKUP(T381,'STANDARD COMM'!A:D,3,FALSE) -> Fittings
A382: OF0039469 | B382: 45628.693 | D382: F600780 | E382: GULBAK BAKALIT METAL VE TEKSTIL SAN. ve TIC. LTD. STI | F382: 26AFF000015 | G382: 46053 | I382: 000281710002 | J382: MANICO AC.SOLE CORTO C/LOGO MC AISI 430 SABBIATO PAD.279 24 | K382: manigliame | L382: =VLOOKUP(K382,'COMM ITY- ENG'!A:B,2,FALSE) -> handles | N382: 4000 | O382: NR | Q382: =+R382/N382 -> 1.137 | R382: 4548 | S382: =IFERROR(VLOOKUP(J382,'DESC ITY - ENG'!B:C,2,FALSE),VLOOKUP(I382,'DESC ITY - ENG'!A:C,3,FALSE)) -> Steel Handle AC.SOLE Short w/Logo MC AISI 430 Pan 279-24 Sandblasted [cite: 4] | T382: =VLOOKUP(S382,'DESC ITY - ENG'!C:D,2,FALSE) -> SHDL | U382: =_xlfn.TRANSLATE(S382,"en","zh-cht") -> 鋼柄冷氣。獨短帶標誌 MC AISI 430 Pan 279-24 噴砂處理 [引用：4] | V382: =VLOOKUP(T382,'STANDARD COMM'!A:D,3,FALSE) -> Fittings
A383: OF0039469 | B383: 45628.693 | D383: F600780 | E383: GULBAK BAKALIT METAL VE TEKSTIL SAN. ve TIC. LTD. STI | F383: 26AFF000015 | G383: 46053 | I383: 000281710003 | J383: MANICO AC.SOLE CORTO C/LOGO MC AISI 430 SABBIATO CAS.433 16 | K383: manigliame | L383: =VLOOKUP(K383,'COMM ITY- ENG'!A:B,2,FALSE) -> handles | N383: 3000 | O383: NR | Q383: =+R383/N383 -> 1.137 | R383: 3411 | S383: =IFERROR(VLOOKUP(J383,'DESC ITY - ENG'!B:C,2,FALSE),VLOOKUP(I383,'DESC ITY - ENG'!A:C,3,FALSE)) -> Steel Handle AC.SOLE Short w/Logo MC AISI 430 Casserole 433-16 Sandblasted [cite: 4] | T383: =VLOOKUP(S383,'DESC ITY - ENG'!C:D,2,FALSE) -> SHDL | U383: =_xlfn.TRANSLATE(S383,"en","zh-cht") -> 鋼柄冷氣。獨角短褲附標誌 MC AISI 430 砂鍋 433-16 砂磨 [引用：4] | V383: =VLOOKUP(T383,'STANDARD COMM'!A:D,3,FALSE) -> Fittings
A384: OF0039469 | B384: 45645.587 | D384: F600780 | E384: GULBAK BAKALIT METAL VE TEKSTIL SAN. ve TIC. LTD. STI | F384: 26AFF000015 | G384: 46053 | I384: 000281710005 | J384: MANICO AC.SOLE LUNGO C/LOGO MC AISI 430 SABBIATO PAD.279 30 | K384: manigliame | L384: =VLOOKUP(K384,'COMM ITY- ENG'!A:B,2,FALSE) -> handles | N384: 2000 | O384: NR | Q384: =+R384/N384 -> 1.227 | R384: 2454 | S384: =IFERROR(VLOOKUP(J384,'DESC ITY - ENG'!B:C,2,FALSE),VLOOKUP(I384,'DESC ITY - ENG'!A:C,3,FALSE)) -> Steel Handle AC.SOLE Long w/Logo MC AISI 430 Pan 279-30 Sandblasted [cite: 4] | T384: HDL- | U384: =_xlfn.TRANSLATE(S384,"en","zh-cht") -> 鋼柄冷氣。鞋底長款，附 MC 標誌 AISI 430 Pan 279-30 噴砂處理 [引用：4] | V384: =VLOOKUP(T384,'STANDARD COMM'!A:D,3,FALSE) -> Fittings
...

Sheet STANDARD COMM
A1: Commodity Code | B1: Commodity Description | C1: Commodity Group (MIL) | D1: Commodity Group (MIL)
A2: EXM- | B2: EXTR TREAT MATERIAL | C2: Coating | D2: =_xlfn.TRANSLATE(C2,"en","zh-cht") -> 塗層
A3: INM- | B3: INTR TREAT MATERIAL | C3: Coating | D3: =_xlfn.TRANSLATE(C3,"en","zh-cht") -> 塗層
A4: SILK | B4: SILK SCREEN MATERIAL | C4: Coating | D4: =_xlfn.TRANSLATE(C4,"en","zh-cht") -> 塗層
A5: BFIT | B5: ELE BULK FITG | C5: Electric Material | D5: =_xlfn.TRANSLATE(C5,"en","zh-cht") -> 電材料
A6: CORD | B6: POWER CORD | C6: Electric Material | D6: =_xlfn.TRANSLATE(C6,"en","zh-cht") -> 電材料
A7: ELCO | B7: ELE COMPONENT | C7: Electric Material | D7: =_xlfn.TRANSLATE(C7,"en","zh-cht") -> 電材料
A8: HS-- | B8: HEAT SHIELD | C8: Electric Material | D8: =_xlfn.TRANSLATE(C8,"en","zh-cht") -> 電材料
A9: HTEL | B9: HEAT ELEMENT | C9: Electric Material | D9: =_xlfn.TRANSLATE(C9,"en","zh-cht") -> 電材料
A10: LAMP | B10: LAMP (LED/NEON) | C10: Electric Material | D10: =_xlfn.TRANSLATE(C10,"en","zh-cht") -> 電材料
A11: PROB | B11: PROBE MATERIAL | C11: Electric Material | D11: =_xlfn.TRANSLATE(C11,"en","zh-cht") -> 電材料
A12: RUCO | B12: RUBBER COMPONENTS | C12: Electric Material | D12: =_xlfn.TRANSLATE(C12,"en","zh-cht") -> 電材料
A13: SIRM | B13: SILICONE RUBBER MATL | C13: Electric Material | D13: =_xlfn.TRANSLATE(C13,"en","zh-cht") -> 電材料
... A79: WIP- | B79: WORK IN PROGRESS | C79: Work In Progress | D79: =_xlfn.TRANSLATE(C79,"en","zh-cht") -> 進行中
A80: Showing 1 to 78 of 78 entries
A81: Previous
A82: 1
A83: Next
A84: Copyright © 2026 Meyer Manufacturing Company Ltd. All rights reserved.

Sheet COMM ITY- ENG
A2: Italian | B2: English
A3: accessori di confez. | B3: packaging accessories
A4: accessori finiti | B4: finished accessories
A5: accessori x manigl. | B5: accessories for handles
A6: acciaio | B6: steel
A7: Acciaio multistrato (5PLY) | B7: multilayer steel (5PLY)
A8: alluminio | B8: aluminium
A9: cartoni e casse | B9: cartons and boxes
A10: manigliame | B10: handles
A11: mater. di confezion. | B11: packaging material
A12: mater.aus.varie acq. | B12: various auxiliary materials purchased
A13: materiali di consumo | B13: consumable materials
... A16: semilavorato | B16: semi-finished product

Sheet DESC ITY - ENG
A1: Item Code | B1: Part Description | C1: Translated Part Description (English) | D1: StandardCommodityCode
A2: 000288100051 | B2: 1-5-HSI103C-Y SI HANDLE 16CM SAUCEPAN... | C2: 1-5 SI Handle 16cm Saucepan (6.5mm hole) | D2: HDL-
A3: 000288100051 | B3: 1-5-HSI103C-Y SI HANDLE 16CM SAUCEPAN... | C3: 1-5 SI Handle 16cm Saucepan (6.5mm hole) | D3: HDL-
A4: 000288100052 | B4: 1-5-HSI105C-Y SI HANDLE 20CM SAUCEPAN... | C4: 1-5 SI Handle 20cm Saucepan (6.5mm hole) | D4: HDL-
A5: 000288100052 | B5: 1-5-HSI105C-Y SI HANDLE 20CM SAUCEPAN... | C5: 1-5 SI Handle 20cm Saucepan (6.5mm hole) | D5: HDL-
A6: 000288100055 | B6: 1-5-HSI203C-Y SI HANDLE 20CM SKILLET... | C6: 1-5 SI Handle 20cm Skillet (6.5mm hole) | D6: HDL-
A7: 000288100055 | B7: 1-5-HSI203C-Y SI HANDLE 20CM SKILLET... | C7: 1-5 SI Handle 20cm Skillet (6.5mm hole) | D7: HDL-
A8: 000288100053 | B8: 1-5-HSI107C-Y SI HANDLE 24CM SAUCIER... | C8: 1-5 SI Handle 24cm Saucier (6.5mm hole) | D8: HDL-
A9: 000288100053 | B9: 1-5-HSI107C-Y SI HANDLE 24CM SAUCIER... | C9: 1-5 SI Handle 24cm Saucier (6.5mm hole) | D9: HDL-
A10: 000288100054 | B10: 1-5-HSI108C-Y SI HANDLE 26CM SAUTE'... | C10: 1-5 SI Handle 26cm Saute (6.5mm hole) | D10: HDL-
A11: 000288100054 | B11: 1-5-HSI108C-Y SI HANDLE 26CM SAUTE'... | C11: 1-5 SI Handle 26cm Saute (6.5mm hole) | D11: HDL-
A12: 000288100056 | B12: 1-5-HSI206C-Y SI HANDLE 26CM SKILLET... | C12: 1-5 SI Handle 26cm Skillet (6.5mm hole) | D12: HDL-
... A63: 000030385027 | B63: DISCO 5PLY 385/27 SS304 0,4 + Al1,8 + SS439 0,5 TOT 27/10 | C63: 5-Ply Disc SS304/AL/SS439 385mm x 2.7mm Total Thickness 2.7mm [cite: 1] | D63: CDM-
A64: 000030470023 | B64: DISCO 5PLY 470/23 SS304 0,4 + Al1,4 + SS439 0,5 TOT 23/10 | C64: 5-Ply Disc SS304/AL/SS439 470mm x 2.3mm Total Thickness 2.3mm [cite: 1] | D64: CDM- | E64: CDM- [cite: 6]
A65: 000030470023 | B65: DISCO 5PLY 470/23 SS304 0,4 + Al1,4 + SS439 0,5 TOT 23/10 | C65: 5-Ply Disc SS304/AL/SS439 470mm x 2.3mm Total Thickness 2.3mm [cite: 1] | D65: CDM- | E65: CDM- [cite: 6]
A66: 000030470023 | B66: DISCO 5PLY 470/23 SS304 0,4 + Al1,4 + SS439 0,5 TOT 23/10 | C66: 5-Ply Disc SS304/AL/SS439 470mm x 2.3mm Total Thickness 2.3mm [cite: 1] | D66: CDM- | E66: CDM- [cite: 6]
A67: 000390103024 | B67: VITE 5MAX14 AC.AUTOM.ZIG.C/TORX T25 | C67: 5x14 Auto Steel Knurled Screw w/ Torx T25 | D67: SCR-
A68: 002340514003 | B68: ACEMATT OK-390 opacizzante | C68: Acematt OK-390 Matting Agent | D68: INM-
A69: 000070265022R | B69: DISCO AL.1200 265/22 RIC | C69: Aluminum Disc Alloy 1200 265mm x 2.2mm Replacement Part [cite: 1] | D69: ALM-
A70: 000070410022R | B70: DISCO AL.1200 410/22 RIC | C70: Aluminum Disc Alloy 1200 410mm x 2.2mm Replacement Part [cite: 1] | D70: ALM-
A71: 000040215036R | B71: DISCO AL.4006 215/36 RIC | C71: Aluminum Disc Alloy 4006 215mm x 3.6mm Replacement Part [cite: 1 2] | D71: ALM-
A72: 000040215036R | B72: DISCO AL.4006 215/36 RIC | C72: Aluminum Disc Alloy 4006 215mm x 3.6mm Replacement Part [cite: 1 2] | D72: ALM-
A73: 000040225029R | B73: DISCO AL.4006 225/29 RIC | C73: Aluminum Disc Alloy 4006 225mm x 2.9mm Replacement Part [cite: 1] | D73: ALM-
A74: 000040235029R | B74: DISCO AL.4006 235/29 RIC | C74: Aluminum Disc Alloy 4006 235mm x 2.9mm Replacement Part [cite: 1] | D74: ALM-
A75: 000040235036R | B75: DISCO AL.4006 235/36 RIC | C75: Aluminum Disc Alloy 4006 235mm x 3.6mm Replacement Part [cite: 2] | D75: ALM-
A76: 000040235036R | B76: DISCO AL.4006 235/36 RIC | C76: Aluminum Disc Alloy 4006 235mm x 3.6mm Replacement Part [cite: 2] | D76: ALM-
A77: 000040235036R | B77: DISCO AL.4006 235/36 RIC | C77: Aluminum Disc Alloy 4006 235mm x 3.6mm Replacement Part [cite: 2] | D77: ALM-
A78: 000040235036R | B78: DISCO AL.4006 235/36 RIC | C78: Aluminum Disc Alloy 4006 235mm x 3.6mm Replacement Part [cite: 2] | D78: ALM-
... A788: 000390115006 | B788: VITE 5MAX18 AC.AUTOM.ZIG.C/TORX T25 | C788: Screw 5x18 mm Steel Self-Locking Knurled Torx T25 | D788: SCW-
