Workbook

Sheet TVS order 31052026
A1: Purchase Order Number | B1: Purchase Order Date | C1: Purchase order issue date | D1: Vendor ID | E1: VendorName | F1: Vendor_Invoice_No | G1: Invoice Date | H1: REF_NO | I1: Item Code | J1: Part Description | K1: Commodity Italian | L1: Commodity English | M1: Division | N1: Quantity | O1: Unit | P1: PO_Price_PO CUR | Q1: PO UNIT PRICE PO_CUR | R1: Total_PO_Price_PO CUR | S1: Translated Part Description (English) | T1: Unified Commodity Code | U1: Standard Comm code description | V1: T Code Validation
A2: OF0039689 | B2: 45442.524 | D2: F600361 | E2: ARCONIC- KOFEM MILL PRODUCTS HUNGARY KFT. | F2: 26AFC000002 | G2: 46037 | I2: 000050235032R | J2: DISCO AL.L.GREEN 235/32 RIC | K2: alluminio | L2: =VLOOKUP(K2,'COMM ITY- ENG'!A:B,2,FALSE) -> aluminium | N2: 2861 | O2: kg | Q2: =+R2/N2 -> 3.427001 | R2: 9804.65 | S2: =IFERROR(VLOOKUP(J2,'DESC ITY - ENG'!B:C,2,FALSE),VLOOKUP(I2,'DESC ITY - ENG'!A:C,3,FALSE)) -> Aluminum Disc L. Green Series 235mm x 3.2mm Replacement Part [cite: 3] | T2: =IFERROR(VLOOKUP(S2,'DESC ITY - ENG'!C:D,2,FALSE),VLOOKUP(J2,'DESC ITY - ENG'!B:D,3,FALSE)) -> ALM- | U2: =VLOOKUP(T2,'STANDARD COMM'!A:B,2,FALSE) -> ALUM MATERIAL | V2: =IF(T2="","(blank)",IF(COUNTIF('STANDARD COMM'!A:A,T2)>0,"OK","OUT OF SCOPE")) -> OK
A3: OF0039508 | B3: 45580.308 | D3: F505839 | E3: CHEMOURS BELGIUM BVBA | F3: 26AFC000001 | G3: 46037 | I3: 003010503004 | J3: 459G-R0185 ROLLER PRIMER GRAY | K3: prodotti chimici | L3: =VLOOKUP(K3,'COMM ITY- ENG'!A:B,2,FALSE) -> chemical products | N3: 460 | O3: kg | Q3: =+R3/N3 -> 8.98 | R3: 4130.8 | S3: =IFERROR(VLOOKUP(J3,'DESC ITY - ENG'!B:C,2,FALSE),VLOOKUP(I3,'DESC ITY - ENG'!A:C,3,FALSE)) -> 459G-R0185 ROLLER PRIMER GRAY | T3: =IFERROR(VLOOKUP(S3,'DESC ITY - ENG'!C:D,2,FALSE),VLOOKUP(J3,'DESC ITY - ENG'!B:D,3,FALSE)) -> INM- | U3: =VLOOKUP(T3,'STANDARD COMM'!A:B,2,FALSE) -> INTR TREAT MATERIAL | V3: =IF(T3="","(blank)",IF(COUNTIF('STANDARD COMM'!A:A,T3)>0,"OK","OUT OF SCOPE")) -> OK
A4: OF0039689 | B4: 45596.39 | D4: F600361 | E4: ARCONIC- KOFEM MILL PRODUCTS HUNGARY KFT. | F4: 26AFC000002 | G4: 46037 | I4: 000050315032R | J4: DISCO AL.L.GREEN 315/32 RIC | K4: alluminio | L4: =VLOOKUP(K4,'COMM ITY- ENG'!A:B,2,FALSE) -> aluminium | N4: 6720 | O4: kg | Q4: =+R4/N4 -> 3.427 | R4: 23029.44 | S4: =IFERROR(VLOOKUP(J4,'DESC ITY - ENG'!B:C,2,FALSE),VLOOKUP(I4,'DESC ITY - ENG'!A:C,3,FALSE)) -> Aluminum Disc L. Green Series 315mm x 3.2mm Replacement Part [cite: 3] | T4: =IFERROR(VLOOKUP(S4,'DESC ITY - ENG'!C:D,2,FALSE),VLOOKUP(J4,'DESC ITY - ENG'!B:D,3,FALSE)) -> ALM- | U4: =VLOOKUP(T4,'STANDARD COMM'!A:B,2,FALSE) -> ALUM MATERIAL | V4: =IF(T4="","(blank)",IF(COUNTIF('STANDARD COMM'!A:A,T4)>0,"OK","OUT OF SCOPE")) -> OK
A5: OF0039689 | B5: 45596.39 | D5: F600361 | E5: ARCONIC- KOFEM MILL PRODUCTS HUNGARY KFT. | F5: 26AFC000002 | G5: 46037 | I5: 000050330032R | J5: DISCO AL.L.GREEN 330/32 RIC | K5: alluminio | L5: =VLOOKUP(K5,'COMM ITY- ENG'!A:B,2,FALSE) -> aluminium | N5: 6735 | O5: kg | Q5: =+R5/N5 -> 3.4270007 | R5: 23080.85 | S5: =IFERROR(VLOOKUP(J5,'DESC ITY - ENG'!B:C,2,FALSE),VLOOKUP(I5,'DESC ITY - ENG'!A:C,3,FALSE)) -> Aluminum Disc L. Green Series 330mm x 3.2mm Replacement Part [cite: 3] | T5: =IFERROR(VLOOKUP(S5,'DESC ITY - ENG'!C:D,2,FALSE),VLOOKUP(J5,'DESC ITY - ENG'!B:D,3,FALSE)) -> ALM- | U5: =VLOOKUP(T5,'STANDARD COMM'!A:B,2,FALSE) -> ALUM MATERIAL | V5: =IF(T5="","(blank)",IF(COUNTIF('STANDARD COMM'!A:A,T5)>0,"OK","OUT OF SCOPE")) -> OK
A6: OF0039508 | B6: 45600.392 | D6: F505839 | E6: CHEMOURS BELGIUM BVBA | F6: 26AFC000001 | G6: 46037 | I6: 003010505005 | J6: 478G-R1090 ROLLER SEALER | K6: prodotti chimici | L6: =VLOOKUP(K6,'COMM ITY- ENG'!A:B,2,FALSE) -> chemical products | N6: 320 | O6: kg | Q6: =+R6/N6 -> 13 | R6: 4160 | S6: =IFERROR(VLOOKUP(J6,'DESC ITY - ENG'!B:C,2,FALSE),VLOOKUP(I6,'DESC ITY - ENG'!A:C,3,FALSE)) -> 478G-R1090 ROLLER SEALER | T6: =IFERROR(VLOOKUP(S6,'DESC ITY - ENG'!C:D,2,FALSE),VLOOKUP(J6,'DESC ITY - ENG'!B:D,3,FALSE)) -> INM- | U6: =VLOOKUP(T6,'STANDARD COMM'!A:B,2,FALSE) -> INTR TREAT MATERIAL | V6: =IF(T6="","(blank)",IF(COUNTIF('STANDARD COMM'!A:A,T6)>0,"OK","OUT OF SCOPE")) -> OK
A7: OF0039508 | B7: 45600.392 | D7: F505839 | E7: CHEMOURS BELGIUM BVBA | F7: 26AFC000001 | G7: 46037 | I7: 003130002004 | J7: 455G-R0385 ROLLER TOPCOAT PEWTER | K7: prodotti chimici | L7: =VLOOKUP(K7,'COMM ITY- ENG'!A:B,2,FALSE) -> chemical products | N7: 660 | O7: kg | Q7: =+R7/N7 -> 8.98 | R7: 5926.8 | S7: =IFERROR(VLOOKUP(J7,'DESC ITY - ENG'!B:C,2,FALSE),VLOOKUP(I7,'DESC ITY - ENG'!A:C,3,FALSE)) -> 455G-R0385 ROLLER TOPCOAT PEWTER | T7: =IFERROR(VLOOKUP(S7,'DESC ITY - ENG'!C:D,2,FALSE),VLOOKUP(J7,'DESC ITY - ENG'!B:D,3,FALSE)) -> INM- | U7: =VLOOKUP(T7,'STANDARD COMM'!A:B,2,FALSE) -> INTR TREAT MATERIAL | V7: =IF(T7="","(blank)",IF(COUNTIF('STANDARD COMM'!A:A,T7)>0,"OK","OUT OF SCOPE")) -> OK
A8: OF0039689 | B8: 45624.677 | D8: F600361 | E8: ARCONIC- KOFEM MILL PRODUCTS HUNGARY KFT. | F8: 26AFC000002 | G8: 46037 | I8: 000050265032R | J8: DISCO AL.L.GREEN 265/32 RIC | K8: alluminio | L8: =VLOOKUP(K8,'COMM ITY- ENG'!A:B,2,FALSE) -> aluminium | N8: 6741 | O8: kg | Q8: =+R8/N8 -> 3.4270004 | R8: 23101.41 | S8: =IFERROR(VLOOKUP(J8,'DESC ITY - ENG'!B:C,2,FALSE),VLOOKUP(I8,'DESC ITY - ENG'!A:C,3,FALSE)) -> Aluminum Disc L. Green Series 265mm x 3.2mm Replacement Part [cite: 3] | T8: =IFERROR(VLOOKUP(S8,'DESC ITY - ENG'!C:D,2,FALSE),VLOOKUP(J8,'DESC ITY - ENG'!B:D,3,FALSE)) -> ALM- | U8: =VLOOKUP(T8,'STANDARD COMM'!A:B,2,FALSE) -> ALUM MATERIAL | V8: =IF(T8="","(blank)",IF(COUNTIF('STANDARD COMM'!A:A,T8)>0,"OK","OUT OF SCOPE")) -> OK
A9: OF0038738 | B9: 45611.483 | D9: F505466 | E9: YUHUAN SUNNAR RUBBER&PLASTIC PRODUCTS CO.LTD | F9: 26AFF000001 | G9: 46049 | I9: 000250042001 | J9: MANICO BIS/1 NERO SATINATO | K9: manigliame | L9: =VLOOKUP(K9,'COMM ITY- ENG'!A:B,2,FALSE) -> handles | N9: 5000 | O9: NR | Q9: =+R9/N9 -> 0.239246 | R9: 1196.23 | S9: =IFERROR(VLOOKUP(J9,'DESC ITY - ENG'!B:C,2,FALSE),VLOOKUP(I9,'DESC ITY - ENG'!A:C,3,FALSE)) -> Handle Bis/1 Black Satin Finish [cite: 5] | T9: =IFERROR(VLOOKUP(S9,'DESC ITY - ENG'!C:D,2,FALSE),VLOOKUP(J9,'DESC ITY - ENG'!B:D,3,FALSE)) -> HDL-- | U9: =VLOOKUP(T9,'STANDARD COMM'!A:B,2,FALSE) -> #N/A | V9: =IF(T9="","(blank)",IF(COUNTIF('STANDARD COMM'!A:A,T9)>0,"OK","OUT OF SCOPE")) -> OUT OF SCOPE
A10: OF0038738 | B10: 45611.483 | D10: F505466 | E10: YUHUAN SUNNAR RUBBER&PLASTIC PRODUCTS CO.LTD | F10: 26AFF000001 | G10: 46049 | I10: 000250044001 | J10: MANICO CIGNO/1 NERO SATINATO | K10: manigliame | L10: =VLOOKUP(K10,'COMM ITY- ENG'!A:B,2,FALSE) -> handles | N10: 10000 | O10: NR | Q10: =+R10/N10 -> 0.207856 | R10: 2078.56 | S10: =IFERROR(VLOOKUP(J10,'DESC ITY - ENG'!B:C,2,FALSE),VLOOKUP(I10,'DESC ITY - ENG'!A:C,3,FALSE)) -> Handle Cigno/1 Black Satin Finish [cite: 5] | T10: =IFERROR(VLOOKUP(S10,'DESC ITY - ENG'!C:D,2,FALSE),VLOOKUP(J10,'DESC ITY - ENG'!B:D,3,FALSE)) -> HDL-- | U10: =VLOOKUP(T10,'STANDARD COMM'!A:B,2,FALSE) -> #N/A | V10: =IF(T10="","(blank)",IF(COUNTIF('STANDARD COMM'!A:A,T10)>0,"OK","OUT OF SCOPE")) -> OUT OF SCOPE
A11: OF0038738 | B11: 45611.483 | D11: F505466 | E11: YUHUAN SUNNAR RUBBER&PLASTIC PRODUCTS CO.LTD | F11: 26AFF000001 | G11: 46049 | I11: 000250045001 | J11: MANICO CIGNO/2 NERO SATINATO | K11: manigliame | L11: =VLOOKUP(K11,'COMM ITY- ENG'!A:B,2,FALSE) -> handles | N11: 30000 | O11: NR | Q11: =+R11/N11 -> 0.25451767 | R11: 7635.53 | S11: =IFERROR(VLOOKUP(J11,'DESC ITY - ENG'!B:C,2,FALSE),VLOOKUP(I11,'DESC ITY - ENG'!A:C,3,FALSE)) -> Handle Cigno/2 Black Satin Finish [cite: 5] | T11: =IFERROR(VLOOKUP(S11,'DESC ITY - ENG'!C:D,2,FALSE),VLOOKUP(J11,'DESC ITY - ENG'!B:D,3,FALSE)) -> HDL-- | U11: =VLOOKUP(T11,'STANDARD COMM'!A:B,2,FALSE) -> #N/A | V11: =IF(T11="","(blank)",IF(COUNTIF('STANDARD COMM'!A:A,T11)>0,"OK","OUT OF SCOPE")) -> OUT OF SCOPE
A12: OF0038893 | B12: 45611.483 | D12: F505466 | E12: YUHUAN SUNNAR RUBBER&PLASTIC PRODUCTS CO.LTD | F12: 26AFF000001 | G12: 46049 | I12: 000250516105 | J12: MANICO TITANO/1 EFFET.LEGNO V.0013 | K12: manigliame | L12: =VLOOKUP(K12,'COMM ITY- ENG'!A:B,2,FALSE) -> handles | N12: 3000 | O12: NR | Q12: =+R12/N12 -> 0.65835333 | R12: 1975.06 | S12: =IFERROR(VLOOKUP(J12,'DESC ITY - ENG'!B:C,2,FALSE),VLOOKUP(I12,'DESC ITY - ENG'!A:C,3,FALSE)) -> Handle Titano/1 Wood Effect V.0013 [cite: 5] | T12: =IFERROR(VLOOKUP(S12,'DESC ITY - ENG'!C:D,2,FALSE),VLOOKUP(J12,'DESC ITY - ENG'!B:D,3,FALSE)) -> HDL-- | U12: =VLOOKUP(T12,'STANDARD COMM'!A:B,2,FALSE) -> #N/A | V12: =IF(T12="","(blank)",IF(COUNTIF('STANDARD COMM'!A:A,T12)>0,"OK","OUT OF SCOPE")) -> OUT OF SCOPE
A13: OF0038893 | B13: 45611.483 | D13: F505466 | E13: YUHUAN SUNNAR RUBBER&PLASTIC PRODUCTS CO.LTD | F13: 26AFF000001 | G13: 46049 | I13: 000250517107 | J13: MANICO TITANO/2 EFFET.LEGNO V.0013 | K13: manigliame | L13: =VLOOKUP(K13,'COMM ITY- ENG'!A:B,2,FALSE) -> handles | N13: 3000 | O13: NR | Q13: =+R13/N13 -> 0.70162 | R13: 2104.86 | S13: =IFERROR(VLOOKUP(J13,'DESC ITY - ENG'!B:C,2,FALSE),VLOOKUP(I13,'DESC ITY - ENG'!A:C,3,FALSE)) -> Titano/2 Handle Wood Effect V.0013 | T13: =IFERROR(VLOOKUP(S13,'DESC ITY - ENG'!C:D,2,FALSE),VLOOKUP(J13,'DESC ITY - ENG'!B:D,3,FALSE)) -> HDL-- | U13: =VLOOKUP(T13,'STANDARD COMM'!A:B,2,FALSE) -> #N/A | V13: =IF(T13="","(blank)",IF(COUNTIF('STANDARD COMM'!A:A,T13)>0,"OK","OUT OF SCOPE")) -> OUT OF SCOPE
... A339: OF0039811 | B339: 45698.437 | D339: F012680 | E339: PROFILGLASS SPA | F339: 26AFI000256 | G339: 46053 | I339: 000050280032R | J339: DISCO AL.L.GREEN 280/32 RIC | K339: alluminio | L339: =VLOOKUP(K339,'COMM ITY- ENG'!A:B,2,FALSE) -> aluminium | N339: 895 | O339: kg | Q339: =+R339/N339 -> 3.33 | R339: 2980.35 | S339: =IFERROR(VLOOKUP(J339,'DESC ITY - ENG'!B:C,2,FALSE),VLOOKUP(I339,'DESC ITY - ENG'!A:C,3,FALSE)) -> Aluminum Disc L. Green Series 280mm x 3.2mm Replacement Part [cite: 3] | T339: =IFERROR(VLOOKUP(S339,'DESC ITY - ENG'!C:D,2,FALSE),VLOOKUP(J339,'DESC ITY - ENG'!B:D,3,FALSE)) -> ALM- | U339: =VLOOKUP(T339,'STANDARD COMM'!A:B,2,FALSE) -> ALUM MATERIAL | V339: =IF(T339="","(blank)",IF(COUNTIF('STANDARD COMM'!A:A,T339)>0,"OK","OUT OF SCOPE")) -> OK
A340: OF0038444 | D340: F600043 | E340: MEYER MANUFACTURING COMPANY LIMITED | F340: 26AFF000009 | G340: 46053 | I340: 000730415002 | J340: REC2008AS-002 COP.AC.MADE IN 20CM ASSEMBLED W/DEY.PVD GOLD | K340: accessori finiti | L340: =VLOOKUP(K340,'COMM ITY- ENG'!A:B,2,FALSE) -> finished accessories | N340: 980 | O340: NR | Q340: =+R340/N340 -> 4.2674082 | R340: 4182.06 | S340: =IFERROR(VLOOKUP(J340,'DESC ITY - ENG'!B:C,2,FALSE),VLOOKUP(I340,'DESC ITY - ENG'!A:C,3,FALSE)) -> SS Lid 20cm Assembled with DEY.PVD Gold Handle | T340: =IFERROR(VLOOKUP(S340,'DESC ITY - ENG'!C:D,2,FALSE),VLOOKUP(J340,'DESC ITY - ENG'!B:D,3,FALSE)) -> LID- | U340: =VLOOKUP(T340,'STANDARD COMM'!A:B,2,FALSE) -> LID | V340: =IF(T340="","(blank)",IF(COUNTIF('STANDARD COMM'!A:A,T340)>0,"OK","OUT OF SCOPE")) -> OK
A341: OF0039830 | B341: 45503.383 | D341: F505839 | E341: CHEMOURS BELGIUM BVBA | F341: 26AFC000029 | G341: 46069 | I341: 003130002004 | J341: 455G-R0385 ROLLER TOPCOAT PEWTER | K341: prodotti chimici | L341: =VLOOKUP(K341,'COMM ITY- ENG'!A:B,2,FALSE) -> chemical products | N341: 460 | O341: kg | Q341: =+R341/N341 -> 8.98 | R341: 4130.8 | S341: =IFERROR(VLOOKUP(J341,'DESC ITY - ENG'!B:C,2,FALSE),VLOOKUP(I341,'DESC ITY - ENG'!A:C,3,FALSE)) -> 455G-R0385 ROLLER TOPCOAT PEWTER | T341: =IFERROR(VLOOKUP(S341,'DESC ITY - ENG'!C:D,2,FALSE),VLOOKUP(J341,'DESC ITY - ENG'!B:D,3,FALSE)) -> INM- | U341: =VLOOKUP(T341,'STANDARD COMM'!A:B,2,FALSE) -> INTR TREAT MATERIAL | V341: =IF(T341="","(blank)",IF(COUNTIF('STANDARD COMM'!A:A,T341)>0,"OK","OUT OF SCOPE")) -> OK
A342: OF0040017 | B342: 45559.363 | D342: F505532 | E342: PEMCO BELGIUM BV | F342: 26AFC000020 | G342: 46069 | I342: 002490189001 | J342: FB 280 ROSSO FERRO | K342: prodotti chimici | L342: =VLOOKUP(K342,'COMM ITY- ENG'!A:B,2,FALSE) -> chemical products | N342: 50 | O342: kg | Q342: =+R342/N342 -> 22.3892 | R342: 1119.46 | S342: =IFERROR(VLOOKUP(J342,'DESC ITY - ENG'!B:C,2,FALSE),VLOOKUP(I342,'DESC ITY - ENG'!A:C,3,FALSE)) -> Pigment FB 280 Iron Red | T342: =IFERROR(VLOOKUP(S342,'DESC ITY - ENG'!C:D,2,FALSE),VLOOKUP(J342,'DESC ITY - ENG'!B:D,3,FALSE)) -> INM- | U342: =VLOOKUP(T342,'STANDARD COMM'!A:B,2,FALSE) -> INTR TREAT MATERIAL | V342: =IF(T342="","(blank)",IF(COUNTIF('STANDARD COMM'!A:A,T342)>0,"OK","OUT OF SCOPE")) -> OK
A343: OF0039842 | B343: 45566.608 | D343: F600361 | E343: ARCONIC- KOFEM MILL PRODUCTS HUNGARY KFT. | F343: 26AFC000024 | G343: 46069 | I343: 000050265032R | J343: DISCO AL.L.GREEN 265/32 RIC | K343: alluminio | L343: =VLOOKUP(K343,'COMM ITY- ENG'!A:B,2,FALSE) -> aluminium | N343: 10198 | O343: kg | Q343: =+R343/N343 -> 3.6420004 | R343: 37141.12 | S343: =IFERROR(VLOOKUP(J343,'DESC ITY - ENG'!B:C,2,FALSE),VLOOKUP(I343,'DESC ITY - ENG'!A:C,3,FALSE)) -> Aluminum Disc L. Green Series 265mm x 3.2mm Replacement Part [cite: 3] | T343: =IFERROR(VLOOKUP(S343,'DESC ITY - ENG'!C:D,2,FALSE),VLOOKUP(J343,'DESC ITY - ENG'!B:D,3,FALSE)) -> ALM- | U343: =VLOOKUP(T343,'STANDARD COMM'!A:B,2,FALSE) -> ALUM MATERIAL | V343: =IF(T343="","(blank)",IF(COUNTIF('STANDARD COMM'!A:A,T343)>0,"OK","OUT OF SCOPE")) -> OK
A344: OF0039955 | B344: 45566.608 | D344: F600361 | E344: ARCONIC- KOFEM MILL PRODUCTS HUNGARY KFT. | F344: 26AFC000025 | G344: 46069 | I344: 000050315032R | J344: DISCO AL.L.GREEN 315/32 RIC | K344: alluminio | L344: =VLOOKUP(K344,'COMM ITY- ENG'!A:B,2,FALSE) -> aluminium | N344: 6654 | O344: kg | Q344: =+R344/N344 -> 3.6420003 | R344: 24233.87 | S344: =IFERROR(VLOOKUP(J344,'DESC ITY - ENG'!B:C,2,FALSE),VLOOKUP(I344,'DESC ITY - ENG'!A:C,3,FALSE)) -> Aluminum Disc L. Green Series 315mm x 3.2mm Replacement Part [cite: 3] | T344: =IFERROR(VLOOKUP(S344,'DESC ITY - ENG'!C:D,2,FALSE),VLOOKUP(J344,'DESC ITY - ENG'!B:D,3,FALSE)) -> ALM- | U344: =VLOOKUP(T344,'STANDARD COMM'!A:B,2,FALSE) -> ALUM MATERIAL | V344: =IF(T344="","(blank)",IF(COUNTIF('STANDARD COMM'!A:A,T344)>0,"OK","OUT OF SCOPE")) -> OK
A345: OF0039955 | B345: 45566.608 | D345: F600361 | E345: ARCONIC- KOFEM MILL PRODUCTS HUNGARY KFT. | F345: 26AFC000025 | G345: 46069 | I345: 000050330032R | J345: DISCO AL.L.GREEN 330/32 RIC | K345: alluminio | L345: =VLOOKUP(K345,'COMM ITY- ENG'!A:B,2,FALSE) -> aluminium | N345: 6528 | O345: kg | Q345: =+R345/N345 -> 3.6420006 | R345: 23774.98 | S345: =IFERROR(VLOOKUP(J345,'DESC ITY - ENG'!B:C,2,FALSE),VLOOKUP(I345,'DESC ITY - ENG'!A:C,3,FALSE)) -> Aluminum Disc L. Green Series 330mm x 3.2mm Replacement Part [cite: 3] | T345: =IFERROR(VLOOKUP(S345,'DESC ITY - ENG'!C:D,2,FALSE),VLOOKUP(J345,'DESC ITY - ENG'!B:D,3,FALSE)) -> ALM- | U345: =VLOOKUP(T345,'STANDARD COMM'!A:B,2,FALSE) -> ALUM MATERIAL | V345: =IF(T345="","(blank)",IF(COUNTIF('STANDARD COMM'!A:A,T345)>0,"OK","OUT OF SCOPE")) -> OK
A346: OF0039842 | B346: 45566.608 | D346: F600361 | E346: ARCONIC- KOFEM MILL PRODUCTS HUNGARY KFT. | F346: 26AFC000026 | G346: 46069 | I346: 000050315032R | J346: DISCO AL.L.GREEN 315/32 RIC | K346: alluminio | L346: =VLOOKUP(K346,'COMM ITY- ENG'!A:B,2,FALSE) -> aluminium | N346: 3409 | O346: kg | Q346: =+R346/N346 -> 3.6420006 | R346: 12415.58 | S346: =IFERROR(VLOOKUP(J346,'DESC ITY - ENG'!B:C,2,FALSE),VLOOKUP(I346,'DESC ITY - ENG'!A:C,3,FALSE)) -> Aluminum Disc L. Green Series 315mm x 3.2mm Replacement Part [cite: 3] | T346: =IFERROR(VLOOKUP(S346,'DESC ITY - ENG'!C:D,2,FALSE),VLOOKUP(J346,'DESC ITY - ENG'!B:D,3,FALSE)) -> ALM- | U346: =VLOOKUP(T346,'STANDARD COMM'!A:B,2,FALSE) -> ALUM MATERIAL | V346: =IF(T346="","(blank)",IF(COUNTIF('STANDARD COMM'!A:A,T346)>0,"OK","OUT OF SCOPE")) -> OK
A347: OF0039842 | B347: 45566.608 | D347: F600361 | E347: ARCONIC- KOFEM MILL PRODUCTS HUNGARY KFT. | F347: 26AFC000026 | G347: 46069 | I347: 000050330032R | J347: DISCO AL.L.GREEN 330/32 RIC | K347: alluminio | L347: =VLOOKUP(K347,'COMM ITY- ENG'!A:B,2,FALSE) -> aluminium | N347: 6520 | O347: kg | Q347: =+R347/N347 -> 3.642 | R347: 23745.84 | S347: =IFERROR(VLOOKUP(J347,'DESC ITY - ENG'!B:C,2,FALSE),VLOOKUP(I347,'DESC ITY - ENG'!A:C,3,FALSE)) -> Aluminum Disc L. Green Series 330mm x 3.2mm Replacement Part [cite: 3] | T347: =IFERROR(VLOOKUP(S347,'DESC ITY - ENG'!C:D,2,FALSE),VLOOKUP(J347,'DESC ITY - ENG'!B:D,3,FALSE)) -> ALM- | U347: =VLOOKUP(T347,'STANDARD COMM'!A:B,2,FALSE) -> ALUM MATERIAL | V347: =IF(T347="","(blank)",IF(COUNTIF('STANDARD COMM'!A:A,T347)>0,"OK","OUT OF SCOPE")) -> OK
A348: OF0039955 | B348: 45566.608 | D348: F600361 | E348: ARCONIC- KOFEM MILL PRODUCTS HUNGARY KFT. | F348: 26AFC000027 | G348: 46069 | I348: 000050225032R | J348: DISCO AL.L.GREEN 225/32 RIC | K348: alluminio | L348: =VLOOKUP(K348,'COMM ITY- ENG'!A:B,2,FALSE) -> aluminium | N348: 2224 | O348: kg | Q348: =+R348/N348 -> 3.6420009 | R348: 8099.81 | S348: =IFERROR(VLOOKUP(J348,'DESC ITY - ENG'!B:C,2,FALSE),VLOOKUP(I348,'DESC ITY - ENG'!A:C,3,FALSE)) -> Aluminum Disc L. Green Series 225mm x 3.2mm Replacement Part [cite: 3] | T348: =IFERROR(VLOOKUP(S348,'DESC ITY - ENG'!C:D,2,FALSE),VLOOKUP(J348,'DESC ITY - ENG'!B:D,3,FALSE)) -> ALM- | U348: =VLOOKUP(T348,'STANDARD COMM'!A:B,2,FALSE) -> ALUM MATERIAL | V348: =IF(T348="","(blank)",IF(COUNTIF('STANDARD COMM'!A:A,T348)>0,"OK","OUT OF SCOPE")) -> OK
A349: OF0039955 | B349: 45566.608 | D349: F600361 | E349: ARCONIC- KOFEM MILL PRODUCTS HUNGARY KFT. | F349: 26AFC000027 | G349: 46069 | I349: 000050235032R | J349: DISCO AL.L.GREEN 235/32 RIC | K349: alluminio | L349: =VLOOKUP(K349,'COMM ITY- ENG'!A:B,2,FALSE) -> aluminium | N349: 2213 | O349: kg | Q349: =+R349/N349 -> 3.6420018 | R349: 8059.75 | S349: =IFERROR(VLOOKUP(J349,'DESC ITY - ENG'!B:C,2,FALSE),VLOOKUP(I349,'DESC ITY - ENG'!A:C,3,FALSE)) -> Aluminum Disc L. Green Series 235mm x 3.2mm Replacement Part [cite: 3] | T349: =IFERROR(VLOOKUP(S349,'DESC ITY - ENG'!C:D,2,FALSE),VLOOKUP(J349,'DESC ITY - ENG'!B:D,3,FALSE)) -> ALM- | U349: =VLOOKUP(T349,'STANDARD COMM'!A:B,2,FALSE) -> ALUM MATERIAL | V349: =IF(T349="","(blank)",IF(COUNTIF('STANDARD COMM'!A:A,T349)>0,"OK","OUT OF SCOPE")) -> OK
A350: OF0039955 | B350: 45566.608 | D350: F600361 | E350: ARCONIC- KOFEM MILL PRODUCTS HUNGARY KFT. | F350: 26AFC000027 | G350: 46069 | I350: 000050265032R | J350: DISCO AL.L.GREEN 265/32 RIC | K350: alluminio | L350: =VLOOKUP(K350,'COMM ITY- ENG'!A:B,2,FALSE) -> aluminium | N350: 2219 | O350: kg | Q350: =+R350/N350 -> 3.6420009 | R350: 8081.6 | S350: =IFERROR(VLOOKUP(J350,'DESC ITY - ENG'!B:C,2,FALSE),VLOOKUP(I350,'DESC ITY - ENG'!A:C,3,FALSE)) -> Aluminum Disc L. Green Series 265mm x 3.2mm Replacement Part [cite: 3] | T350: =IFERROR(VLOOKUP(S350,'DESC ITY - ENG'!C:D,2,FALSE),VLOOKUP(J350,'DESC ITY - ENG'!B:D,3,FALSE)) -> ALM- | U350: =VLOOKUP(T350,'STANDARD COMM'!A:B,2,FALSE) -> ALUM MATERIAL | V350: =IF(T350="","(blank)",IF(COUNTIF('STANDARD COMM'!A:A,T350)>0,"OK","OUT OF SCOPE")) -> OK
A351: OF0039830 | B351: 45566.608 | D351: F505839 | E351: CHEMOURS BELGIUM BVBA | F351: 26AFC000029 | G351: 46069 | I351: 003010503004 | J351: 459G-R0185 ROLLER PRIMER GRAY | K351: prodotti chimici | L351: =VLOOKUP(K351,'COMM ITY- ENG'!A:B,2,FALSE) -> chemical products | N351: 300 | O351: kg | Q351: =+R351/N351 -> 8.98 | R351: 2694 | S351: =IFERROR(VLOOKUP(J351,'DESC ITY - ENG'!B:C,2,FALSE),VLOOKUP(I351,'DESC ITY - ENG'!A:C,3,FALSE)) -> 459G-R0185 ROLLER PRIMER GRAY | T351: =IFERROR(VLOOKUP(S351,'DESC ITY - ENG'!C:D,2,FALSE),VLOOKUP(J351,'DESC ITY - ENG'!B:D,3,FALSE)) -> INM- | U351: =VLOOKUP(T351,'STANDARD COMM'!A:B,2,FALSE) -> INTR TREAT MATERIAL | V351: =IF(T351="","(blank)",IF(COUNTIF('STANDARD COMM'!A:A,T351)>0,"OK","OUT OF SCOPE")) -> OK
A352: OF0039830 | B352: 45566.608 | D352: F505839 | E352: CHEMOURS BELGIUM BVBA | F352: 26AFC000029 | G352: 46069 | I352: 003040090024 | J352: 479G-81190 PRIMER BLACK PROFES (ex 81197) | K352: prodotti chimici | L352: =VLOOKUP(K352,'COMM ITY- ENG'!A:B,2,FALSE) -> chemical products | N352: 320 | O352: kg | Q352: =+R352/N352 -> 22.79 | R352: 7292.8 | S352: =IFERROR(VLOOKUP(J352,'DESC ITY - ENG'!B:C,2,FALSE),VLOOKUP(I352,'DESC ITY - ENG'!A:C,3,FALSE)) -> 479G-81190 PRIMER BLACK PROFES (ex 81197) | T352: =IFERROR(VLOOKUP(S352,'DESC ITY - ENG'!C:D,2,FALSE),VLOOKUP(J352,'DESC ITY - ENG'!B:D,3,FALSE)) -> INM- | U352: =VLOOKUP(T352,'STANDARD COMM'!A:B,2,FALSE) -> INTR TREAT MATERIAL | V352: =IF(T352="","(blank)",IF(COUNTIF('STANDARD COMM'!A:A,T352)>0,"OK","OUT OF SCOPE")) -> OK
... A429: OF0040138 | B429: 45714.681 | D429: F010036 | E429: BBC PLASTIK SRL | F429: 26AFI000263 | G429: 46071 | I429: 001150300006 | J429: BUSTA POL.50X70 FORATA RIGENERATA 100% MADE IN | K429: accessori di confez. | L429: =VLOOKUP(K429,'COMM ITY- ENG'!A:B,2,FALSE) -> packaging accessories | N429: 2000 | O429: NR | Q429: =+R429/N429 -> 0.065 | R429: 130 | S429: =IFERROR(VLOOKUP(J429,'DESC ITY - ENG'!B:C,2,FALSE),VLOOKUP(I429,'DESC ITY - ENG'!A:C,3,FALSE)) -> POLY BAG 50X70 PERFORATED REGENERATED 100% MADE IN | T429: =IFERROR(VLOOKUP(S429,'DESC ITY - ENG'!C:D,2,FALSE),VLOOKUP(J429,'DESC ITY - ENG'!B:D,3,FALSE)) -> BAG- | U429: =VLOOKUP(T429,'STANDARD COMM'!A:B,2,FALSE) -> BAG PACK | V429: =IF(T429="","(blank)",IF(COUNTIF('STANDARD COMM'!A:A,T429)>0,"OK","OUT OF SCOPE")) -> OK
A430: OF0039884 | D430: F600439 | E430: CARTON SRL | F430: 26AFI000267 | G430: 46071 | I430: 002030160001 | J430: STRISCIA CARTA BUL.52X27,5 GR90 STD FSC+LOGHI | K430: accessori di confez. | L430: =VLOOKUP(K430,'COMM ITY- ENG'!A:B,2,FALSE) -> packaging accessories | N430: 25000 | O430: NR | Q430: =+R430/N430 -> 0.017 | R430: 425 | S430: =IFERROR(VLOOKUP(J430,'DESC ITY - ENG'!B:C,2,FALSE),VLOOKUP(I430,'DESC ITY - ENG'!A:C,3,FALSE)) -> 5 GR90 STD FSC+LOGHIPaper Strip 52x27.5 cm 90g Standard FSC with Logos | T430: =IFERROR(VLOOKUP(S430,'DESC ITY - ENG'!C:D,2,FALSE),VLOOKUP(J430,'DESC ITY - ENG'!B:D,3,FALSE)) -> PAP- | U430: =VLOOKUP(T430,'STANDARD COMM'!A:B,2,FALSE) -> PAPER FOR BOX | V430: =IF(T430="","(blank)",IF(COUNTIF('STANDARD COMM'!A:A,T430)>0,"OK","OUT OF SCOPE")) -> OK
A431: OF0039884 | D431: F600439 | E431: CARTON SRL | F431: 26AFI000267 | G431: 46071 | I431: 002030161001 | J431: STRISCIA CARTA BUL.60X36,5 GR90 STD FSC+LOGHI | K431: accessori di confez. | L431: =VLOOKUP(K431,'COMM ITY- ENG'!A:B,2,FALSE) -> packaging accessories | N431: 30000 | O431: NR | Q431: =+R431/N431 -> 0.025 | R431: 750 | S431: =IFERROR(VLOOKUP(J431,'DESC ITY - ENG'!B:C,2,FALSE),VLOOKUP(I431,'DESC ITY - ENG'!A:C,3,FALSE)) -> 5 GR90 STD FSC+LOGHIPaper Strip 61X36.5 cm 90g Standard FSC with Logos | T431: =IFERROR(VLOOKUP(S431,'DESC ITY - ENG'!C:D,2,FALSE),VLOOKUP(J431,'DESC ITY - ENG'!B:D,3,FALSE)) -> PAP- | U431: =VLOOKUP(T431,'STANDARD COMM'!A:B,2,FALSE) -> PAPER FOR BOX | V431: =IF(T431="","(blank)",IF(COUNTIF('STANDARD COMM'!A:A,T431)>0,"OK","OUT OF SCOPE")) -> OK
A432: OF0039767 | D432: F014441 | E432: COOPERATIVA ALBANESI SCRL | F432: 26AFI000268 | G432: 46071 | I432: 000390111001 | J432: VITE 5MAX16 AC TCB T9,5 C./TORX T25 | K432: accessori x manigl. | L432: =VLOOKUP(K432,'COMM ITY- ENG'!A:B,2,FALSE) -> accessories for handles | N432: 20000 | O432: NR | Q432: =+R432/N432 -> 0.0354 | R432: 708 | S432: =IFERROR(VLOOKUP(J432,'DESC ITY - ENG'!B:C,2,FALSE),VLOOKUP(I432,'DESC ITY - ENG'!A:C,3,FALSE)) -> Screw 5x16 mm Steel Cylindrical Button Head Torx T25 | T432: =IFERROR(VLOOKUP(S432,'DESC ITY - ENG'!C:D,2,FALSE),VLOOKUP(J432,'DESC ITY - ENG'!B:D,3,FALSE)) -> SCR- | U432: =VLOOKUP(T432,'STANDARD COMM'!A:B,2,FALSE) -> SCREW | V432: =IF(T432="","(blank)",IF(COUNTIF('STANDARD COMM'!A:A,T432)>0,"OK","OUT OF SCOPE")) -> OK
A433: OF0039502 | D433: F014441 | E433: COOPERATIVA ALBANESI SCRL | F433: 26AFI000268 | G433: 46071 | I433: 000390111024 | J433: VITE 5MAX16 ZN B.AUTOM.ZIG.C/TO.T25 | K433: accessori x manigl. | L433: =VLOOKUP(K433,'COMM ITY- ENG'!A:B,2,FALSE) -> accessories for handles | N433: 4044 | O433: NR | Q433: =+R433/N433 -> 0.01810089 | R433: 73.2 | S433: =IFERROR(VLOOKUP(J433,'DESC ITY - ENG'!B:C,2,FALSE),VLOOKUP(I433,'DESC ITY - ENG'!A:C,3,FALSE)) -> Screw 5x16 mm Steel Cylindrical Button Head Torx T25 | T433: =IFERROR(VLOOKUP(S433,'DESC ITY - ENG'!C:D,2,FALSE),VLOOKUP(J433,'DESC ITY - ENG'!B:D,3,FALSE)) -> SCR- | U433: =VLOOKUP(T433,'STANDARD COMM'!A:B,2,FALSE) -> SCREW | V433: =IF(T433="","(blank)",IF(COUNTIF('STANDARD COMM'!A:A,T433)>0,"OK","OUT OF SCOPE")) -> OK
A434: OF0039875 | B434: 45560.447 | D434: F600780 | E434: GULBAK BAKALIT METAL VE TEKSTIL SAN. ve TIC. LTD. STI | F434: 26AFF000047 | G434: 46081 | I434: 000281710003 | J434: MANICO AC.SOLE CORTO C/LOGO MC AISI 430 SABBIATO CAS.433 16 | K434: manigliame | L434: =VLOOKUP(K434,'COMM ITY- ENG'!A:B,2,FALSE) -> handles | N434: 4000 | O434: NR | Q434: =+R434/N434 -> 1.137 | R434: 4548 | S434: =IFERROR(VLOOKUP(J434,'DESC ITY - ENG'!B:C,2,FALSE),VLOOKUP(I434,'DESC ITY - ENG'!A:C,3,FALSE)) -> Steel Handle AC.SOLE Short w/Logo MC AISI 430 Casserole 433-16 Sandblasted [cite: 4] | T434: =IFERROR(VLOOKUP(S434,'DESC ITY - ENG'!C:D,2,FALSE),VLOOKUP(J434,'DESC ITY - ENG'!B:D,3,FALSE)) -> SHDL- | U434: =VLOOKUP(T434,'STANDARD COMM'!A:B,2,FALSE) -> #N/A | V434: =IF(T434="","(blank)",IF(COUNTIF('STANDARD COMM'!A:A,T434)>0,"OK","OUT OF SCOPE")) -> OUT OF SCOPE
A435: OF0040544 | B435: 45580.643 | D435: F014980 | E435: INDUSTRIAL SERVICE Srl | F435: 26AFI000443 | G435: 46081 | I435: 009100002001 | J435: BOBINA POMERCART GR 40 (KG 4) | K435: materiali di consumo | L435: =VLOOKUP(K435,'COMM ITY- ENG'!A:B,2,FALSE) -> consumable materials | N435: 18 | O435: NR | Q435: =+R435/N435 -> 17.2 | R435: 309.6 | S435: =IFERROR(VLOOKUP(J435,'DESC ITY - ENG'!B:C,2,FALSE),VLOOKUP(I435,'DESC ITY - ENG'!A:C,3,FALSE)) -> Paper Roll Pomercart 40g 4kg | T435: =IFERROR(VLOOKUP(S435,'DESC ITY - ENG'!C:D,2,FALSE),VLOOKUP(J435,'DESC ITY - ENG'!B:D,3,FALSE)) -> PAP- | U435: =VLOOKUP(T435,'STANDARD COMM'!A:B,2,FALSE) -> PAPER FOR BOX | V435: =IF(T435="","(blank)",IF(COUNTIF('STANDARD COMM'!A:A,T435)>0,"OK","OUT OF SCOPE")) -> OK
A436: OF0040100 | B436: 45582.527 | D436: F600361 | E436: ARCONIC- KOFEM MILL PRODUCTS HUNGARY KFT. | F436: 26AFC000035 | G436: 46081 | I436: 000050220032R | J436: DISCO AL.L.GREEN 220/32 RIC | K436: alluminio | L436: =VLOOKUP(K436,'COMM ITY- ENG'!A:B,2,FALSE) -> aluminium | N436: 2233 | O436: kg | Q436: =+R436/N436 -> 3.6420018 | R436: 8132.59 | S436: =IFERROR(VLOOKUP(J436,'DESC ITY - ENG'!B:C,2,FALSE),VLOOKUP(I436,'DESC ITY - ENG'!A:C,3,FALSE)) -> Aluminum Disc L. Green Series 220mm x 3.2mm Replacement Part [cite: 3] | T436: =IFERROR(VLOOKUP(S436,'DESC ITY - ENG'!C:D,2,FALSE),VLOOKUP(J436,'DESC ITY - ENG'!B:D,3,FALSE)) -> ALM- | U436: =VLOOKUP(T436,'STANDARD COMM'!A:B,2,FALSE) -> ALUM MATERIAL | V436: =IF(T436="","(blank)",IF(COUNTIF('STANDARD COMM'!A:A,T436)>0,"OK","OUT OF SCOPE")) -> OK
A437: OF0040100 | B437: 45582.527 | D437: F600361 | E437: ARCONIC- KOFEM MILL PRODUCTS HUNGARY KFT. | F437: 26AFC000035 | G437: 46081 | I437: 000050305029R | J437: DISCO AL.L.GREEN 305/29 RIC | K437: alluminio | L437: =VLOOKUP(K437,'COMM ITY- ENG'!A:B,2,FALSE) -> aluminium | N437: 2246 | O437: kg | Q437: =+R437/N437 -> 3.6419991 | R437: 8179.93 | S437: =IFERROR(VLOOKUP(J437,'DESC ITY - ENG'!B:C,2,FALSE),VLOOKUP(I437,'DESC ITY - ENG'!A:C,3,FALSE)) -> Aluminum Disc L. Green Series 305mm x 2.9mm Replacement Part [cite: 3] | T437: =IFERROR(VLOOKUP(S437,'DESC ITY - ENG'!C:D,2,FALSE),VLOOKUP(J437,'DESC ITY - ENG'!B:D,3,FALSE)) -> ALM- | U437: =VLOOKUP(T437,'STANDARD COMM'!A:B,2,FALSE) -> ALUM MATERIAL | V437: =IF(T437="","(blank)",IF(COUNTIF('STANDARD COMM'!A:A,T437)>0,"OK","OUT OF SCOPE")) -> OK
A438: OF0040100 | B438: 45582.527 | D438: F600361 | E438: ARCONIC- KOFEM MILL PRODUCTS HUNGARY KFT. | F438: 26AFC000035 | G438: 46081 | I438: 000050315032R | J438: DISCO AL.L.GREEN 315/32 RIC | K438: alluminio | L438: =VLOOKUP(K438,'COMM ITY- ENG'!A:B,2,FALSE) -> aluminium | N438: 2250 | O438: kg | Q438: =+R438/N438 -> 3.642 | R438: 8194.5 | S438: =IFERROR(VLOOKUP(J438,'DESC ITY - ENG'!B:C,2,FALSE),VLOOKUP(I438,'DESC ITY - ENG'!A:C,3,FALSE)) -> Aluminum Disc L. Green Series 315mm x 3.2mm Replacement Part [cite: 3] | T438: =IFERROR(VLOOKUP(S438,'DESC ITY - ENG'!C:D,2,FALSE),VLOOKUP(J438,'DESC ITY - ENG'!B:D,3,FALSE)) -> ALM- | U438: =VLOOKUP(T438,'STANDARD COMM'!A:B,2,FALSE) -> ALUM MATERIAL | V438: =IF(T438="","(blank)",IF(COUNTIF('STANDARD COMM'!A:A,T438)>0,"OK","OUT OF SCOPE")) -> OK
A439: OF0040508 | B439: 45582.527 | D439: F502625 | E439: INTERNATIONAL COOKWARE S.A.S. | F439: 26AFC000033 | G439: 46081 | I439: 000750000003 | J439: OVALE VET.BORO.26X18 REF.6/360 | K439: accessori finiti | L439: =VLOOKUP(K439,'COMM ITY- ENG'!A:B,2,FALSE) -> finished accessories | N439: 1002 | O439: NR | Q439: =+R439/N439 -> 2.4 | R439: 2404.8 | S439: =IFERROR(VLOOKUP(J439,'DESC ITY - ENG'!B:C,2,FALSE),VLOOKUP(I439,'DESC ITY - ENG'!A:C,3,FALSE)) -> Oval Baking Dish Borosilicate Glass 26x18 cm | T439: =IFERROR(VLOOKUP(S439,'DESC ITY - ENG'!C:D,2,FALSE),VLOOKUP(J439,'DESC ITY - ENG'!B:D,3,FALSE)) -> PAN- | U439: =VLOOKUP(T439,'STANDARD COMM'!A:B,2,FALSE) -> BODY | V439: =IF(T439="","(blank)",IF(COUNTIF('STANDARD COMM'!A:A,T439)>0,"OK","OUT OF SCOPE")) -> OK
A440: OF0040508 | B440: 45582.527 | D440: F502625 | E440: INTERNATIONAL COOKWARE S.A.S. | F440: 26AFC000033 | G440: 46081 | I440: 000750000005 | J440: TEGLIA RET.VET.BORO.39X24 REF.6/216 | K440: accessori finiti | L440: =VLOOKUP(K440,'COMM ITY- ENG'!A:B,2,FALSE) -> finished accessories | N440: 900 | O440: NR | Q440: =+R440/N440 -> 2.95 | R440: 2655 | S440: =IFERROR(VLOOKUP(J440,'DESC ITY - ENG'!B:C,2,FALSE),VLOOKUP(I440,'DESC ITY - ENG'!A:C,3,FALSE)) -> Rectangular Baking Dish Borosilicate Glass 39x24 cm | T440: =IFERROR(VLOOKUP(S440,'DESC ITY - ENG'!C:D,2,FALSE),VLOOKUP(J440,'DESC ITY - ENG'!B:D,3,FALSE)) -> PAN- | U440: =VLOOKUP(T440,'STANDARD COMM'!A:B,2,FALSE) -> BODY | V440: =IF(T440="","(blank)",IF(COUNTIF('STANDARD COMM'!A:A,T440)>0,"OK","OUT OF SCOPE")) -> OK
A441: OF0040508 | B441: 45582.527 | D441: F502625 | E441: INTERNATIONAL COOKWARE S.A.S. | F441: 26AFC000033 | G441: 46081 | I441: 000750000006 | J441: TEGLIA RET.VET.BORO.32X20 REF.7/308 | K441: accessori finiti | L441: =VLOOKUP(K441,'COMM ITY- ENG'!A:B,2,FALSE) -> finished accessories | N441: 1232 | O441: NR | Q441: =+R441/N441 -> 2.3 | R441: 2833.6 | S441: =IFERROR(VLOOKUP(J441,'DESC ITY - ENG'!B:C,2,FALSE),VLOOKUP(I441,'DESC ITY - ENG'!A:C,3,FALSE)) -> Rectangular Baking Dish Borosilicate Glass 32x20 cm | T441: =IFERROR(VLOOKUP(S441,'DESC ITY - ENG'!C:D,2,FALSE),VLOOKUP(J441,'DESC ITY - ENG'!B:D,3,FALSE)) -> PAN- | U441: =VLOOKUP(T441,'STANDARD COMM'!A:B,2,FALSE) -> BODY | V441: =IF(T441="","(blank)",IF(COUNTIF('STANDARD COMM'!A:A,T441)>0,"OK","OUT OF SCOPE")) -> OK
A442: OF0040239 | B442: 45583.663 | D442: F502408 | E442: ILAG INDUSTRIELACK AG | F442: 26AFF000050 | G442: 46081 | I442: 003040104002 | J442: PRIMER 1213-009 DURIT PROTECT PRO BLACK | K442: prodotti chimici | L442: =VLOOKUP(K442,'COMM ITY- ENG'!A:B,2,FALSE) -> chemical products | N442: 502 | O442: kg | Q442: =+R442/N442 -> 16.2 | R442: 8132.4 | S442: =IFERROR(VLOOKUP(J442,'DESC ITY - ENG'!B:C,2,FALSE),VLOOKUP(I442,'DESC ITY - ENG'!A:C,3,FALSE)) -> Coating Durit Protect Pro Black Primer 1213-009 | T442: =IFERROR(VLOOKUP(S442,'DESC ITY - ENG'!C:D,2,FALSE),VLOOKUP(J442,'DESC ITY - ENG'!B:D,3,FALSE)) -> INM- | U442: =VLOOKUP(T442,'STANDARD COMM'!A:B,2,FALSE) -> INTR TREAT MATERIAL | V442: =IF(T442="","(blank)",IF(COUNTIF('STANDARD COMM'!A:A,T442)>0,"OK","OUT OF SCOPE")) -> OK
A443: OF0039276 | B443: 45589.387 | D443: F506013 | E443: NINGBO CITY BEILUN HECHENG METAL PRODUCTS CO.LTD | F443: 26AFF000043 | G443: 46081 | I443: 0002A0205TS5 | J443: DISCO AC.205/040 C/F 2,5 MM+TAGLI STRETTI+FORO CENTRALE 50mm | K443: acciaio | L443: =VLOOKUP(K443,'COMM ITY- ENG'!A:B,2,FALSE) -> steel | N443: 60000 | O443: NR | Q443: =+R443/N443 -> 0.21637283 | R443: 12982.37 | S443: =IFERROR(VLOOKUP(J443,'DESC ITY - ENG'!B:C,2,FALSE),VLOOKUP(I443,'DESC ITY - ENG'!A:C,3,FALSE)) -> Steel Disc AC.205/040 2.5mm Narrow Slots + 50mm Center Hole [cite: 1] | T443: =IFERROR(VLOOKUP(S443,'DESC ITY - ENG'!C:D,2,FALSE),VLOOKUP(J443,'DESC ITY - ENG'!B:D,3,FALSE)) -> SM-- | U443: =VLOOKUP(T443,'STANDARD COMM'!A:B,2,FALSE) -> STEEL MATERIAL | V443: =IF(T443="","(blank)",IF(COUNTIF('STANDARD COMM'!A:A,T443)>0,"OK","OUT OF SCOPE")) -> OK
A444: OF0039875 | B444: 45593.687 | D444: F600780 | E444: GULBAK BAKALIT METAL VE TEKSTIL SAN. ve TIC. LTD. STI | F444: 26AFF000049 | G444: 46081 | I444: 000281710003 | J444: MANICO AC.SOLE CORTO C/LOGO MC AISI 430 SABBIATO CAS.433 16 | K444: manigliame | L444: =VLOOKUP(K444,'COMM ITY- ENG'!A:B,2,FALSE) -> handles | N444: 15000 | O444: NR | Q444: =+R444/N444 -> 1.137 | R444: 17055 | S444: =IFERROR(VLOOKUP(J444,'DESC ITY - ENG'!B:C,2,FALSE),VLOOKUP(I444,'DESC ITY - ENG'!A:C,3,FALSE)) -> Steel Handle AC.SOLE Short w/Logo MC AISI 430 Casserole 433-16 Sandblasted [cite: 4] | T444: =IFERROR(VLOOKUP(S444,'DESC ITY - ENG'!C:D,2,FALSE),VLOOKUP(J444,'DESC ITY - ENG'!B:D,3,FALSE)) -> SHDL- | U444: =VLOOKUP(T444,'STANDARD COMM'!A:B,2,FALSE) -> #N/A | V444: =IF(T444="","(blank)",IF(COUNTIF('STANDARD COMM'!A:A,T444)>0,"OK","OUT OF SCOPE")) -> OUT OF SCOPE
A445: OF0039874 | B445: 45593.687 | D445: F600732 | E445: MUTLU METAL DIS TICARET LTD.STI | F445: 26AFF000052 | G445: 46081 | I445: 000281710006 | J445: MANICO AC.SOLE LUNGO C/LOGO MC AISI 430 SABBIATO TEG.379 26 | K445: manigliame | L445: =VLOOKUP(K445,'COMM ITY- ENG'!A:B,2,FALSE) -> handles | N445: 15015 | O445: NR | Q445: =+R445/N445 -> 1.29 | R445: 19369.35 | S445: =IFERROR(VLOOKUP(J445,'DESC ITY - ENG'!B:C,2,FALSE),VLOOKUP(I445,'DESC ITY - ENG'!A:C,3,FALSE)) -> Steel Handle AC.SOLE Long w/Logo MC AISI 430 Skillet 379-26 Sandblasted [cite: 4 5] | T445: =IFERROR(VLOOKUP(S445,'DESC ITY - ENG'!C:D,2,FALSE),VLOOKUP(J445,'DESC ITY - ENG'!B:D,3,FALSE)) -> HDL-- | U445: =VLOOKUP(T445,'STANDARD COMM'!A:B,2,FALSE) -> #N/A | V445: =IF(T445="","(blank)",IF(COUNTIF('STANDARD COMM'!A:A,T445)>0,"OK","OUT OF SCOPE")) -> OUT OF SCOPE
... A509: OF0039875 | B509: 45632.698 | D509: F600780 | E509: GULBAK BAKALIT METAL VE TEKSTIL SAN. ve TIC. LTD. STI | F509: 26AFF000056 | G509: 46081 | I509: 000281710001 | J509: MANICO AC.SOLE CORTO C/LOGO MC AISI 430 SABBIATO PAD.279 20 | K509: manigliame | L509: =VLOOKUP(K509,'COMM ITY- ENG'!A:B,2,FALSE) -> handles | N509: 5000 | O509: NR | Q509: =+R509/N509 -> 1.137 | R509: 5685 | S509: =IFERROR(VLOOKUP(J509,'DESC ITY - ENG'!B:C,2,FALSE),VLOOKUP(I509,'DESC ITY - ENG'!A:C,3,FALSE)) -> Steel Handle AC.SOLE Short w/Logo MC AISI 430 Pan 279-20 Sandblasted [cite: 4] | T509: =IFERROR(VLOOKUP(S509,'DESC ITY - ENG'!C:D,2,FALSE),VLOOKUP(J509,'DESC ITY - ENG'!B:D,3,FALSE)) -> SHDL- | U509: =VLOOKUP(T509,'STANDARD COMM'!A:B,2,FALSE) -> #N/A | V509: =IF(T509="","(blank)",IF(COUNTIF('STANDARD COMM'!A:A,T509)>0,"OK","OUT OF SCOPE")) -> OUT OF SCOPE
B510: 45635.558 | D510: F600780 | E510: GULBAK BAKALIT METAL VE TEKSTIL SAN. ve TIC. LTD. STI | F510: 26AFF000056 | G510: 46081 | I510: 000281710003 | J510: MANICO AC.SOLE CORTO C/LOGO MC AISI 430 SABBIATO CAS.433 16 | K510: manigliame | L510: =VLOOKUP(K510,'COMM ITY- ENG'!A:B,2,FALSE) -> handles | N510: 6000 | O510: NR | Q510: =+R510/N510 -> 1.137 | R510: 6822 | S510: =IFERROR(VLOOKUP(J510,'DESC ITY - ENG'!B:C,2,FALSE),VLOOKUP(I510,'DESC ITY - ENG'!A:C,3,FALSE)) -> Steel Handle AC.SOLE Short w/Logo MC AISI 430 Casserole 433-16 Sandblasted [cite: 4] | T510: =IFERROR(VLOOKUP(S510,'DESC ITY - ENG'!C:D,2,FALSE),VLOOKUP(J510,'DESC ITY - ENG'!B:D,3,FALSE)) -> SHDL- | U510: =VLOOKUP(T510,'STANDARD COMM'!A:B,2,FALSE) -> #N/A | V510: =IF(T510="","(blank)",IF(COUNTIF('STANDARD COMM'!A:A,T510)>0,"OK","OUT OF SCOPE")) -> OUT OF SCOPE
A511: OF0039875 | B511: 45635.558 | D511: F600780 | E511: GULBAK BAKALIT METAL VE TEKSTIL SAN. ve TIC. LTD. STI | F511: 26AFF000056 | G511: 46081 | I511: 000281710005 | J511: MANICO AC.SOLE LUNGO C/LOGO MC AISI 430 SABBIATO PAD.279 30 | K511: manigliame | L511: =VLOOKUP(K511,'COMM ITY- ENG'!A:B,2,FALSE) -> handles | N511: 20000 | O511: NR | Q511: =+R511/N511 -> 1.227 | R511: 24540 | S511: =IFERROR(VLOOKUP(J511,'DESC ITY - ENG'!B:C,2,FALSE),VLOOKUP(I511,'DESC ITY - ENG'!A:C,3,FALSE)) -> Steel Handle AC.SOLE Long w/Logo MC AISI 430 Pan 279-30 Sandblasted [cite: 4] | T511: =IFERROR(VLOOKUP(S511,'DESC ITY - ENG'!C:D,2,FALSE),VLOOKUP(J511,'DESC ITY - ENG'!B:D,3,FALSE)) -> HDL-- | U511: =VLOOKUP(T511,'STANDARD COMM'!A:B,2,FALSE) -> #N/A | V511: =IF(T511="","(blank)",IF(COUNTIF('STANDARD COMM'!A:A,T511)>0,"OK","OUT OF SCOPE")) -> OUT OF SCOPE
A512: OF0040184 | B512: 45635.558 | D512: F600850 | E512: TEKNIKEL MAKINA KALIP IMALAT SAN. VE TIC. LTD STI. | F512: 26AFF000057 | G512: 46081 | I512: 000250028001 | J512: MANICO L890/2 ODINO NERO SAT. | K512: manigliame | L512: =VLOOKUP(K512,'COMM ITY- ENG'!A:B,2,FALSE) -> handles | N512: 22500 | O512: NR | Q512: =+R512/N512 -> 0.35 | R512: 7875 | S512: =IFERROR(VLOOKUP(J512,'DESC ITY - ENG'!B:C,2,FALSE),VLOOKUP(I512,'DESC ITY - ENG'!A:C,3,FALSE)) -> Handle 1890/2 Odino Black Satin Finish [cite: 5] | T512: =IFERROR(VLOOKUP(S512,'DESC ITY - ENG'!C:D,2,FALSE),VLOOKUP(J512,'DESC ITY - ENG'!B:D,3,FALSE)) -> HDL-- | U512: =VLOOKUP(T512,'STANDARD COMM'!A:B,2,FALSE) -> #N/A | V512: =IF(T512="","(blank)",IF(COUNTIF('STANDARD COMM'!A:A,T512)>0,"OK","OUT OF SCOPE")) -> OUT OF SCOPE
A513: OF0039471 | B513: 45635.558 | D513: F600985 | E513: EL.MA SNC | F513: 26AFI000487 | G513: 46081 | I513: 001717795001 | J513: BOX FLEXO 7795+KIT DIV.MADE IN 16 CM SAUCE SCMI 16095 | K513: cartoni e casse | L513: =VLOOKUP(K513,'COMM ITY- ENG'!A:B,2,FALSE) -> cartons and boxes | N513: 2836 | O513: NR | Q513: =+R513/N513 -> 1.205 | R513: 3417.38 | S513: =IFERROR(VLOOKUP(J513,'DESC ITY - ENG'!B:C,2,FALSE),VLOOKUP(I513,'DESC ITY - ENG'!A:C,3,FALSE)) -> Flexo Box 7795 + Divider Kit, Made In 16cm | T513: =IFERROR(VLOOKUP(S513,'DESC ITY - ENG'!C:D,2,FALSE),VLOOKUP(J513,'DESC ITY - ENG'!B:D,3,FALSE)) -> BOX- | U513: =VLOOKUP(T513,'STANDARD COMM'!A:B,2,FALSE) -> BOX / CARTON | V513: =IF(T513="","(blank)",IF(COUNTIF('STANDARD COMM'!A:A,T513)>0,"OK","OUT OF SCOPE")) -> OK
A514: OF0039933 | B514: 45635.567 | D514: F600985 | E514: EL.MA SNC | F514: 26AFI000487 | G514: 46081 | I514: 001717796001 | J514: BOX FLEXO 7796+KIT DIV.MADE IN 20 CM SKILLET SCMI 20040 | K514: cartoni e casse | L514: =VLOOKUP(K514,'COMM ITY- ENG'!A:B,2,FALSE) -> cartons and boxes | N514: 7070 | O514: NR | Q514: =+R514/N514 -> 0.835 | R514: 5903.45 | S514: =IFERROR(VLOOKUP(J514,'DESC ITY - ENG'!B:C,2,FALSE),VLOOKUP(I514,'DESC ITY - ENG'!A:C,3,FALSE)) -> Flexo Box 7796 + Divider Kit for 20cm Skillet SCMI 20040 | T514: =IFERROR(VLOOKUP(S514,'DESC ITY - ENG'!C:D,2,FALSE),VLOOKUP(J514,'DESC ITY - ENG'!B:D,3,FALSE)) -> BOX- | U514: =VLOOKUP(T514,'STANDARD COMM'!A:B,2,FALSE) -> BOX / CARTON | V514: =IF(T514="","(blank)",IF(COUNTIF('STANDARD COMM'!A:A,T514)>0,"OK","OUT OF SCOPE")) -> OK
A515: OF0040028 | B515: 45635.7 | D515: F600456 | E515: ALMESAN ALUMINYUM SAN.VE TIC. A.S | F515: 26AFF000045 | G515: 46081 | I515: 000040235029R | J515: DISCO AL.4006 235/29 RIC | K515: alluminio | L515: =VLOOKUP(K515,'COMM ITY- ENG'!A:B,2,FALSE) -> aluminium | N515: 1006 | O515: kg | Q515: =+R515/N515 -> 3.455 | R515: 3475.73 | S515: =IFERROR(VLOOKUP(J515,'DESC ITY - ENG'!B:C,2,FALSE),VLOOKUP(I515,'DESC ITY - ENG'!A:C,3,FALSE)) -> Aluminum Disc Alloy 4006 235mm x 2.9mm Replacement Part [cite: 1] | T515: =IFERROR(VLOOKUP(S515,'DESC ITY - ENG'!C:D,2,FALSE),VLOOKUP(J515,'DESC ITY - ENG'!B:D,3,FALSE)) -> ALM- | U515: =VLOOKUP(T515,'STANDARD COMM'!A:B,2,FALSE) -> ALUM MATERIAL | V515: =IF(T515="","(blank)",IF(COUNTIF('STANDARD COMM'!A:A,T515)>0,"OK","OUT OF SCOPE")) -> OK
A516: OF0040028 | B516: 45635.7 | D516: F600456 | E516: ALMESAN ALUMINYUM SAN.VE TIC. A.S | F516: 26AFF000045 | G516: 46081 | I516: 000040265029R | J516: DISCO AL.4006 265/29 RIC | K516: alluminio | L516: =VLOOKUP(K516,'COMM ITY- ENG'!A:B,2,FALSE) -> aluminium | N516: 1050 | O516: kg | Q516: =+R516/N516 -> 3.455 | R516: 3627.75 | S516: =IFERROR(VLOOKUP(J516,'DESC ITY - ENG'!B:C,2,FALSE),VLOOKUP(I516,'DESC ITY - ENG'!A:C,3,FALSE)) -> Aluminum Disc Alloy 4006 265mm x 2.9mm Replacement Part [cite: 2] | T516: =IFERROR(VLOOKUP(S516,'DESC ITY - ENG'!C:D,2,FALSE),VLOOKUP(J516,'DESC ITY - ENG'!B:D,3,FALSE)) -> ALM- | U516: =VLOOKUP(T516,'STANDARD COMM'!A:B,2,FALSE) -> ALUM MATERIAL | V516: =IF(T516="","(blank)",IF(COUNTIF('STANDARD COMM'!A:A,T516)>0,"OK","OUT OF SCOPE")) -> OK
A517: OF0040028 | B517: 45635.7 | D517: F600456 | E517: ALMESAN ALUMINYUM SAN.VE TIC. A.S | F517: 26AFF000045 | G517: 46081 | I517: 000040265032R | J517: DISCO AL.4006 265/32 RIC | K517: alluminio | L517: =VLOOKUP(K517,'COMM ITY- ENG'!A:B,2,FALSE) -> aluminium | N517: 3050 | O517: kg | Q517: =+R517/N517 -> 3.455 | R517: 10537.75 | S517: =IFERROR(VLOOKUP(J517,'DESC ITY - ENG'!B:C,2,FALSE),VLOOKUP(I517,'DESC ITY - ENG'!A:C,3,FALSE)) -> Aluminum Disc Alloy 4006 265mm x 3.2mm Replacement Part [cite: 2] | T517: =IFERROR(VLOOKUP(S517,'DESC ITY - ENG'!C:D,2,FALSE),VLOOKUP(J517,'DESC ITY - ENG'!B:D,3,FALSE)) -> ALM- | U517: =VLOOKUP(T517,'STANDARD COMM'!A:B,2,FALSE) -> ALUM MATERIAL | V517: =IF(T517="","(blank)",IF(COUNTIF('STANDARD COMM'!A:A,T517)>0,"OK","OUT OF SCOPE")) -> OK
A518: OF0040528 | B518: 45635.7 | D518: F504561 | E518: KOREA FINE CERAMIC CO., LTD | F518: 26AFF000044 | G518: 46081 | I518: 003091002018 | J518: G8 BS GHOST GREY FC-20917A | K518: prodotti chimici | L518: =VLOOKUP(K518,'COMM ITY- ENG'!A:B,2,FALSE) -> chemical products | N518: 600.12 | O518: kg | Q518: =+R518/N518 -> 16 | R518: 9601.92 | S518: =IFERROR(VLOOKUP(J518,'DESC ITY - ENG'!B:C,2,FALSE),VLOOKUP(I518,'DESC ITY - ENG'!A:C,3,FALSE)) -> Coating G8 Base System Ghost Grey FC-20917A | T518: =IFERROR(VLOOKUP(S518,'DESC ITY - ENG'!C:D,2,FALSE),VLOOKUP(J518,'DESC ITY - ENG'!B:D,3,FALSE)) -> INM- | U518: =VLOOKUP(T518,'STANDARD COMM'!A:B,2,FALSE) -> INTR TREAT MATERIAL | V518: =IF(T518="","(blank)",IF(COUNTIF('STANDARD COMM'!A:A,T518)>0,"OK","OUT OF SCOPE")) -> OK
A519: OF0039276 | B519: 45635.7 | D519: F506013 | E519: NINGBO CITY BEILUN HECHENG METAL PRODUCTS CO.LTD | F519: 26AFF000043 | G519: 46081 | I519: 0002A0185TS5 | J519: DISCO AC.185/040 C/F 2,5 MM+TAGLI STRETTI+FORO CENTRALE 50mm | K519: acciaio | L519: =VLOOKUP(K519,'COMM ITY- ENG'!A:B,2,FALSE) -> steel | N519: 10000 | O519: NR | Q519: =+R519/N519 -> 0.18315 | R519: 1831.5 | S519: =IFERROR(VLOOKUP(J519,'DESC ITY - ENG'!B:C,2,FALSE),VLOOKUP(I519,'DESC ITY - ENG'!A:C,3,FALSE)) -> 5 MM+TAGLI STRETTI+FORO CENTRALE 50mmSteel Disc AC.185/040 2.5mm Narrow Slots + 50mm Center Hole [cite: 1] | T519: =IFERROR(VLOOKUP(S519,'DESC ITY - ENG'!C:D,2,FALSE),VLOOKUP(J519,'DESC ITY - ENG'!B:D,3,FALSE)) -> SSM- | U519: =VLOOKUP(T519,'STANDARD COMM'!A:B,2,FALSE) -> STAINLESS STEEL MATERIAL | V519: =IF(T519="","(blank)",IF(COUNTIF('STANDARD COMM'!A:A,T519)>0,"OK","OUT OF SCOPE")) -> OK
A520: OF0039276 | B520: 45635.7 | D520: F506013 | E520: NINGBO CITY BEILUN HECHENG METAL PRODUCTS CO.LTD | F520: 26AFF000043 | G520: 46081 | I520: 0002A0195TS5 | J520: DISCO AC.195/040 C/F 2,5 MM+TAGLI STRETTI+FORO CENTRALE 50mm | K520: acciaio | L520: =VLOOKUP(K520,'COMM ITY- ENG'!A:B,2,FALSE) -> steel | N520: 50000 | O520: NR | Q520: =+R520/N520 -> 0.2001874 | R520: 10009.37 | S520: =IFERROR(VLOOKUP(J520,'DESC ITY - ENG'!B:C,2,FALSE),VLOOKUP(I520,'DESC ITY - ENG'!A:C,3,FALSE)) -> 5 MM+TAGLI STRETTI+FORO CENTRALE 50mmSteel Disc AC.195/040 2.5mm Narrow Slots + 50mm Center Hole [cite: 1] | T520: =IFERROR(VLOOKUP(S520,'DESC ITY - ENG'!C:D,2,FALSE),VLOOKUP(J520,'DESC ITY - ENG'!B:D,3,FALSE)) -> SSM- | U520: =VLOOKUP(T520,'STANDARD COMM'!A:B,2,FALSE) -> STAINLESS STEEL MATERIAL | V520: =IF(T520="","(blank)",IF(COUNTIF('STANDARD COMM'!A:A,T520)>0,"OK","OUT OF SCOPE")) -> OK
A521: OF0039875 | B521: 45636.469 | D521: F600780 | E521: GULBAK BAKALIT METAL VE TEKSTIL SAN. ve TIC. LTD. STI | F521: 26AFF000049 | G521: 46081 | I521: 000281710005 | J521: MANICO AC.SOLE LUNGO C/LOGO MC AISI 430 SABBIATO PAD.279 30 | K521: manigliame | L521: =VLOOKUP(K521,'COMM ITY- ENG'!A:B,2,FALSE) -> handles | N521: 30000 | O521: NR | Q521: =+R521/N521 -> 1.227 | R521: 36810 | S521: =IFERROR(VLOOKUP(J521,'DESC ITY - ENG'!B:C,2,FALSE),VLOOKUP(I521,'DESC ITY - ENG'!A:C,3,FALSE)) -> Steel Handle AC.SOLE Long w/Logo MC AISI 430 Pan 279-30 Sandblasted [cite: 4] | T521: =IFERROR(VLOOKUP(S521,'DESC ITY - ENG'!C:D,2,FALSE),VLOOKUP(J521,'DESC ITY - ENG'!B:D,3,FALSE)) -> HDL-- | U521: =VLOOKUP(T521,'STANDARD COMM'!A:B,2,FALSE) -> #N/A | V521: =IF(T521="","(blank)",IF(COUNTIF('STANDARD COMM'!A:A,T521)>0,"OK","OUT OF SCOPE")) -> OUT OF SCOPE
A522: OF0040356 | B522: 45638.7 | D522: F504561 | E522: KOREA FINE CERAMIC CO., LTD | F522: 26AFF000048 | G522: 46081 | I522: 003091002018 | J522: G8 BS GHOST GREY FC-20917A | K522: prodotti chimici | L522: =VLOOKUP(K522,'COMM ITY- ENG'!A:B,2,FALSE) -> chemical products | N522: 500.1 | O522: kg | Q522: =+R522/N522 -> 16 | R522: 8001.6 | S522: =IFERROR(VLOOKUP(J522,'DESC ITY - ENG'!B:C,2,FALSE),VLOOKUP(I522,'DESC ITY - ENG'!A:C,3,FALSE)) -> Coating G8 Base System Ghost Grey FC-20917A | T522: =IFERROR(VLOOKUP(S522,'DESC ITY - ENG'!C:D,2,FALSE),VLOOKUP(J522,'DESC ITY - ENG'!B:D,3,FALSE)) -> INM- | U522: =VLOOKUP(T522,'STANDARD COMM'!A:B,2,FALSE) -> INTR TREAT MATERIAL | V522: =IF(T522="","(blank)",IF(COUNTIF('STANDARD COMM'!A:A,T522)>0,"OK","OUT OF SCOPE")) -> OK
... A545: OF0039874 | B545: 45642.711 | D545: F600732 | E545: MUTLU METAL DIS TICARET LTD.STI | F545: 26AFF000046 | G545: 46081 | I545: 000281710002 | J545: MANICO AC.SOLE CORTO C/LOGO MC AISI 430 SABBIATO PAD.279 24 | K545: manigliame | L545: =VLOOKUP(K545,'COMM ITY- ENG'!A:B,2,FALSE) -> handles | N545: 10000 | O545: NR | Q545: =+R545/N545 -> 1.19 | R545: 11900 | S545: =IFERROR(VLOOKUP(J545,'DESC ITY - ENG'!B:C,2,FALSE),VLOOKUP(I545,'DESC ITY - ENG'!A:C,3,FALSE)) -> Steel Handle AC.SOLE Short w/Logo MC AISI 430 Pan 279-24 Sandblasted [cite: 4] | T545: =IFERROR(VLOOKUP(S545,'DESC ITY - ENG'!C:D,2,FALSE),VLOOKUP(J545,'DESC ITY - ENG'!B:D,3,FALSE)) -> SHDL- | U545: =VLOOKUP(T545,'STANDARD COMM'!A:B,2,FALSE) -> #N/A | V545: =IF(T545="","(blank)",IF(COUNTIF('STANDARD COMM'!A:A,T545)>0,"OK","OUT OF SCOPE")) -> OUT OF SCOPE
B546: 45642.711 | D546: F600732 | E546: MUTLU METAL DIS TICARET LTD.STI | F546: 26AFF000046 | G546: 46081 | I546: 000281710002 | J546: MANICO AC.SOLE CORTO C/LOGO MC AISI 430 SABBIATO PAD.279 24 | K546: manigliame | L546: =VLOOKUP(K546,'COMM ITY- ENG'!A:B,2,FALSE) -> handles | N546: 9292 | O546: NR | Q546: =+R546/N546 -> 1.19 | R546: 11057.48 | S546: =IFERROR(VLOOKUP(J546,'DESC ITY - ENG'!B:C,2,FALSE),VLOOKUP(I546,'DESC ITY - ENG'!A:C,3,FALSE)) -> Steel Handle AC.SOLE Short w/Logo MC AISI 430 Pan 279-24 Sandblasted [cite: 4] | T546: =IFERROR(VLOOKUP(S546,'DESC ITY - ENG'!C:D,2,FALSE),VLOOKUP(J546,'DESC ITY - ENG'!B:D,3,FALSE)) -> SHDL- | U546: =VLOOKUP(T546,'STANDARD COMM'!A:B,2,FALSE) -> #N/A | V546: =IF(T546="","(blank)",IF(COUNTIF('STANDARD COMM'!A:A,T546)>0,"OK","OUT OF SCOPE")) -> OUT OF SCOPE
A547: OF0039874 | B547: 45642.711 | D547: F600732 | E547: MUTLU METAL DIS TICARET LTD.STI | F547: 26AFF000046 | G547: 46081 | I547: 000320380001 | J547: POMOLO AC.SOLE C/LOGO MC AISI 430 SABBIATO | K547: manigliame | L547: =VLOOKUP(K547,'COMM ITY- ENG'!A:B,2,FALSE) -> handles | N547: 3960 | O547: NR | Q547: =+R547/N547 -> 1.15 | R547: 4554 | S547: =IFERROR(VLOOKUP(J547,'DESC ITY - ENG'!B:C,2,FALSE),VLOOKUP(I547,'DESC ITY - ENG'!A:C,3,FALSE)) -> Steel Knob AC.SOLE w/Logo MC AISI 430 Sandblasted [cite: 5] | T547: =IFERROR(VLOOKUP(S547,'DESC ITY - ENG'!C:D,2,FALSE),VLOOKUP(J547,'DESC ITY - ENG'!B:D,3,FALSE)) -> KNOB | U547: =VLOOKUP(T547,'STANDARD COMM'!A:B,2,FALSE) -> KNOB | V547: =IF(T547="","(blank)",IF(COUNTIF('STANDARD COMM'!A:A,T547)>0,"OK","OUT OF SCOPE")) -> OK
A548: OF0039918 | B548: 45642.711 | D548: F013344 | E548: VITINOX SAS DI GUGLIELMELLI R.& C. | F548: 26AFI000488 | G548: 46081 | I548: 000450626001 | J548: RIBATTINO AC.6X12 MADE IN | K548: accessori x manigl. | L548: =VLOOKUP(K548,'COMM ITY- ENG'!A:B,2,FALSE) -> accessories for handles | N548: 100000 | O548: NR | Q548: =+R548/N548 -> 0.0646 | R548: 6460 | S548: =IFERROR(VLOOKUP(J548,'DESC ITY - ENG'!B:C,2,FALSE),VLOOKUP(I548,'DESC ITY - ENG'!A:C,3,FALSE)) -> Steel Rivet 6x12 mm | T548: =IFERROR(VLOOKUP(S548,'DESC ITY - ENG'!C:D,2,FALSE),VLOOKUP(J548,'DESC ITY - ENG'!B:D,3,FALSE)) -> RIV- | U548: =VLOOKUP(T548,'STANDARD COMM'!A:B,2,FALSE) -> RIVET | V548: =IF(T548="","(blank)",IF(COUNTIF('STANDARD COMM'!A:A,T548)>0,"OK","OUT OF SCOPE")) -> OK
A549: OF0040247 | B549: 45645.653 | D549: F600456 | E549: ALMESAN ALUMINYUM SAN.VE TIC. A.S | F549: 26AFF000055 | G549: 46081 | I549: 000040235036R | J549: DISCO AL.4006 235/36 RIC | K549: alluminio | L549: =VLOOKUP(K549,'COMM ITY- ENG'!A:B,2,FALSE) -> aluminium | N549: 2560 | O549: kg | Q549: =+R549/N549 -> 3.732 | R549: 9553.92 | S549: =IFERROR(VLOOKUP(J549,'DESC ITY - ENG'!B:C,2,FALSE),VLOOKUP(I549,'DESC ITY - ENG'!A:C,3,FALSE)) -> Aluminum Disc Alloy 4006 235mm x 3.6mm Replacement Part [cite: 2] | T549: =IFERROR(VLOOKUP(S549,'DESC ITY - ENG'!C:D,2,FALSE),VLOOKUP(J549,'DESC ITY - ENG'!B:D,3,FALSE)) -> ALM- | U549: =VLOOKUP(T549,'STANDARD COMM'!A:B,2,FALSE) -> ALUM MATERIAL | V549: =IF(T549="","(blank)",IF(COUNTIF('STANDARD COMM'!A:A,T549)>0,"OK","OUT OF SCOPE")) -> OK
A550: OF0040247 | B550: 45645.653 | D550: F600456 | E550: ALMESAN ALUMINYUM SAN.VE TIC. A.S | F550: 26AFF000055 | G550: 46081 | I550: 000040310036R | J550: DISCO AL.4006 310/36 RIC | K550: alluminio | L550: =VLOOKUP(K550,'COMM ITY- ENG'!A:B,2,FALSE) -> aluminium | N550: 1540 | O550: kg | Q550: =+R550/N550 -> 3.732 | R550: 5747.28 | S550: =IFERROR(VLOOKUP(J550,'DESC ITY - ENG'!B:C,2,FALSE),VLOOKUP(I550,'DESC ITY - ENG'!A:C,3,FALSE)) -> Aluminum Disc Alloy 4006 310mm x 3.6mm Replacement Part [cite: 2] | T550: =IFERROR(VLOOKUP(S550,'DESC ITY - ENG'!C:D,2,FALSE),VLOOKUP(J550,'DESC ITY - ENG'!B:D,3,FALSE)) -> ALM- | U550: =VLOOKUP(T550,'STANDARD COMM'!A:B,2,FALSE) -> ALUM MATERIAL | V550: =IF(T550="","(blank)",IF(COUNTIF('STANDARD COMM'!A:A,T550)>0,"OK","OUT OF SCOPE")) -> OK
A551: OF0040247 | B551: 45645.653 | D551: F600456 | E551: ALMESAN ALUMINYUM SAN.VE TIC. A.S | F551: 26AFF000055 | G551: 46081 | I551: 000040350036R | J551: DISCO AL.4006 350/36 RIC | K551: alluminio | L551: =VLOOKUP(K551,'COMM ITY- ENG'!A:B,2,FALSE) -> aluminium | N551: 2544 | O551: kg | Q551: =+R551/N551 -> 3.7320008 | R551: 9494.21 | S551: =IFERROR(VLOOKUP(J551,'DESC ITY - ENG'!B:C,2,FALSE),VLOOKUP(I551,'DESC ITY - ENG'!A:C,3,FALSE)) -> Aluminum Disc Alloy 4006 350mm x 3.6mm Replacement Part [cite: 2] | T551: =IFERROR(VLOOKUP(S551,'DESC ITY - ENG'!C:D,2,FALSE),VLOOKUP(J551,'DESC ITY - ENG'!B:D,3,FALSE)) -> ALM- | U551: =VLOOKUP(T551,'STANDARD COMM'!A:B,2,FALSE) -> ALUM MATERIAL | V551: =IF(T551="","(blank)",IF(COUNTIF('STANDARD COMM'!A:A,T551)>0,"OK","OUT OF SCOPE")) -> OK
A552: OF0040247 | B552: 45645.653 | D552: F600456 | E552: ALMESAN ALUMINYUM SAN.VE TIC. A.S | F552: 26AFF000055 | G552: 46081 | I552: 000040355036R | J552: DISCO AL.4006 355/36 RIC | K552: alluminio | L552: =VLOOKUP(K552,'COMM ITY- ENG'!A:B,2,FALSE) -> aluminium | N552: 6100 | O552: kg | Q552: =+R552/N552 -> 3.732 | R552: 22765.2 | S552: =IFERROR(VLOOKUP(J552,'DESC ITY - ENG'!B:C,2,FALSE),VLOOKUP(I552,'DESC ITY - ENG'!A:C,3,FALSE)) -> Aluminum Disc Alloy 4006 355mm x 3.6mm Replacement Part [cite: 2] | T552: =IFERROR(VLOOKUP(S552,'DESC ITY - ENG'!C:D,2,FALSE),VLOOKUP(J552,'DESC ITY - ENG'!B:D,3,FALSE)) -> ALM- | U552: =VLOOKUP(T552,'STANDARD COMM'!A:B,2,FALSE) -> ALUM MATERIAL | V552: =IF(T552="","(blank)",IF(COUNTIF('STANDARD COMM'!A:A,T552)>0,"OK","OUT OF SCOPE")) -> OK
A553: OF0038802 | B553: 45645.653 | D553: F600958 | E553: EDENTECH CO.LTD. | F553: 26AFF000054 | G553: 46081 | I553: 000030470023 | J553: DISCO 5PLY 470/23 SS304 0,4 + Al1,4 + SS439 0,5 TOT 23/10 | K553: Acciaio multistrato (5PLY) | L553: =VLOOKUP(K553,'COMM ITY- ENG'!A:B,2,FALSE) -> multilayer steel (5PLY) | N553: 1630 | O553: NR | Q553: =+R553/N553 -> 10.04 | R553: 16365.2 | S553: =IFERROR(VLOOKUP(J553,'DESC ITY - ENG'!B:C,2,FALSE),VLOOKUP(I553,'DESC ITY - ENG'!A:C,3,FALSE)) -> 5-Ply Disc SS304/AL/SS439 470mm x 2.3mm Total Thickness 2.3mm [cite: 1] | T553: =IFERROR(VLOOKUP(S553,'DESC ITY - ENG'!C:D,2,FALSE),VLOOKUP(J553,'DESC ITY - ENG'!B:D,3,FALSE)) -> CDM- | U553: =VLOOKUP(T553,'STANDARD COMM'!A:B,2,FALSE) -> CLAD MATERIAL | V553: =IF(T553="","(blank)",IF(COUNTIF('STANDARD COMM'!A:A,T553)>0,"OK","OUT OF SCOPE")) -> OK
B554: 45645.653 | D554: F600780 | E554: GULBAK BAKALIT METAL VE TEKSTIL SAN. ve TIC. LTD. STI | F554: 26AFF000056 | G554: 46081 | I554: 000281710001 | J554: MANICO AC.SOLE CORTO C/LOGO MC AISI 430 SABBIATO PAD.279 20 | K554: manigliame | L554: =VLOOKUP(K554,'COMM ITY- ENG'!A:B,2,FALSE) -> handles | N554: 2000 | O554: NR | Q554: =+R554/N554 -> 1.137 | R554: 2274 | S554: =IFERROR(VLOOKUP(J554,'DESC ITY - ENG'!B:C,2,FALSE),VLOOKUP(I554,'DESC ITY - ENG'!A:C,3,FALSE)) -> Steel Handle AC.SOLE Short w/Logo MC AISI 430 Pan 279-20 Sandblasted [cite: 4] | T554: =IFERROR(VLOOKUP(S554,'DESC ITY - ENG'!C:D,2,FALSE),VLOOKUP(J554,'DESC ITY - ENG'!B:D,3,FALSE)) -> SHDL- | U554: =VLOOKUP(T554,'STANDARD COMM'!A:B,2,FALSE) -> #N/A | V554: =IF(T554="","(blank)",IF(COUNTIF('STANDARD COMM'!A:A,T554)>0,"OK","OUT OF SCOPE")) -> OUT OF SCOPE
A555: OF0040356 | B555: 45645.685 | D555: F504561 | E555: KOREA FINE CERAMIC CO., LTD | F555: 26AFF000048 | G555: 46081 | I555: 003090005031 | J555: G8 BS GRIGIO GRAFITE FC-30949A | K555: prodotti chimici | L555: =VLOOKUP(K555,'COMM ITY- ENG'!A:B,2,FALSE) -> chemical products | N555: 26.67 | O555: kg | Q555: =+R555/N555 -> 0 | R555: 0 | S555: =IFERROR(VLOOKUP(J555,'DESC ITY - ENG'!B:C,2,FALSE),VLOOKUP(I555,'DESC ITY - ENG'!A:C,3,FALSE)) -> G8 BS Graphite Grey FC-30949A | T555: =IFERROR(VLOOKUP(S555,'DESC ITY - ENG'!C:D,2,FALSE),VLOOKUP(J555,'DESC ITY - ENG'!B:D,3,FALSE)) -> INM- | U555: =VLOOKUP(T555,'STANDARD COMM'!A:B,2,FALSE) -> INTR TREAT MATERIAL | V555: =IF(T555="","(blank)",IF(COUNTIF('STANDARD COMM'!A:A,T555)>0,"OK","OUT OF SCOPE")) -> OK
A556: OF0040356 | B556: 45645.685 | D556: F504561 | E556: KOREA FINE CERAMIC CO., LTD | F556: 26AFF000048 | G556: 46081 | I556: 003091001008 | J556: G8 BS DARK GREY FC-30159A | K556: prodotti chimici | L556: =VLOOKUP(K556,'COMM ITY- ENG'!A:B,2,FALSE) -> chemical products | N556: 26.67 | O556: kg | Q556: =+R556/N556 -> 16 | R556: 426.72 | S556: =IFERROR(VLOOKUP(J556,'DESC ITY - ENG'!B:C,2,FALSE),VLOOKUP(I556,'DESC ITY - ENG'!A:C,3,FALSE)) -> G8 BS Dark Grey FC-30159A | T556: =IFERROR(VLOOKUP(S556,'DESC ITY - ENG'!C:D,2,FALSE),VLOOKUP(J556,'DESC ITY - ENG'!B:D,3,FALSE)) -> INM- | U556: =VLOOKUP(T556,'STANDARD COMM'!A:B,2,FALSE) -> INTR TREAT MATERIAL | V556: =IF(T556="","(blank)",IF(COUNTIF('STANDARD COMM'!A:A,T556)>0,"OK","OUT OF SCOPE")) -> OK
A557: OF0040356 | B557: 45645.685 | D557: F504561 | E557: KOREA FINE CERAMIC CO., LTD | F557: 26AFF000048 | G557: 46081 | I557: 003091001015 | J557: G8 BS WHITE FC-1462 A | K557: prodotti chimici | L557: =VLOOKUP(K557,'COMM ITY- ENG'!A:B,2,FALSE) -> chemical products | N557: 200.04 | O557: kg | Q557: =+R557/N557 -> 16 | R557: 3200.64 | S557: =IFERROR(VLOOKUP(J557,'DESC ITY - ENG'!B:C,2,FALSE),VLOOKUP(I557,'DESC ITY - ENG'!A:C,3,FALSE)) -> Coating G8 Base System White FC-1462 Grade A | T557: =IFERROR(VLOOKUP(S557,'DESC ITY - ENG'!C:D,2,FALSE),VLOOKUP(J557,'DESC ITY - ENG'!B:D,3,FALSE)) -> INM- | U557: =VLOOKUP(T557,'STANDARD COMM'!A:B,2,FALSE) -> INTR TREAT MATERIAL | V557: =IF(T557="","(blank)",IF(COUNTIF('STANDARD COMM'!A:A,T557)>0,"OK","OUT OF SCOPE")) -> OK
A558: OF0040356 | B558: 45645.685 | D558: F504561 | E558: KOREA FINE CERAMIC CO., LTD | F558: 26AFF000048 | G558: 46081 | I558: 003091001017 | J558: G8 BS GREEN FC-40322 A | K558: prodotti chimici | L558: =VLOOKUP(K558,'COMM ITY- ENG'!A:B,2,FALSE) -> chemical products | N558: 20 | O558: kg | Q558: =+R558/N558 -> 16 | R558: 320 | S558: =IFERROR(VLOOKUP(J558,'DESC ITY - ENG'!B:C,2,FALSE),VLOOKUP(I558,'DESC ITY - ENG'!A:C,3,FALSE)) -> G8 BS Green FC-40322 A | T558: =IFERROR(VLOOKUP(S558,'DESC ITY - ENG'!C:D,2,FALSE),VLOOKUP(J558,'DESC ITY - ENG'!B:D,3,FALSE)) -> INM- | U558: =VLOOKUP(T558,'STANDARD COMM'!A:B,2,FALSE) -> INTR TREAT MATERIAL | V558: =IF(T558="","(blank)",IF(COUNTIF('STANDARD COMM'!A:A,T558)>0,"OK","OUT OF SCOPE")) -> OK
A559: OF0040356 | B559: 45645.685 | D559: F504561 | E559: KOREA FINE CERAMIC CO., LTD | F559: 26AFF000048 | G559: 46081 | I559: 003091001018 | J559: G8 BS FC-41058 A VERDE MET. | K559: prodotti chimici | L559: =VLOOKUP(K559,'COMM ITY- ENG'!A:B,2,FALSE) -> chemical products | N559: 100.02 | O559: kg | Q559: =+R559/N559 -> 16 | R559: 1600.32 | S559: =IFERROR(VLOOKUP(J559,'DESC ITY - ENG'!B:C,2,FALSE),VLOOKUP(I559,'DESC ITY - ENG'!A:C,3,FALSE)) -> G8 BS FC-41058 A GREEN MET. | T559: =IFERROR(VLOOKUP(S559,'DESC ITY - ENG'!C:D,2,FALSE),VLOOKUP(J559,'DESC ITY - ENG'!B:D,3,FALSE)) -> INM- | U559: =VLOOKUP(T559,'STANDARD COMM'!A:B,2,FALSE) -> INTR TREAT MATERIAL | V559: =IF(T559="","(blank)",IF(COUNTIF('STANDARD COMM'!A:A,T559)>0,"OK","OUT OF SCOPE")) -> OK
A560: OF0040356 | B560: 45645.685 | D560: F504561 | E560: KOREA FINE CERAMIC CO., LTD | F560: 26AFF000048 | G560: 46081 | I560: 003190001023 | J560: G8 TC MET.FC-30950M A GRAFITE | K560: prodotti chimici | L560: =VLOOKUP(K560,'COMM ITY- ENG'!A:B,2,FALSE) -> chemical products | N560: 20 | O560: kg | Q560: =+R560/N560 -> 0 | R560: 0 | S560: =IFERROR(VLOOKUP(J560,'DESC ITY - ENG'!B:C,2,FALSE),VLOOKUP(I560,'DESC ITY - ENG'!A:C,3,FALSE)) -> G8 TC Metallic Graphite FC-30950M | T560: =IFERROR(VLOOKUP(S560,'DESC ITY - ENG'!C:D,2,FALSE),VLOOKUP(J560,'DESC ITY - ENG'!B:D,3,FALSE)) -> INM- | U560: =VLOOKUP(T560,'STANDARD COMM'!A:B,2,FALSE) -> INTR TREAT MATERIAL | V560: =IF(T560="","(blank)",IF(COUNTIF('STANDARD COMM'!A:A,T560)>0,"OK","OUT OF SCOPE")) -> OK
A561: OF0040356 | B561: 45645.685 | D561: F504561 | E561: KOREA FINE CERAMIC CO., LTD | F561: 26AFF000048 | G561: 46081 | I561: 003191003016 | J561: G8 TC MET.FC-1710M A VERDE MET. | K561: prodotti chimici | L561: =VLOOKUP(K561,'COMM ITY- ENG'!A:B,2,FALSE) -> chemical products | N561: 100 | O561: kg | Q561: =+R561/N561 -> 16 | R561: 1600 | S561: =IFERROR(VLOOKUP(J561,'DESC ITY - ENG'!B:C,2,FALSE),VLOOKUP(I561,'DESC ITY - ENG'!A:C,3,FALSE)) -> G8 TC MET.FC-1710M A GREEN MET. | T561: =IFERROR(VLOOKUP(S561,'DESC ITY - ENG'!C:D,2,FALSE),VLOOKUP(J561,'DESC ITY - ENG'!B:D,3,FALSE)) -> INM- | U561: =VLOOKUP(T561,'STANDARD COMM'!A:B,2,FALSE) -> INTR TREAT MATERIAL | V561: =IF(T561="","(blank)",IF(COUNTIF('STANDARD COMM'!A:A,T561)>0,"OK","OUT OF SCOPE")) -> OK
A562: OF0040656 | B562: 45666.46 | D562: F015558 | E562: Q.S.ABRASIVI MARENGO SRL | F562: 26AFI000454 | G562: 46081 | I562: 009430002001 | J562: CORINDONE GRANA 50 | K562: materiali di consumo | L562: =VLOOKUP(K562,'COMM ITY- ENG'!A:B,2,FALSE) -> consumable materials | N562: 8000 | O562: kg | Q562: =+R562/N562 -> 0.95 | R562: 7600 | S562: =IFERROR(VLOOKUP(J562,'DESC ITY - ENG'!B:C,2,FALSE),VLOOKUP(I562,'DESC ITY - ENG'!A:C,3,FALSE)) -> Corundum Abrasive 50 GritCorundum Abrasive | T562: =IFERROR(VLOOKUP(S562,'DESC ITY - ENG'!C:D,2,FALSE),VLOOKUP(J562,'DESC ITY - ENG'!B:D,3,FALSE)) -> POLM | U562: =VLOOKUP(T562,'STANDARD COMM'!A:B,2,FALSE) -> POLISH MATERIAL | V562: =IF(T562="","(blank)",IF(COUNTIF('STANDARD COMM'!A:A,T562)>0,"OK","OUT OF SCOPE")) -> OK
A563: OF0040035 | B563: 45666.5 | D563: F600467 | E563: IMF INDUSTRIE MARCHIGIANE FILTRI SRL | F563: 26AFI000496 | G563: 46081 | I563: 0002A0127TS4 | J563: DISCO AC.127/040 C/F 3MM+TAGLI STRETTI+FORO CENTRALE 38mm | K563: acciaio | L563: =VLOOKUP(K563,'COMM ITY- ENG'!A:B,2,FALSE) -> steel | N563: 9700 | O563: NR | Q563: =+R563/N563 -> 0.1449 | R563: 1405.53 | S563: =IFERROR(VLOOKUP(J563,'DESC ITY - ENG'!B:C,2,FALSE),VLOOKUP(I563,'DESC ITY - ENG'!A:C,3,FALSE)) -> Steel Disc AC.127/040 3.0mm Narrow Slots + 38mm Center Hole [cite: 1] | T563: =IFERROR(VLOOKUP(S563,'DESC ITY - ENG'!C:D,2,FALSE),VLOOKUP(J563,'DESC ITY - ENG'!B:D,3,FALSE)) -> SM-- | U563: =VLOOKUP(T563,'STANDARD COMM'!A:B,2,FALSE) -> STEEL MATERIAL | V563: =IF(T563="","(blank)",IF(COUNTIF('STANDARD COMM'!A:A,T563)>0,"OK","OUT OF SCOPE")) -> OK
A564: OF0039954 | B564: 45666.5 | D564: F014515 | E564: SANMIRO SRL | F564: 26AFI000495 | G564: 46081 | I564: 000251627001 | J564: MANIGLIA VANITY NERO SATINATO | K564: manigliame | L564: =VLOOKUP(K564,'COMM ITY- ENG'!A:B,2,FALSE) -> handles | N564: 6300 | O564: NR | Q564: =+R564/N564 -> 0.2249 | R564: 1416.87 | S564: =IFERROR(VLOOKUP(J564,'DESC ITY - ENG'!B:C,2,FALSE),VLOOKUP(I564,'DESC ITY - ENG'!A:C,3,FALSE)) -> Side Handle Vanity Black Satin Finish [cite: 5] | T564: =IFERROR(VLOOKUP(S564,'DESC ITY - ENG'!C:D,2,FALSE),VLOOKUP(J564,'DESC ITY - ENG'!B:D,3,FALSE)) -> SHDL- | U564: =VLOOKUP(T564,'STANDARD COMM'!A:B,2,FALSE) -> #N/A | V564: =IF(T564="","(blank)",IF(COUNTIF('STANDARD COMM'!A:A,T564)>0,"OK","OUT OF SCOPE")) -> OUT OF SCOPE
A565: OF0040153 | B565: 45666.5 | D565: F014515 | E565: SANMIRO SRL | F565: 26AFI000495 | G565: 46081 | I565: 000251627001 | J565: MANIGLIA VANITY NERO SATINATO | K565: manigliame | L565: =VLOOKUP(K565,'COMM ITY- ENG'!A:B,2,FALSE) -> handles | N565: 15120 | O565: NR | Q565: =+R565/N565 -> 0.22490013 | R565: 3400.49 | S565: =IFERROR(VLOOKUP(J565,'DESC ITY - ENG'!B:C,2,FALSE),VLOOKUP(I565,'DESC ITY - ENG'!A:C,3,FALSE)) -> Side Handle Vanity Black Satin Finish [cite: 5] | T565: =IFERROR(VLOOKUP(S565,'DESC ITY - ENG'!C:D,2,FALSE),VLOOKUP(J565,'DESC ITY - ENG'!B:D,3,FALSE)) -> SHDL- | U565: =VLOOKUP(T565,'STANDARD COMM'!A:B,2,FALSE) -> #N/A | V565: =IF(T565="","(blank)",IF(COUNTIF('STANDARD COMM'!A:A,T565)>0,"OK","OUT OF SCOPE")) -> OUT OF SCOPE
A566: OF0040548 | B566: 45666.598 | D566: F013851 | E566: LINK GRUPPO SPA | F566: 26AFI000444 | G566: 46081 | I566: 009430060001 | J566: 770 PRIMER LOCT0016777 GR.10 | K566: materiali di consumo | L566: =VLOOKUP(K566,'COMM ITY- ENG'!A:B,2,FALSE) -> consumable materials | N566: 5 | O566: NR | Q566: =+R566/N566 -> 26.61 | R566: 133.05 | S566: =IFERROR(VLOOKUP(J566,'DESC ITY - ENG'!B:C,2,FALSE),VLOOKUP(I566,'DESC ITY - ENG'!A:C,3,FALSE)) -> 770 PRIMER LOCT0016777 GR.10 | T566: =IFERROR(VLOOKUP(S566,'DESC ITY - ENG'!C:D,2,FALSE),VLOOKUP(J566,'DESC ITY - ENG'!B:D,3,FALSE)) -> INM- | U566: =VLOOKUP(T566,'STANDARD COMM'!A:B,2,FALSE) -> INTR TREAT MATERIAL | V566: =IF(T566="","(blank)",IF(COUNTIF('STANDARD COMM'!A:A,T566)>0,"OK","OUT OF SCOPE")) -> OK
... A568: OF0038649 | B568: 45666.598 | D568: F600958 | E568: EDENTECH CO.LTD. | F568: 26AFF000040 | G568: 46081 | I568: 000030470023 | J568: DISCO 5PLY 470/23 SS304 0,4 + Al1,4 + SS439 0,5 TOT 23/10 | K568: Acciaio multistrato (5PLY) | L568: =VLOOKUP(K568,'COMM ITY- ENG'!A:B,2,FALSE) -> multilayer steel (5PLY) | N568: 1760 | O568: NR | Q568: =+R568/N568 -> 10.04 | R568: 17670.4 | S568: =IFERROR(VLOOKUP(J568,'DESC ITY - ENG'!B:C,2,FALSE),VLOOKUP(I568,'DESC ITY - ENG'!A:C,3,FALSE)) -> 5-Ply Disc SS304/AL/SS439 470mm x 2.3mm Total Thickness 2.3mm [cite: 1] | T568: =IFERROR(VLOOKUP(S568,'DESC ITY - ENG'!C:D,2,FALSE),VLOOKUP(J568,'DESC ITY - ENG'!B:D,3,FALSE)) -> CDM- | U568: =VLOOKUP(T568,'STANDARD COMM'!A:B,2,FALSE) -> CLAD MATERIAL | V568: =IF(T568="","(blank)",IF(COUNTIF('STANDARD COMM'!A:A,T568)>0,"OK","OUT OF SCOPE")) -> OK
B569: 45666.665 | D569: F600780 | E569: GULBAK BAKALIT METAL VE TEKSTIL SAN. ve TIC. LTD. STI | F569: 26AFF000056 | G569: 46081 | I569: 000281710005 | J569: MANICO AC.SOLE LUNGO C/LOGO MC AISI 430 SABBIATO PAD.279 30 | K569: manigliame | L569: =VLOOKUP(K569,'COMM ITY- ENG'!A:B,2,FALSE) -> handles | N569: 15000 | O569: NR | Q569: =+R569/N569 -> 1.227 | R569: 18405 | S569: =IFERROR(VLOOKUP(J569,'DESC ITY - ENG'!B:C,2,FALSE),VLOOKUP(I569,'DESC ITY - ENG'!A:C,3,FALSE)) -> Steel Handle AC.SOLE Long w/Logo MC AISI 430 Pan 279-30 Sandblasted [cite: 4] | T569: =IFERROR(VLOOKUP(S569,'DESC ITY - ENG'!C:D,2,FALSE),VLOOKUP(J569,'DESC ITY - ENG'!B:D,3,FALSE)) -> HDL-- | U569: =VLOOKUP(T569,'STANDARD COMM'!A:B,2,FALSE) -> #N/A | V569: =IF(T569="","(blank)",IF(COUNTIF('STANDARD COMM'!A:A,T569)>0,"OK","OUT OF SCOPE")) -> OUT OF SCOPE
A570: OF0040184 | B570: 45666.665 | D570: F600850 | E570: TEKNIKEL MAKINA KALIP IMALAT SAN. VE TIC. LTD STI. | F570: 26AFF000057 | G570: 46081 | I570: 000250027001 | J570: MANICO L890/1 ODINO NERO SAT. | K570: manigliame | L570: =VLOOKUP(K570,'COMM ITY- ENG'!A:B,2,FALSE) -> handles | N570: 12100 | O570: NR | Q570: =+R570/N570 -> 0.31 | R570: 3751 | S570: =IFERROR(VLOOKUP(J570,'DESC ITY - ENG'!B:C,2,FALSE),VLOOKUP(I570,'DESC ITY - ENG'!A:C,3,FALSE)) -> Handle 1890/1 Odino Black Satin Finish [cite: 5] | T570: =IFERROR(VLOOKUP(S570,'DESC ITY - ENG'!C:D,2,FALSE),VLOOKUP(J570,'DESC ITY - ENG'!B:D,3,FALSE)) -> HDL-- | U570: =VLOOKUP(T570,'STANDARD COMM'!A:B,2,FALSE) -> #N/A | V570: =IF(T570="","(blank)",IF(COUNTIF('STANDARD COMM'!A:A,T570)>0,"OK","OUT OF SCOPE")) -> OUT OF SCOPE
A571: OF0040247 | B571: 45667.611 | D571: F600456 | E571: ALMESAN ALUMINYUM SAN.VE TIC. A.S | F571: 26AFF000055 | G571: 46081 | I571: 000040285036R | J571: DISCO AL.4006 285/36 RIC | K571: alluminio | L571: =VLOOKUP(K571,'COMM ITY- ENG'!A:B,2,FALSE) -> aluminium | N571: 4550 | O571: kg | Q571: =+R571/N571 -> 3.732 | R571: 16980.6 | S571: =IFERROR(VLOOKUP(J571,'DESC ITY - ENG'!B:C,2,FALSE),VLOOKUP(I571,'DESC ITY - ENG'!A:C,3,FALSE)) -> Aluminum Disc Alloy 4006 285mm x 3.6mm Replacement Part [cite: 2] | T571: =IFERROR(VLOOKUP(S571,'DESC ITY - ENG'!C:D,2,FALSE),VLOOKUP(J571,'DESC ITY - ENG'!B:D,3,FALSE)) -> ALM- | U571: =VLOOKUP(T571,'STANDARD COMM'!A:B,2,FALSE) -> ALUM MATERIAL | V571: =IF(T571="","(blank)",IF(COUNTIF('STANDARD COMM'!A:A,T571)>0,"OK","OUT OF SCOPE")) -> OK
A572: OF0040247 | B572: 45667.611 | D572: F600456 | E572: ALMESAN ALUMINYUM SAN.VE TIC. A.S | F572: 26AFF000055 | G572: 46081 | I572: 000040325036R | J572: DISCO AL.4006 325/36 RIC | K572: alluminio | L572: =VLOOKUP(K572,'COMM ITY- ENG'!A:B,2,FALSE) -> aluminium | N572: 7978 | O572: kg | Q572: =+R572/N572 -> 3.7320005 | R572: 29773.9 | S572: =IFERROR(VLOOKUP(J572,'DESC ITY - ENG'!B:C,2,FALSE),VLOOKUP(I572,'DESC ITY - ENG'!A:C,3,FALSE)) -> Aluminum Disc Alloy 4006 325mm x 3.6mm Replacement Part [cite: 2] | T572: =IFERROR(VLOOKUP(S572,'DESC ITY - ENG'!C:D,2,FALSE),VLOOKUP(J572,'DESC ITY - ENG'!B:D,3,FALSE)) -> ALM- | U572: =VLOOKUP(T572,'STANDARD COMM'!A:B,2,FALSE) -> ALUM MATERIAL | V572: =IF(T572="","(blank)",IF(COUNTIF('STANDARD COMM'!A:A,T572)>0,"OK","OUT OF SCOPE")) -> OK
A573: OF0039875 | B573: 45667.611 | D573: F600780 | E573: GULBAK BAKALIT METAL VE TEKSTIL SAN. ve TIC. LTD. STI | F573: 26AFF000056 | G573: 46081 | I573: 000281710003 | J573: MANICO AC.SOLE CORTO C/LOGO MC AISI 430 SABBIATO CAS.433 16 | K573: manigliame | L573: =VLOOKUP(K573,'COMM ITY- ENG'!A:B,2,FALSE) -> handles | N573: 10000 | O573: NR | Q573: =+R573/N573 -> 1.137 | R573: 11370 | S573: =IFERROR(VLOOKUP(J573,'DESC ITY - ENG'!B:C,2,FALSE),VLOOKUP(I573,'DESC ITY - ENG'!A:C,3,FALSE)) -> Steel Handle AC.SOLE Short w/Logo MC AISI 430 Casserole 433-16 Sandblasted [cite: 4] | T573: =IFERROR(VLOOKUP(S573,'DESC ITY - ENG'!C:D,2,FALSE),VLOOKUP(J573,'DESC ITY - ENG'!B:D,3,FALSE)) -> SHDL- | U573: =VLOOKUP(T573,'STANDARD COMM'!A:B,2,FALSE) -> #N/A | V573: =IF(T573="","(blank)",IF(COUNTIF('STANDARD COMM'!A:A,T573)>0,"OK","OUT OF SCOPE")) -> OUT OF SCOPE
A574: OF0040035 | B574: 45667.611 | D574: F600467 | E574: IMF INDUSTRIE MARCHIGIANE FILTRI SRL | F574: 26AFI000496 | G574: 46081 | I574: 0002A0157TS4 | J574: DISCO AC.157/040 C/F 3MM+TAGLI STRETTI+FORO CENTRALE 51mm | K574: acciaio | L574: =VLOOKUP(K574,'COMM ITY- ENG'!A:B,2,FALSE) -> steel | N574: 8750 | O574: NR | Q574: =+R574/N574 -> 0.214 | R574: 1872.5 | S574: =IFERROR(VLOOKUP(J574,'DESC ITY - ENG'!B:C,2,FALSE),VLOOKUP(I574,'DESC ITY - ENG'!A:C,3,FALSE)) -> Steel Disc AC.157/040 3.0mm Narrow Slots + 51mm Center Hole [cite: 1] | T574: =IFERROR(VLOOKUP(S574,'DESC ITY - ENG'!C:D,2,FALSE),VLOOKUP(J574,'DESC ITY - ENG'!B:D,3,FALSE)) -> SM-- | U574: =VLOOKUP(T574,'STANDARD COMM'!A:B,2,FALSE) -> STEEL MATERIAL | V574: =IF(T574="","(blank)",IF(COUNTIF('STANDARD COMM'!A:A,T574)>0,"OK","OUT OF SCOPE")) -> OK
A575: OF0040185 | B575: 45667.611 | D575: F600467 | E575: IMF INDUSTRIE MARCHIGIANE FILTRI SRL | F575: 26AFI000496 | G575: 46081 | I575: 0002A0157TS4 | J575: DISCO AC.157/040 C/F 3MM+TAGLI STRETTI+FORO CENTRALE 51mm | K575: acciaio | L575: =VLOOKUP(K575,'COMM ITY- ENG'!A:B,2,FALSE) -> steel | N575: 14080 | O575: NR | Q575: =+R575/N575 -> 0.214 | R575: 3013.12 | S575: =IFERROR(VLOOKUP(J575,'DESC ITY - ENG'!B:C,2,FALSE),VLOOKUP(I575,'DESC ITY - ENG'!A:C,3,FALSE)) -> Steel Disc AC.157/040 3.0mm Narrow Slots + 51mm Center Hole [cite: 1] | T575: =IFERROR(VLOOKUP(S575,'DESC ITY - ENG'!C:D,2,FALSE),VLOOKUP(J575,'DESC ITY - ENG'!B:D,3,FALSE)) -> SM-- | U575: =VLOOKUP(T575,'STANDARD COMM'!A:B,2,FALSE) -> STEEL MATERIAL | V575: =IF(T575="","(blank)",IF(COUNTIF('STANDARD COMM'!A:A,T575)>0,"OK","OUT OF SCOPE")) -> OK
A576: OF0040035 | B576: 45667.611 | D576: F600467 | E576: IMF INDUSTRIE MARCHIGIANE FILTRI SRL | F576: 26AFI000496 | G576: 46081 | I576: 0002A0187TS4 | J576: DISCO AC.187/040 C/F 3MM+TAGLI STRETTI+FORO CENTRALE 51mm | K576: acciaio | L576: =VLOOKUP(K576,'COMM ITY- ENG'!A:B,2,FALSE) -> steel | N576: 15000 | O576: NR | Q576: =+R576/N576 -> 0.2784 | R576: 4176 | S576: =IFERROR(VLOOKUP(J576,'DESC ITY - ENG'!B:C,2,FALSE),VLOOKUP(I576,'DESC ITY - ENG'!A:C,3,FALSE)) -> Steel Disc AC.187/040 3.0mm Narrow Slots + 51mm Center Hole [cite: 1] | T576: =IFERROR(VLOOKUP(S576,'DESC ITY - ENG'!C:D,2,FALSE),VLOOKUP(J576,'DESC ITY - ENG'!B:D,3,FALSE)) -> SM-- | U576: =VLOOKUP(T576,'STANDARD COMM'!A:B,2,FALSE) -> STEEL MATERIAL | V576: =IF(T576="","(blank)",IF(COUNTIF('STANDARD COMM'!A:A,T576)>0,"OK","OUT OF SCOPE")) -> OK
A577: OF0040185 | B577: 45667.611 | D577: F600467 | E577: IMF INDUSTRIE MARCHIGIANE FILTRI SRL | F577: 26AFI000496 | G577: 46081 | I577: 0002A0187TS4 | J577: DISCO AC.187/040 C/F 3MM+TAGLI STRETTI+FORO CENTRALE 51mm | K577: acciaio | L577: =VLOOKUP(K577,'COMM ITY- ENG'!A:B,2,FALSE) -> steel | N577: 8278 | O577: NR | Q577: =+R577/N577 -> 0.27840058 | R577: 2304.6 | S577: =IFERROR(VLOOKUP(J577,'DESC ITY - ENG'!B:C,2,FALSE),VLOOKUP(I577,'DESC ITY - ENG'!A:C,3,FALSE)) -> Steel Disc AC.187/040 3.0mm Narrow Slots + 51mm Center Hole [cite: 1] | T577: =IFERROR(VLOOKUP(S577,'DESC ITY - ENG'!C:D,2,FALSE),VLOOKUP(J577,'DESC ITY - ENG'!B:D,3,FALSE)) -> SM-- | U577: =VLOOKUP(T577,'STANDARD COMM'!A:B,2,FALSE) -> STEEL MATERIAL | V577: =IF(T577="","(blank)",IF(COUNTIF('STANDARD COMM'!A:A,T577)>0,"OK","OUT OF SCOPE")) -> OK
A578: OF0040338 | B578: 45667.643 | D578: F013851 | E578: LINK GRUPPO SPA | F578: 26AFI000444 | G578: 46081 | I578: 009430059001 | J578: 406 ADESIVO LOCT0040630 GR.20 | K578: materiali di consumo | L578: =VLOOKUP(K578,'COMM ITY- ENG'!A:B,2,FALSE) -> consumable materials | N578: 3 | O578: NR | Q578: =+R578/N578 -> 18.936667 | R578: 56.81 | S578: =IFERROR(VLOOKUP(J578,'DESC ITY - ENG'!B:C,2,FALSE),VLOOKUP(I578,'DESC ITY - ENG'!A:C,3,FALSE)) -> Adhesive Loctite 406 28cm SS304 Rim with Steam Vent Type AGlass Lid | T578: =IFERROR(VLOOKUP(S578,'DESC ITY - ENG'!C:D,2,FALSE),VLOOKUP(J578,'DESC ITY - ENG'!B:D,3,FALSE)) -> MISC | U578: =VLOOKUP(T578,'STANDARD COMM'!A:B,2,FALSE) -> MISCELLANEOUS | V578: =IF(T578="","(blank)",IF(COUNTIF('STANDARD COMM'!A:A,T578)>0,"OK","OUT OF SCOPE")) -> OK
A579: OF0039471 | B579: 45667.693 | D579: F600985 | E579: EL.MA SNC | F579: 26AFI000487 | G579: 46081 | I579: 001717802001 | J579: BOX FLEXO 7802+KIT DIV.MADE IN 30 CM SKILLET SCMI 30050 | K579: cartoni e casse | L579: =VLOOKUP(K579,'COMM ITY- ENG'!A:B,2,FALSE) -> cartons and boxes | N579: 6610 | O579: NR | Q579: =+R579/N579 -> 1.135 | R579: 7502.35 | S579: =IFERROR(VLOOKUP(J579,'DESC ITY - ENG'!B:C,2,FALSE),VLOOKUP(I579,'DESC ITY - ENG'!A:C,3,FALSE)) -> Flexo Box 7802 + Divider Kit for 30cm Skillet SCMI 30050 | T579: =IFERROR(VLOOKUP(S579,'DESC ITY - ENG'!C:D,2,FALSE),VLOOKUP(J579,'DESC ITY - ENG'!B:D,3,FALSE)) -> BOX- | U579: =VLOOKUP(T579,'STANDARD COMM'!A:B,2,FALSE) -> BOX / CARTON | V579: =IF(T579="","(blank)",IF(COUNTIF('STANDARD COMM'!A:A,T579)>0,"OK","OUT OF SCOPE")) -> OK
A580: OF0039114 | B580: 45667.693 | D580: F506075 | E580: HEBEI BOZHENG GLASSWORK CO.LTD. | F580: 26AFF000036 | G580: 46081 | I580: 000700044002 | J580: COP.VET.24 PIAT.BOR./SF.VAP.SIL.STD | K580: accessori finiti | L580: =VLOOKUP(K580,'COMM ITY- ENG'!A:B,2,FALSE) -> finished accessories | N580: 3000 | O580: NR | Q580: =+R580/N580 -> 1.0316033 | R580: 3094.81 | S580: =IFERROR(VLOOKUP(J580,'DESC ITY - ENG'!B:C,2,FALSE),VLOOKUP(I580,'DESC ITY - ENG'!A:C,3,FALSE)) -> Glass Lid 24cm Flat Rim Silicone Steam Vent StandardGlass Lid | T580: =IFERROR(VLOOKUP(S580,'DESC ITY - ENG'!C:D,2,FALSE),VLOOKUP(J580,'DESC ITY - ENG'!B:D,3,FALSE)) -> LID- | U580: =VLOOKUP(T580,'STANDARD COMM'!A:B,2,FALSE) -> LID | V580: =IF(T580="","(blank)",IF(COUNTIF('STANDARD COMM'!A:A,T580)>0,"OK","OUT OF SCOPE")) -> OK
A581: OF0039114 | B581: 45667.693 | D581: F506075 | E581: HEBEI BOZHENG GLASSWORK CO.LTD. | F581: 26AFF000036 | G581: 46081 | I581: 000700046002 | J581: COP.VET.28 PIAT.BOR./SF.VAP.SIL.STD | K581: accessori finiti | L581: =VLOOKUP(K581,'COMM ITY- ENG'!A:B,2,FALSE) -> finished accessories | N581: 3000 | O581: NR | Q581: =+R581/N581 -> 1.1772733 | R581: 3531.82 | S581: =IFERROR(VLOOKUP(J581,'DESC ITY - ENG'!B:C,2,FALSE),VLOOKUP(I581,'DESC ITY - ENG'!A:C,3,FALSE)) -> Glass Lid 28cm Flat Rim Silicone Steam Vent StandardGlass Lid | T581: =IFERROR(VLOOKUP(S581,'DESC ITY - ENG'!C:D,2,FALSE),VLOOKUP(J581,'DESC ITY - ENG'!B:D,3,FALSE)) -> LID- | U581: =VLOOKUP(T581,'STANDARD COMM'!A:B,2,FALSE) -> LID | V581: =IF(T581="","(blank)",IF(COUNTIF('STANDARD COMM'!A:A,T581)>0,"OK","OUT OF SCOPE")) -> OK
... A594: OF0039833 | B594: 45680.639 | D594: F600389 | E594: VIBRANTZ ITALY SRL | F594: 26AFI000491 | G594: 46081 | I594: 002490304002 | J594: OSSIDO VERDE FK 8497 (EX FA 6290) | K594: prodotti chimici | L594: =VLOOKUP(K594,'COMM ITY- ENG'!A:B,2,FALSE) -> chemical products | N594: 50 | O594: kg | Q594: =+R594/N594 -> 48.9458 | R594: 2447.29 | S594: =IFERROR(VLOOKUP(J594,'DESC ITY - ENG'!B:C,2,FALSE),VLOOKUP(I594,'DESC ITY - ENG'!A:C,3,FALSE)) -> Green Oxide FK 8497 (formerly FA 6290) | T594: =IFERROR(VLOOKUP(S594,'DESC ITY - ENG'!C:D,2,FALSE),VLOOKUP(J594,'DESC ITY - ENG'!B:D,3,FALSE)) -> INM- | U594: =VLOOKUP(T594,'STANDARD COMM'!A:B,2,FALSE) -> INTR TREAT MATERIAL | V594: =IF(T594="","(blank)",IF(COUNTIF('STANDARD COMM'!A:A,T594)>0,"OK","OUT OF SCOPE")) -> OK
B595: 45680.639 | D595: F013344 | E595: VITINOX SAS DI GUGLIELMELLI R.& C. | F595: 26AFI000488 | G595: 46081 | I595: 000450626001 | J595: RIBATTINO AC.6X12 MADE IN | K595: accessori x manigl. | L595: =VLOOKUP(K595,'COMM ITY- ENG'!A:B,2,FALSE) -> accessories for handles | N595: 3000 | O595: NR | Q595: =+R595/N595 -> 0.0646 | R595: 193.8 | S595: =IFERROR(VLOOKUP(J595,'DESC ITY - ENG'!B:C,2,FALSE),VLOOKUP(I595,'DESC ITY - ENG'!A:C,3,FALSE)) -> Steel Rivet 6x12 mm | T595: =IFERROR(VLOOKUP(S595,'DESC ITY - ENG'!C:D,2,FALSE),VLOOKUP(J595,'DESC ITY - ENG'!B:D,3,FALSE)) -> RIV- | U595: =VLOOKUP(T595,'STANDARD COMM'!A:B,2,FALSE) -> RIVET | V595: =IF(T595="","(blank)",IF(COUNTIF('STANDARD COMM'!A:A,T595)>0,"OK","OUT OF SCOPE")) -> OK
A596: OF0039933 | B596: 45688.572 | D596: F600985 | E596: EL.MA SNC | F596: 26AFI000487 | G596: 46081 | I596: 001717802001 | J596: BOX FLEXO 7802+KIT DIV.MADE IN 30 CM SKILLET SCMI 30050 | K596: cartoni e casse | L596: =VLOOKUP(K596,'COMM ITY- ENG'!A:B,2,FALSE) -> cartons and boxes | N596: 2200 | O596: NR | Q596: =+R596/N596 -> 1.135 | R596: 2497 | S596: =IFERROR(VLOOKUP(J596,'DESC ITY - ENG'!B:C,2,FALSE),VLOOKUP(I596,'DESC ITY - ENG'!A:C,3,FALSE)) -> Flexo Box 7802 + Divider Kit for 30cm Skillet SCMI 30050 | T596: =IFERROR(VLOOKUP(S596,'DESC ITY - ENG'!C:D,2,FALSE),VLOOKUP(J596,'DESC ITY - ENG'!B:D,3,FALSE)) -> BOX- | U596: =VLOOKUP(T596,'STANDARD COMM'!A:B,2,FALSE) -> BOX / CARTON | V596: =IF(T596="","(blank)",IF(COUNTIF('STANDARD COMM'!A:A,T596)>0,"OK","OUT OF SCOPE")) -> OK
A597: OF0039933 | B597: 45688.611 | D597: F600985 | E597: EL.MA SNC | F597: 26AFI000487 | G597: 46081 | I597: 001717805001 | J597: BOX FLEXO 7805 COP. MADE IN 7 PCS SET SCMI 7PCSCOPERCHIO | K597: cartoni e casse | L597: =VLOOKUP(K597,'COMM ITY- ENG'!A:B,2,FALSE) -> cartons and boxes | N597: 1067 | O597: NR | Q597: =+R597/N597 -> 1.0150047 | R597: 1083.01 | S597: =IFERROR(VLOOKUP(J597,'DESC ITY - ENG'!B:C,2,FALSE),VLOOKUP(I597,'DESC ITY - ENG'!A:C,3,FALSE)) -> Flexo Box 7805 Lid, Made In, 7 Pcs Set | T597: =IFERROR(VLOOKUP(S597,'DESC ITY - ENG'!C:D,2,FALSE),VLOOKUP(J597,'DESC ITY - ENG'!B:D,3,FALSE)) -> BOX- | U597: =VLOOKUP(T597,'STANDARD COMM'!A:B,2,FALSE) -> BOX / CARTON | V597: =IF(T597="","(blank)",IF(COUNTIF('STANDARD COMM'!A:A,T597)>0,"OK","OUT OF SCOPE")) -> OK
A598: OF0039933 | B598: 45688.632 | D598: F600985 | E598: EL.MA SNC | F598: 26AFI000487 | G598: 46081 | I598: 001717804001 | J598: BOX FLEXO 7804 FONDO MADE IN 7 PCS SET SCMI7PCSFONDO | K598: cartoni e casse | L598: =VLOOKUP(K598,'COMM ITY- ENG'!A:B,2,FALSE) -> cartons and boxes | N598: 1035 | O598: NR | Q598: =+R598/N598 -> 1.2950048 | R598: 1340.33 | S598: =IFERROR(VLOOKUP(J598,'DESC ITY - ENG'!B:C,2,FALSE),VLOOKUP(I598,'DESC ITY - ENG'!A:C,3,FALSE)) -> BOX FLEXO 7804 BOTTOM MADE IN 7 PCS SET SCMI7PCSFONDO | T598: =IFERROR(VLOOKUP(S598,'DESC ITY - ENG'!C:D,2,FALSE),VLOOKUP(J598,'DESC ITY - ENG'!B:D,3,FALSE)) -> BOX- | U598: =VLOOKUP(T598,'STANDARD COMM'!A:B,2,FALSE) -> BOX / CARTON | V598: =IF(T598="","(blank)",IF(COUNTIF('STANDARD COMM'!A:A,T598)>0,"OK","OUT OF SCOPE")) -> OK
A599: OF0039933 | B599: 45688.677 | D599: F600985 | E599: EL.MA SNC | F599: 26AFI000487 | G599: 46081 | I599: 001717800001 | J599: BOX FLEXO 7800+KIT DIV.MADE IN 26 CM SAUTE SCMI 26066 | K599: cartoni e casse | L599: =VLOOKUP(K599,'COMM ITY- ENG'!A:B,2,FALSE) -> cartons and boxes | N599: 1800 | O599: NR | Q599: =+R599/N599 -> 1.345 | R599: 2421 | S599: =IFERROR(VLOOKUP(J599,'DESC ITY - ENG'!B:C,2,FALSE),VLOOKUP(I599,'DESC ITY - ENG'!A:C,3,FALSE)) -> Flexo Box 7800 + Divider Kit, Made In 26cm | T599: =IFERROR(VLOOKUP(S599,'DESC ITY - ENG'!C:D,2,FALSE),VLOOKUP(J599,'DESC ITY - ENG'!B:D,3,FALSE)) -> BOX- | U599: =VLOOKUP(T599,'STANDARD COMM'!A:B,2,FALSE) -> BOX / CARTON | V599: =IF(T599="","(blank)",IF(COUNTIF('STANDARD COMM'!A:A,T599)>0,"OK","OUT OF SCOPE")) -> OK
...

Sheet STANDARD COMM
A1: Commodity Code | B1: Commodity Description | C1: Commodity Group (MIL)
A2: ALM- | B2: ALUM MATERIAL | C2: Metal | D2: =_xlfn.TRANSLATE(C2,"en","zh-cht") -> 金屬
A3: BAG- | B3: BAG PACK | C3: Plastic | D3: =_xlfn.TRANSLATE(C3,"en","zh-cht") -> 塑膠
A4: BAKT | B4: BASKET | C4: Kitchen Tools | D4: =_xlfn.TRANSLATE(C4,"en","zh-cht") -> 廚房工具
A5: BFIT | B5: ELE BULK FITG | C5: Electric Material | D5: =_xlfn.TRANSLATE(C5,"en","zh-cht") -> 電材料
A6: BHRE | B6: BROCHURE / LEAFLET / RECIPE | C6: Paper Material | D6: =_xlfn.TRANSLATE(C6,"en","zh-cht") -> 紙張材料
A7: BOX- | B7: BOX / CARTON | C7: Paper Material | D7: =_xlfn.TRANSLATE(C7,"en","zh-cht") -> 紙張材料
A8: BRKT | B8: BRACKET | C8: Fastener | D8: =_xlfn.TRANSLATE(C8,"en","zh-cht") -> 緊固件
A9: CAPS | B9: END CAP SS | C9: Fastener | D9: =_xlfn.TRANSLATE(C9,"en","zh-cht") -> 緊固件
A10: CBS- | B10: CARD BOARD INSERT | C10: Paper Material | D10: =_xlfn.TRANSLATE(C10,"en","zh-cht") -> 紙張材料
A11: CDM- | B11: CLAD MATERIAL | C11: Metal | D11: =_xlfn.TRANSLATE(C11,"en","zh-cht") -> 金屬
A12: CORD | B12: POWER CORD | C12: Electric Material | D12: =_xlfn.TRANSLATE(C12,"en","zh-cht") -> 電材料
A13: CUM- | B13: COPPER MATERIAL | C13: Metal | D13: =_xlfn.TRANSLATE(C13,"en","zh-cht") -> 金屬
... A79: WIRE | B79: LEAD WIRE | C79: Electric Material | D79: =_xlfn.TRANSLATE(C79,"en","zh-cht") -> 電材料
A80: Showing 1 to 78 of 78 entries
A81: Previous
A82: 1
A83: Next
A84: Copyright © 2026 Meyer Manufacturing Company Ltd. All rights reserved.

Sheet COMM ITY- ENG
A2: Italian | B2: English
A3: accessori di confez. | B3: packaging accessories
A4: accessori finiti | B4: finished accessories
A5: accessori x manigl. | B5: accessories for handles
A6: acciaio | B6: steel
A7: Acciaio multistrato (5PLY) | B7: multilayer steel (5PLY)
A8: alluminio | B8: aluminium
A9: cartoni e casse | B9: cartons and boxes
A10: manigliame | B10: handles
A11: mater. di confezion. | B11: packaging material
A12: mater.aus.varie acq. | B12: various auxiliary materials purchased
A13: materiali di consumo | B13: consumable materials
... A16: semilavorato | B16: semi-finished product

Sheet DESC ITY - ENG
A1: Jan - Feb 26 | B1: Part Description | C1: Translated Part Description (English) | D1: Commodity
A2: 000288100051 | B2: 1-5-HSI103C-Y SI HANDLE 16CM SAUCEPAN... | C2: 1-5 SI Handle 16cm Saucepan (6.5mm hole) | D2: HDL--
A3: 000288100051 | B3: 1-5-HSI103C-Y SI HANDLE 16CM SAUCEPAN... | C3: 1-5 SI Handle 16cm Saucepan (6.5mm hole) | D3: HDL--
A4: 000288100052 | B4: 1-5-HSI105C-Y SI HANDLE 20CM SAUCEPAN... | C4: 1-5 SI Handle 20cm Saucepan (6.5mm hole) | D4: HDL--
A5: 000288100052 | B5: 1-5-HSI105C-Y SI HANDLE 20CM SAUCEPAN... | C5: 1-5 SI Handle 20cm Saucepan (6.5mm hole) | D5: HDL--
A6: 000288100055 | B6: 1-5-HSI203C-Y SI HANDLE 20CM SKILLET... | C6: 1-5 SI Handle 20cm Skillet (6.5mm hole) | D6: HDL--
A7: 000288100055 | B7: 1-5-HSI203C-Y SI HANDLE 20CM SKILLET... | C7: 1-5 SI Handle 20cm Skillet (6.5mm hole) | D7: HDL--
A8: 000288100053 | B8: 1-5-HSI107C-Y SI HANDLE 24CM SAUCIER... | C8: 1-5 SI Handle 24cm Saucier (6.5mm hole) | D8: HDL--
A9: 000288100053 | B9: 1-5-HSI107C-Y SI HANDLE 24CM SAUCIER... | C9: 1-5 SI Handle 24cm Saucier (6.5mm hole) | D9: HDL--
A10: 000288100054 | B10: 1-5-HSI108C-Y SI HANDLE 26CM SAUTE'... | C10: 1-5 SI Handle 26cm Saute (6.5mm hole) | D10: HDL--
A11: 000288100054 | B11: 1-5-HSI108C-Y SI HANDLE 26CM SAUTE'... | C11: 1-5 SI Handle 26cm Saute (6.5mm hole) | D11: HDL--
A12: 000288100056 | B12: 1-5-HSI206C-Y SI HANDLE 26CM SKILLET... | C12: 1-5 SI Handle 26cm Skillet (6.5mm hole) | D12: HDL--
... A819: 000730414004 | B819: COPERCHIO SS WOK 32 CM OQC3210AS-001 | C819: Stainless Steel Wok Lid 32cm OQC3210AS-001 | D819: LID-
A820: 1760000324 | B820: FASCIA LIT.MONTAGNE BASIC 279 24 8721381150369 | C820: Litho Sleeve Montagne Basic 279 24 | D820: SHTS
A821: 001760000326 | B821: FASCIA LIT.MONTAGNE BASIC 380 28 8721381150390 | C821: Litho Sleeve Montagne Basic 380 28 | D821: SHTS
A822: 001760000600 | B822: FASCIA LITOGRAFTA CREPE PAN 179Ø 25 8000807075227 | C822: Litho Sleeve Crepe Pan 179 Dia. 25 | D822: SHTS
A823: 001760057800 | B823: FASCIA LIT.TEG.24 MONTANA RESTYLYNG 3522-346 | C823: Litho Sleeve Montana Restyling Pan 24 | D823: SHTS
A824: 001760057801 | B824: FASCIA LIT.TEG.28 MONTANA RESTYLYNG 3524-346 | C824: Litho Sleeve Montana Restyling Pan 28 | D824: SHTS
A825: 001761029103 | B825: FASCIA LIT.MIGROS STAR 2023 PAD.207 Ø20 7035.831-899466 | C825: Litho Sleeve Migros Star 2023 Pan Dia. 20 | D825: SHTS
A826: 001761029105 | B826: FASCIA LIT.MIGROS STAR 2023 PAD.207 Ø28 7035.839-899480 | C826: Litho Sleeve Migros Star 2023 Pan Dia. 28 | D826: SHTS
A827: 001761029109 | B827: FASCIA LIT.MIGROS STAR 2023 TEG.311 Ø28 7035.842-899619 | C827: Litho Sleeve Migros Star 2023 Pan Dia. 28 (Ref. 311) | D827: SHTS
A828: 001761029230 | B828: FASCIA LIT.MIGROS PRO CER.IN.2025 PAD.125Ø20 7038.359-663029 | C828: Litho Sleeve Migros Pro Cer.In. 2025 Pan Dia. 20 | D828: SHTS
A829: 001761029231 | B829: FASCIA LIT.MIGROS PRO CER.IN.2025 PAD.125Ø24 7038.360-663036 | C829: Litho Sleeve Migros Pro Cer.In. 2025 Pan Dia. 24 | D829: SHTS
A830: 001761029232 | B830: FASCIA LIT.MIGROS PRO CER.IN.2025 PAD.125Ø28 7038.361-663043 | C830: Litho Sleeve Migros Pro Cer.In. 2025 Pan Dia. 28 | D830: SHTS
A831: 001761029232 | B831: FASCIA LIT.MIGROS PRO CER.IN.2025 PAD.125Ø28 7038.361-663043 | C831: Litho Sleeve Migros Pro Cer.In. 2025 Pan Dia. 30 | D831: SHTS
A832: 001761029233 | B832: FASCIA LIT.MIGROS PRO CER.IN.2025 PAD.125Ø30 7038.362-663050 | C832: Litho Sleeve Migros Pro Cer.In. 2025 Pan Dia. 28 (Ref. 126) | D832: SHTS
... A930: 000110496001 | B930: GHIERA AR 0400 17/20,5 | C930: Ring Nut AR 0400 17/20.5mm | D930: NUT-
A931: 110520001 | B931: GHIERA AR 0400 16,5/20,5 R100 | C931: Ring Nut AR 0400 16.5/20.5 R100 | D931: NUT-
A932: 110521001 | B932: GHIERA AR 0400 16/19 R110 | C932: Ring Nut AR 0400 16/19 R110 | D932: NUT-
A933: 110559001 | B933: GHIERA L1500 11/30 R58 F90 A-8° | C933: Ring Nut L1500 11/30 R58 F90 A-8° | D933: NUT-
A934: 110593001 | B934: GHIERA P075 11,5/28 R70 F90 A-8° | C934: Ring Nut P075 11.5/28 R70 F90 A-8° | D934: NUT-
A935: 110594001 | B935: GHIERA P075 11,5/26 R55 F100 A-8° | C935: Ring Nut P075 11.5/26 R55 F100 A-8° | D935: NUT-
A936: 110595001 | B936: GHIERA P075 11,5/25 R55 F120 A-8° | C936: Ring Nut P075 11.5/25 R55 F120 A-8° | D936: NUT-
A937: 110635001 | B937: GHIERA AR 0400 17,5/20,5 R100 F140 | C937: Ring Nut AR 0400 17.5/20.5 R100 F140 | D937: NUT-
A938: 110636001 | B938: GHIERA AR 0400 18/20,5 R90 F140 | C938: Ring Nut AR 0400 18/20.5 R90 F140 | D938: NUT-
A939: 110636001 | B939: GHIERA AR 0400 18/20,5 R90 F140 | C939: Ring Nut AR 0400 18/20.5 R90 F140 | D939: NUT-
A940: 110645001 | B940: GHIERA AR 0400 18,5/25,5 R48 F110 | C940: Ring Nut AR 0400 18.5/25.5 R48 F110 | D940: NUT-
A941: 110646001 | B941: GHIERA AR 0400 19/24 R55 F140 A-0° | C941: Ring Nut AR 0400 19/24 R55 F140 A-0° | D941: NUT-
A942: 110649001 | B942: GHIERA AR 0400 15/21,5 R90 F140 A-0° | C942: Ring Nut AR 0400 15/21.5 R90 F140 A-0° | D942: NUT-
... A961: 112370001 | B961: GHIERA P089 15X23 R120 F140 A-8° X 125 28 | C961: Ring Nut P089 15X23 R120 F140 A-8° for 125 28 | D961: NUT-
A962: 000285501020 | B962: MANIGLIA TUBO AC.INOX AISI 441 SERIE "AX" PER PAELLERA | C962: Side Handle AISI "AX" Series for Paella Pan | D962: SHDL-
A963: 000251533001 | B963: MANIGLIA MOD.PRO NERA SATINATA | C963: Mod. Pro Satin Black side Handle | D963: SHDL-
A964: 000250904001 | B964: MANICO KELOMAT NEW MONKENNRSKX C/SER.SCRITTA KELOMAT(bianco) | C964: Kelomat New Handle w/ White Kelomat Printed Silk-screen | D964: HDL--
A965: 000280256001 | B965: MANICO 290/2 NE.AT.PAD.3R | C965: Handle 290/2 Non-toxic Black Pan 3R | D965: HDL--
A966: 000280256003 | B966: MANICO 290/2 NE.AT.PAD/CREP.2R | C966: Handle 290/2 Non-toxic Black Pan/Crepe 2R | D966: HDL--
A967: 000110532001 | B967: GHIERA P15 15,5/30,5 R15/824 FR75 | C967: Ring Nut P15 15.5/30.5 R15/824 FR75 | D967: NUT-
A968: 000280256003 | B968: MANICO 290/2 NE.AT.PAD/CREP.2R | C968: Handle 290/2 Non-toxic Black Pan/Crepe 2R | D968: HDL--
A969: 000320212001 | B969: POMOLO 810 STUDIO NERO SATINATO | C969: Knob 810 Studio Satin Black | D969: KNOB
A970: 000320212001 | B970: POMOLO 810 STUDIO NERO SATINATO | C970: Knob 810 Studio Satin Black | D970: KNOB
A971: 000250628001 | B971: MANICO LEGNO FONDUE PICCOLO | C971: Small Wooden Fondue Handle | D971: HDL--
A972: 000250630001 | B972: MANICO LEGNO FONDUE GRANDE | C972: Large Wooden Fondue Handle | D972: HDL--
A973: 001110033002 | B973: BUSTA BOCC.27X30 SU ENTRAMBI I LATI | C973: 27x30 Bubble Bag, open on both sides | D973: BAG-
... A992: 0001A0180005 | B992: DISCO AC.180/05 AISI430 LISCIO/SAT. | C992: Steel Disc 180/05 AISI430 Smooth/Satin | D992: SSM-
A994: 46082 | B994: Original Description | C994: Translated Part Description (English) | D994: Commodity | E994: Code
A995: 000050265032R | B995: DISCO AL.L.GREEN 265/32 RIC | C995: Aluminum Disc, Green Series, 265x3.2mm | D995: ALM-
A996: 000050315032R | B996: DISCO AL.L.GREEN 315/32 RIC | C996: Aluminum Disc, Green Series, 315x3.2mm | D996: ALM-
A997: 000050265032R | B997: DISCO AL.L.GREEN 265/32 RIC | C997: Aluminum Disc, Green Series, 265x3.2mm | D997: ALM-
A998: 000050315032R | B998: DISCO AL.L.GREEN 315/32 RIC | C998: Aluminum Disc, Green Series, 315x3.2mm | D998: ALM-
A999: 000050330032R | B999: DISCO AL.L.GREEN 330/32 RIC | C999: Aluminum Disc, Green Series, 330x3.2mm | D999: ALM-
A1000: 002490296001 | B1000: FA 5231 marrone spinello | C1000: Pigment FA 5231, Brown Spinel | D1000: INM-
A1001: 002430002001 | B1001: SILIKOFTAL HTL 2 | C1001: Silikoftal HTL 2 (Silicone Resin Coating) | D1001: INM-
A1002: 002430002001 | B1002: SILIKOFTAL HTL 2 | C1002: Silikoftal HTL 2 (Silicone Resin Coating) | D1002: INM-
A1003: 003010503004 | B1003: 459G-R0185 ROLLER PRIMER GRAY | C1003: Roller Primer Gray 459G-R0185 | D1003: INM-
A1004: 003040090024 | B1004: 479G-81190 PRIMER BLACK PROFES (ex 811) | C1004: Primer Black Professional 479G-81190 | D1004: INM-
A1005: 003130002004 | B1005: 455G-R0385 ROLLER TOPCOAT PEWTER | C1005: Roller Topcoat Pewter 455G-R0385 | D1005: INM-
A1006: 000730415001 | B1006: REC1608AS-002 COP.AC.MADE IN 16CM AS. | C1006: SS Lid 16cm Assembled w/ PVD Gold Handle | D1006: LID-
... A1056: 000051617619R | B1056: RETT.AL.GREEN 310X225X19 CON BORDI TAGLIATI RIC | C1056: Aluminum Rectangle, Green Series, 310x225x1.9mm, with cut edges | D1056: ALM-
A1057: 420113001 | B1057: ROND.ACC.SOTT.XVITE 5MA 11,5X2,5MM | C1057: Thin steel washer for M5 screw, 11.5x2.5mm | D1057: WHR-
A1058: 450296001 | B1058: RIBATTINO 5X14 AG5 | C1058: 5x14mm rivet, AG5 aluminum alloy | D1058: RIV-
A1059: 000250518001 | B1059: MANICO TITANO/0 PICCOLISSIMO NERO SATINATO | C1059: Titano/0 Handle, Very Small, Satin Black | D1059: HDL
A1060: 000250562001 | B1060: MANICO GERM/2 NER.SAT.S/TVS MOD.DEP | C1060: Germ/2 Handle, Satin Black without TVS, Registered Design | D1060: HDL
A1061: 000250622001 | B1061: MANICO STYLE/1 NERO SATINATO | C1061: Style/1 Handle, Satin Black | D1061: HDL
A1062: 000251518001 | B1062: MANIGLIA GERMANIA NERA SATINATA | C1062: Germany Side Handle, Satin Black | D1062: HDL
A1063: 000251618001 | B1063: MANIGLIA TITANO NERA SATINATA | C1063: Titano Side Handle, Satin Black | D1063: HDL
A1064: 000282003002 | B1064: MANICO AC.SAT.MED.ARTUSI PA.28/ NEW | C1064: Artusi Medium Satin Steel Handle, PA.28 / New | D1064: HDL
A1065: 000288000058 | B1065: 1-5-HSI210CAY LG 210 MA.IN PVD GOLD BSH HCK3427AX C/C48 6.5 | C1065: 1-5-HSI210CAY LG 210 Made in PVD Gold, BSH H | D1065: HDL
A1066: 000288100058 | B1066: 1-5-HSI210C-Y LG 210 MADE IN BSH HCK3427AX C/C48 (6,5 mm) | C1066: 1-5-HSI210C-Y LG 210 Made in BSH HCK3427A | D1066: HDL
A1067: 000288200058 | B1067: 1-5-HSI210CCY LG 210 MA.IN GD04K ROSE BSH HCK3427AX C/C48 | C1067: 1-5-HSI210CCY LG 210 Made in GD04K Rose BSH | D1067: HDL
A1068: 000289000053 | B1068: 1-5-SSI210CAY STD 210 MADE IN PVD GOLD BSH HCK3427AX C/C83 | C1068: 1-5-SSI210CAY STD 210 Made in PVD Gold, BSH | D1068: HDL
A1069: 000289100053 | B1069: 1-5-SSI210C-Y STD210 MADE IN BSH HCK3427AX C/C83.6 (6,5 mm) | C1069: 1-5-SSI210C-Y STD210 Made in BSH HCK3427A | D1069: HDL
A1070: 000289200053 | B1070: 1-5-SSI210CCY STD210 MA.IN GD04K ROSE BSH HCK3427AX C/C83 | C1070: 1-5-SSI210CCY STD210 Made in GD04K Rose BSH | D1070: HDL
... A1247: 000281710006 | B1247: MANICO AC.SOLE LUNGO C/LOGO MC AISI 430 SABBIATO TEG.379 26 | C1247: Steel Long Handle, SOLE Long w/ Logo MC, AISI 430, Sandblasted, Skillet 379-26 | D1247: HDL-
B1248: Original Description | C1248: Translated Part Description (English) | D1248: Commodity | E1248: Code
A1249: 000320380001 | B1249: POMOLO AC.SOLE C/LOGO MC AISI 430 SA | C1249: Steel Knob, SOLE w/ Logo MC, AISI 430, Sandblasted | D1249: KNOB
A1250: 000281710001 | B1250: MANICO AC.SOLE CORTO C/LOGO MC AIS | C1250: Steel Side Handle, SOLE Short w/ Logo MC, AISI 430 | D1250: SHDL
A1251: 000281710003 | B1251: MANICO AC.SOLE CORTO C/LOGO MC AIS | C1251: Steel Side Handle, SOLE Short w/ Logo MC, AISI 430 | D1251: SHDL
A1252: 000281710005 | B1252: MANICO AC.SOLE LUNGO C/LOGO MC AIS | C1252: Steel Long Handle, SOLE Long w/ Logo MC, AISI 430 | D1252: HDL-
A1253: 000281710005 | B1253: MANICO AC.SOLE LUNGO C/LOGO MC AIS | C1253: Steel Long Handle, SOLE Long w/ Logo MC, AISI 430 | D1253: HDL-
A1254: 000700042002 | B1254: COP.VET.20 PIAT.BOR./SF.VAP.SIL.STD | C1254: Flat Glass Lid, 20cm, Silicone Rim, Steam Vent Standard | D1254: LID-
A1255: 000700050002 | B1255: COP.VET.32 PIAT.BOR./SF.VAP.SIL.STD | C1255: Flat Glass Lid, 32cm, Silicone Rim, Steam Vent Standard | D1255: LID-
A1256: 000700081001 | B1256: COP.VET.26 PIATTO BORDO ACCIAIO C/F.V | C1256: Flat Glass Lid, 26cm, Steel Rim w/ Steam Vent | D1256: LID-
A1257: 000700090001 | B1257: COP.VET.16 PIATTO BOR.SILICONE (nero)P | C1257: Flat Glass Lid, 16cm, Silicone Rim (Black) | D1257: LID-
A1258: 000700090002 | B1258: COP.VET.20 PIATTO BOR.SILICONE (nero)P | C1258: Flat Glass Lid, 20cm, Silicone Rim (Black) | D1258: LID-
A1259: 000700090003 | B1259: COP.VET.24 PIATTO BOR.SILICONE (nero)P | C1259: Flat Glass Lid, 24cm, Silicone Rim (Black) | D1259: LID-
A1260: 000700090004 | B1260: COP.VET.28 PIATTO BOR.SILICONE (nero)P | C1260: Flat Glass Lid, 28cm, Silicone Rim (Black) | D1260: LID-
... A1278: 000288100053 | B1278: 1-5-HSI107C-Y SI HANDLE 24CM SAUCIER | C1278: SI Long Handle, 24cm Saucier | D1278: HDL-
C1279: Translated Part Description (English) | D1279: Commodity | E1279: Code
A1280: 000288100054 | B1280: 1-5-HSI108C-Y SI HANDLE 26CM SAUTE' (6.5mm hole) | C1280: SI Long Handle, 26cm Saute (6.5mm hole) | D1280: HDL-
A1281: 000288100055 | B1281: 1-5-HSI203C-Y SI HANDLE 20CM SKILLET (6.5mm hole) | C1281: SI Long Handle, 20cm Skillet (6.5mm hole) | D1281: HDL-
A1282: 000288100056 | B1282: 1-5-HSI206C-Y SI HANDLE 26CM SKILLET (6.5mm hole) | C1282: SI Long Handle, 26cm Skillet (6.5mm hole) | D1282: HDL-
...

Sheet 工作表2
A3: Commodity Italian | B3: Commodity English
A4: accessori di confez. | B4: packaging accessories
A5: accessori finiti | B5: finished accessories
A6: accessori x manigl. | B6: accessories for handles
A7: acciaio | B7: steel
A8: Acciaio multistrato (5PLY) | B8: multilayer steel (5PLY)
A9: alluminio | B9: aluminium
A10: cartoni e casse | B10: cartons and boxes
A11: manigliame | B11: handles
A12: mater. di confezion. | B12: packaging material
A13: mater.aus.varie acq. | B13: various auxiliary materials purchased
A14: materiali di consumo | B14: consumable materials
... A18: (空白) | B18: (空白)
A19: 總計

Sheet By Gemini
A1: Item Code | B1: Part Description | C1: Commodity Italian | D1: Commodity English | E1: Translated Part Description (English) | F1: Unified Commodity Code
A2: 002300020064 | B2: "DIVISORIO FUST.""B""X PAD.24+28" | C2: cartoni e casse | D2: cartons and boxes | E2: "DIVISORIO FUST.""B""X PAD.24+28" | F2: BOX-
A3: 002490149001 | B3: 1008335 PS UMB EP-62 Blue Oltremare | C3: prodotti chimici | D3: chemical products | E3: 1008335 PS UMB EP-62 Blue Oltremare | F3: CBS-
A4: 003040104009 | B4: 1224-002 DURIT Professional P Primer Black | C4: prodotti chimici | D4: chemical products | E4: 1224-002 DURIT Professional P Primer Black | F4: PRIM
A5: 000288100051 | B5: 1-5-HSI103C-Y SI HANDLE 16CM SAUCEPAN (6.5mm hole) | C5: manigliame | D5: handles | E5: =VLOOKUP(Tabella3[[#This Row],[Item Code]],'DESC ITY - ENG'!A:C,3,FALSE) -> 1-5 SI Handle 16cm Saucepan (6.5mm hole) | F5: =VLOOKUP(Tabella3[[#This Row],[Item Code]],Foglio8!A:C,3,FALSE) -> #N/A
A6: 000288100052 | B6: 1-5-HSI105C-Y SI HANDLE 20CM SAUCEPAN (6.5mm hole) | C6: manigliame | D6: handles | E6: =VLOOKUP(Tabella3[[#This Row],[Item Code]],'DESC ITY - ENG'!A:C,3,FALSE) -> 1-5 SI Handle 20cm Saucepan (6.5mm hole) | F6: =VLOOKUP(Tabella3[[#This Row],[Item Code]],Foglio8!A:C,3,FALSE) -> #N/A
A7: 000288100055 | B7: 1-5-HSI203C-Y SI HANDLE 20CM SKILLET (6.5mm hole) | C7: manigliame | D7: handles | E7: =VLOOKUP(Tabella3[[#This Row],[Item Code]],'DESC ITY - ENG'!A:C,3,FALSE) -> 1-5 SI Handle 20cm Skillet (6.5mm hole) | F7: =VLOOKUP(Tabella3[[#This Row],[Item Code]],Foglio8!A:C,3,FALSE) -> #N/A
A8: 000288100053 | B8: 1-5-HSI107C-Y SI HANDLE 24CM SAUCIER (6.5mm hole) | C8: manigliame | D8: handles | E8: =VLOOKUP(Tabella3[[#This Row],[Item Code]],'DESC ITY - ENG'!A:C,3,FALSE) -> 1-5 SI Handle 24cm Saucier (6.5mm hole) | F8: =VLOOKUP(Tabella3[[#This Row],[Item Code]],Foglio8!A:C,3,FALSE) -> #N/A
A9: 000288100054 | B9: 1-5-HSI108C-Y SI HANDLE 26CM SAUTE' (6.5mm hole) | C9: manigliame | D9: handles | E9: =VLOOKUP(Tabella3[[#This Row],[Item Code]],'DESC ITY - ENG'!A:C,3,FALSE) -> 1-5 SI Handle 26cm Saute (6.5mm hole) | F9: =VLOOKUP(Tabella3[[#This Row],[Item Code]],Foglio8!A:C,3,FALSE) -> #N/A
A10: 000288100056 | B10: 1-5-HSI206C-Y SI HANDLE 26CM SKILLET (6.5mm hole) | C10: manigliame | D10: handles | E10: =VLOOKUP(Tabella3[[#This Row],[Item Code]],'DESC ITY - ENG'!A:C,3,FALSE) -> 1-5 SI Handle 26cm Skillet (6.5mm hole) | F10: =VLOOKUP(Tabella3[[#This Row],[Item Code]],Foglio8!A:C,3,FALSE) -> #N/A
A11: 000288100057 | B11: 1-5-HSI208C-Y SI HANDLE 30CM SKILLET (6.5mm hole) | C11: manigliame | D11: handles | E11: =VLOOKUP(Tabella3[[#This Row],[Item Code]],'DESC ITY - ENG'!A:C,3,FALSE) -> 1-5 SI Handle 30cm Skillet (6.5mm hole) | F11: =VLOOKUP(Tabella3[[#This Row],[Item Code]],Foglio8!A:C,3,FALSE) -> #N/A
A12: 000288000051 | B12: 1-5-HSI103CAY SI HANDLE PVD GOLD 16CM SAUCEPAN (6.5mm hole) | C12: manigliame | D12: handles | E12: =VLOOKUP(Tabella3[[#This Row],[Item Code]],'DESC ITY - ENG'!A:C,3,FALSE) -> 1-5 SI Handle PVD Gold 16cm Saucepan (6.5mm hole) | F12: =VLOOKUP(Tabella3[[#This Row],[Item Code]],Foglio8!A:C,3,FALSE) -> #N/A
A13: 000288000052 | B13: 1-5-HSI105CAY SI HANDLE PVD GOLD 20CM SAUCEPAN (6.5mm hole) | C13: manigliame | D13: handles | E13: =VLOOKUP(Tabella3[[#This Row],[Item Code]],'DESC ITY - ENG'!A:C,3,FALSE) -> 1-5 SI Handle PVD Gold 20cm Saucepan (6.5mm hole) | F13: =VLOOKUP(Tabella3[[#This Row],[Item Code]],Foglio8!A:C,3,FALSE) -> #N/A
A14: 000288000055 | B14: 1-5-HSI203CAY SI HANDLE PVD GOLD 20CM SKILLET (6.5mm hole) | C14: manigliame | D14: handles | E14: =VLOOKUP(Tabella3[[#This Row],[Item Code]],'DESC ITY - ENG'!A:C,3,FALSE) -> 1-5 SI Handle PVD Gold 20cm Skillet (6.5mm hole) | F14: =VLOOKUP(Tabella3[[#This Row],[Item Code]],Foglio8!A:C,3,FALSE) -> #N/A
A15: 000288000053 | B15: 1-5-HSI107CAY SI HANDLE PVD GOLD 24CM SAUCIER (6.5mm hole) | C15: manigliame | D15: handles | E15: =VLOOKUP(Tabella3[[#This Row],[Item Code]],'DESC ITY - ENG'!A:C,3,FALSE) -> 1-5 SI Handle PVD Gold 24cm Saucier (6.5mm hole) | F15: =VLOOKUP(Tabella3[[#This Row],[Item Code]],Foglio8!A:C,3,FALSE) -> #N/A
A16: 000288000054 | B16: 1-5-HSI108CAY SI HANDLE PVD GOLD 26CM SAUTE' (6.5mm hole) | C16: manigliame | D16: handles | E16: =VLOOKUP(Tabella3[[#This Row],[Item Code]],'DESC ITY - ENG'!A:C,3,FALSE) -> 1-5 SI Handle PVD Gold 26cm Saute (6.5mm hole) | F16: =VLOOKUP(Tabella3[[#This Row],[Item Code]],Foglio8!A:C,3,FALSE) -> #N/A
... A20: 000289000052 | B20: 1-5-SSI108CAY SI SIDE IHANDLE PVD GOLD 26CM STOCK.(6.5mm ho) | C20: manigliame | D20: handles | E20: =VLOOKUP(Tabella3[[#This Row],[Item Code]],'DESC ITY - ENG'!A:C,3,FALSE) -> 1-5 SI Side Handle PVD Gold 26cm Stock (6.5mm hole) | F20: =VLOOKUP(Tabella3[[#This Row],[Item Code]],Foglio8!A:C,3,FALSE) -> #N/A
A21: 000288000001 | B21: 1-5-HSI103BAY SI HANDLE PVD GOLD 16CM SAUCEPAN (6.5mm hole) | C21: manigliame | D21: handles | E21: 1-5-HSI103BAY SI HANDLE PVD GOLD 16CM SAUCEPAN (6.5mm hole) | F21: HDL-
A22: 000288100001 | B22: 1-5-HSI103B-Y SI HANDLE 16CM SAUCEPAN (6.5mm hole) | C22: manigliame | D22: handles | E22: 1-5-HSI103B-Y SI HANDLE 16CM SAUCEPAN (6.5mm hole) | F22: HDL-
A23: 000288000002 | B23: 1-5-HSI105BAY SI HANDLE PVD GOLD 20CM SAUCEPAN (6.5mm hole) | C23: manigliame | D23: handles | E23: 1-5-HSI105BAY SI HANDLE PVD GOLD 20CM SAUCEPAN (6.5mm hole) | F23: HDL-
A24: 000288100002 | B24: 1-5-HSI105B-Y SI HANDLE 20CM SAUCEPAN (6.5mm hole) | C24: manigliame | D24: handles | E24: 1-5-HSI105B-Y SI HANDLE 20CM SAUCEPAN (6.5mm hole) | F24: HDL-
A25: 000288000003 | B25: 1-5-HSI107BAY SI HANDLE PVD GOLD 24CM SAUCIER (6.5mm hole) | C25: manigliame | D25: handles | E25: 1-5-HSI107BAY SI HANDLE PVD GOLD 24CM SAUCIER (6.5mm hole) | F25: HDL-
A26: 000288100003 | B26: 1-5-HSI107B-Y SI HANDLE 24CM SAUCIER (6.5mm hole) | C26: manigliame | D26: handles | E26: 1-5-HSI107B-Y SI HANDLE 24CM SAUCIER (6.5mm hole) | F26: HDL-
A27: 000288000004 | B27: 1-5-HSI108BAY SI HANDLE PVD GOLD 26CM SAUTE' (6.5mm hole) | C27: manigliame | D27: handles | E27: 1-5-HSI108BAY SI HANDLE PVD GOLD 26CM SAUTE' (6.5mm hole) | F27: HDL-
A28: 000288100004 | B28: 1-5-HSI108B-Y SI HANDLE 26CM SAUTE' (6.5mm hole) | C28: manigliame | D28: handles | E28: 1-5-HSI108B-Y SI HANDLE 26CM SAUTE' (6.5mm hole) | F28: HDL-
A29: 000288000005 | B29: 1-5-HSI203BAY SI HANDLE PVD GOLD 20CM SKILLET (6.5mm hole) | C29: manigliame | D29: handles | E29: 1-5-HSI203BAY SI HANDLE PVD GOLD 20CM SKILLET (6.5mm hole) | F29: HDL-
A30: 000288100005 | B30: 1-5-HSI203B-Y SI HANDLE 20CM SKILLET (6.5mm hole) | C30: manigliame | D30: handles | E30: 1-5-HSI203B-Y SI HANDLE 20CM SKILLET (6.5mm hole) | F30: HDL-
A31: 000288000006 | B31: 1-5-HSI206BAY SI HANDLE PVD GOLD 26CM SKILLET (6.5mm hole) | C31: manigliame | D31: handles | E31: 1-5-HSI206BAY SI HANDLE PVD GOLD 26CM SKILLET (6.5mm hole) | F31: HDL-
A32: 000288100006 | B32: 1-5-HSI206B-Y SI HANDLE 26CM SKILLET (6.5mm hole) | C32: manigliame | D32: handles | E32: 1-5-HSI206B-Y SI HANDLE 26CM SKILLET (6.5mm hole) | F32: HDL-
... A55: 000030470023 | B55: DISCO 5PLY 470/23 SS304 0,4 + Al1,4 + SS439 0,5 TOT 23/10 | C55: Acciaio multistrato (5PLY) | D55: multilayer steel (5PLY) | E55: 5PLY DISC 470/23 SS304 0,4 + Al1,4 + SS439 0,5 TOT 23/10 | F55: uncl
A56: 000390103024 | B56: VITE 5MAX14 AC.AUTOM.ZIG.C/TORX T25 | C56: accessori x manigl. | D56: accessories for handles | E56: =VLOOKUP(Tabella3[[#This Row],[Item Code]],'DESC ITY - ENG'!A:C,3,FALSE) -> 5x14 Auto Steel Knurled Screw w/ Torx T25 | F56: PRIM
A57: 003160081019 | B57: 7343/V5949Z SILVER Q. CONSTEL. 1P | C57: prodotti chimici | D57: chemical products | E57: 7343/V5949Z SILVER Q. CONSTEL. 1P | F57: uncl
A58: 003481003001 | B58: 750.20 S LACCA R.TER.NERO2978000015 | C58: prodotti chimici | D58: chemical products | E58: 750.20 S LACCA R.TER.NERO2978000015 | F58: SHTS
A59: 009430060001 | B59: 770 PRIMER LOCT0016777 GR.10 | C59: materiali di consumo | D59: consumable materials | E59: 770 PRIMER LOCT0016777 GR.10 | F59: PRIM
A60: 000320212001 | B60: POMOLO 810 STUDIO NERO SATINATO | C60: manigliame | D60: handles | E60: 810 STUDIO SATIN BLACK KNOB | F60: KNOB
A61: 000283490001 | B61: MANIGLIA AC.LEVANTE SABBIATA CASS.D.20 | C61: manigliame | D61: handles | E61: AC.LEVANTE SANDBLASTED HANDLE POT D.20 (472) | F61: HDL-
A62: 000283490001 | B62: MANIGLIA AC.LEVANTE SABBIATA CASS.D.20 (472) | C62: manigliame | D62: handles | E62: AC.LEVANTE SANDBLASTED HANDLE POT D.20 (472) | F62: HDL-
A63: 000281710007 | B63: MANIGLIA AC.SOLE C/LOGO MC AISI 430 SABBIATA CAS.480 20 | C63: manigliame | D63: handles | E63: AC.SOLE HANDLE W/LOGO MC AISI 430 SANDBLASTED CAS.480 20 | F63: HDL-
A64: 000320380001 | B64: POMOLO AC.SOLE C/LOGO MC AISI 430 SABBIATO | C64: manigliame | D64: handles | E64: AC.SOLE KNOB W/LOGO MC AISI 430 SANDBLASTED | F64: KNOB
A65: 000281710005 | B65: MANICO AC.SOLE LUNGO C/LOGO MC AISI 430 SABBIATO PAD.279 30 | C65: manigliame | D65: handles | E65: AC.SOLE LONG HANDLE W/LOGO MC AISI 430 SANDBLASTED PAD.279 30 | F65: HDL-
A66: 000281710006 | B66: MANICO AC.SOLE LUNGO C/LOGO MC AISI 430 SABBIATO TEG.379 26 | C66: manigliame | D66: handles | E66: AC.SOLE LONG HANDLE W/LOGO MC AISI 430 SANDBLASTED TEG.379 26 | F66: HDL-
A67: 000281710003 | B67: MANICO AC.SOLE CORTO C/LOGO MC AISI 430 SABBIATO CAS.433 16 | C67: manigliame | D67: handles | E67: AC.SOLE SHORT HANDLE W/LOGO MC AISI 430 SANDBLASTED CAS.433 16 | F67: HDL-
A68: 000281710001 | B68: MANICO AC.SOLE CORTO C/LOGO MC AISI 430 SABBIATO PAD.279 20 | C68: manigliame | D68: handles | E68: AC.SOLE SHORT HANDLE W/LOGO MC AISI 430 SANDBLASTED PAD.279 20 | F68: HDL-
... A72: 002340514002 | B72: ACEMATT 3300 OPACIZ. SOFT-TOUCH LAC | C72: prodotti chimici | D72: chemical products | E72: ACEMATT 3300 OPACIZ. SOFT-TOUCH LAC | F72: FLAN
A73: 002340514003 | B73: ACEMATT OK-390 opacizzante | C73: prodotti chimici | D73: chemical products | E73: =VLOOKUP(Tabella3[[#This Row],[Item Code]],'DESC ITY - ENG'!A:C,3,FALSE) -> Acematt OK-390 Matting Agent | F73: PRIM
A74: 009200001001 | B74: ACIDO CLORIDRICO | C74: materiali di consumo | D74: consumable materials | E74: ACIDO CLORIDRICO | F74: LABL
A75: 002310002001 | B75: ACIDO OLEICO | C75: prodotti chimici | D75: chemical products | E75: ACIDO OLEICO | F75: CBS-
A76: 002430065001 | B76: ACRYSOL RM 55 | C76: prodotti chimici | D76: chemical products | E76: ACRYSOL RM 55 | F76: FLAN
A77: 000800004001 | B77: ETICHETTA ADESIVA Ø 40 MM ANTITACCHEGGIO DEL CLIENTE (TCM) | C77: mater. di confezion. | D77: packaging material | E77: ADHESIVE LABEL Ø 40 MM ANTI-SHOPLIFTING CUSTOMER (TCM) | F77: LABL
A78: 000250274001 | B78: MANICO ACCIAIO AISI 201 SATINATO FONDUE GRANDE | C78: manigliame | D78: handles | E78: AISI 201 SATIN STEEL FONDUE HANDLE LARGE | F78: HDL-
A79: 000070205014R | B79: DISCO AL.1200 205/14 RIC | C79: alluminio | D79: aluminium | E79: AL.1200 DISC 205/14 RIC | F79: ALM-
A80: 000070230014R | B80: DISCO AL.1200 230/14 RIC | C80: alluminio | D80: aluminium | E80: AL.1200 DISC 230/14 RIC | F80: ALM-
A81: 000070265022R | B81: DISCO AL.1200 265/22 RIC | C81: alluminio | D81: aluminium | E81: AL.1200 DISC 265/22 RIC | F81: ALM-
A82: 000070340010R | B82: DISCO AL.1200 340/10 RIC | C82: alluminio | D82: aluminium | E82: AL.1200 DISC 340/10 RIC | F82: ALM-
A83: 000040155019R | B83: DISCO AL.4006 155/19 RIC | C83: alluminio | D83: aluminium | E83: AL.4006 DISC 155/19 RIC | F83: ALM-
A84: 000040205036R | B84: DISCO AL.4006 205/36 RIC | C84: alluminio | D84: aluminium | E84: AL.4006 DISC 205/36 RIC | F84: ALM-
A85: 000040215036R | B85: DISCO AL.4006 215/36 RIC | C85: alluminio | D85: aluminium | E85: AL.4006 DISC 215/36 RIC | F85: ALM-
... A628: 001516408000 | B628: BOX 6408/000 CM23X14X13 | C628: cartoni e casse | D628: cartons and boxes | E628: BOX 6408/000 CM23X14X13 | F628: BAG-
A629: 001516408012 | B629: BOX 6408/012*CM23X14X13 | C629: cartoni e casse | D629: cartons and boxes | E629: BOX 6408/012*CM23X14X13 | F629: #N/A
A630: 001516408013 | B630: BOX 6408/013*CM23X14X13 | C630: cartoni e casse | D630: cartons and boxes | E630: BOX 6408/013*CM23X14X13 | F630: #N/A
A631: 001516408014 | B631: BOX 6408/014*CM23X14X13 | C631: cartoni e casse | D631: cartons and boxes | E631: BOX 6408/014*CM23X14X13 | F631: BAG-
A632: 001516409000 | B632: BOX 6409/000 CM29X18,5X15 CM | C632: cartoni e casse | D632: cartons and boxes | E632: BOX 6409/000 CM29X18,5X15 CM | F632: BOX-
A633: 001516445000 | B633: BOX 6445/000 CM39X38,5X33,5 | C633: cartoni e casse | D633: cartons and boxes | E633: BOX 6445/000 CM39X38.5X33.5 | F633: BOX-
A634: 001516459007 | B634: BOX 6459/007 *CM59X35X20 | C634: cartoni e casse | D634: cartons and boxes | E634: BOX 6459/007 *CM59X35X20 | F634: uncl
A635: 001516459008 | B635: BOX 6459/008*CM59X35X20 \\ | C635: cartoni e casse | D635: cartons and boxes | E635: BOX 6459/008*CM59X35X20 \ | F635: BOX-
A636: 001516504000 | B636: BOX 6504/000 CM25X16X13 | C636: cartoni e casse | D636: cartons and boxes | E636: BOX 6504/000 CM25X16X13 | F636: HDL-
A637: 001516521000 | B637: BOX 6521/000 CM47X26,5X39 | C637: cartoni e casse | D637: cartons and boxes | E637: BOX 6521/000 CM47X26,5X39 | F637: ALM-
A638: 001516522000 | B638: BOX 6522/000 CM61X50,5X24 | C638: cartoni e casse | D638: cartons and boxes | E638: BOX 6522/000 CM61X50,5X24 | F638: ALM-
A639: 001516523000 | B639: BOX 6523/000 CM61X50,5X28 | C639: cartoni e casse | D639: cartons and boxes | E639: BOX 6523/000 CM61X50,5X28 | F639: ALM-
A640: 001546550002 | B640: BOX 6550/002 CM56X33,5X27 \\ | C640: cartoni e casse | D640: cartons and boxes | E640: BOX 6550/002 CM56X33,5X27 \ | F640: BOX-
A641: 001516562000 | B641: BOX 6562/000 CM39X28,5X35 | C641: cartoni e casse | D641: cartons and boxes | E641: BOX 6562/000 CM39X28.5X35 | F641: BOX-
A642: 001516563000 | B642: BOX 6563/000 CM29X25X24 | C642: cartoni e casse | D642: cartons and boxes | E642: BOX 6563/000 CM29X25X24 | F642: BOX-
... A723: 001716789002 | B723: BOX LIT.6789 DEEP SKI.28 ESSTEELE X DOMANI REST 051153103773 | C723: cartoni e casse | D723: cartons and boxes | E723: BOX LIT.6789 DEEP SKI.28 ESSTEELE X DOMANI REST 051153103773 | F723: LABL
A724: 001716824004 | B724: BOX LIT.6824 7 PEZZI FONDUE Ø16 CM 7033.357 EAN.-526775 | C724: cartoni e casse | D724: cartons and boxes | E724: BOX LIT.6824 7 PEZZI FONDUE Ø16 CM 7033.357 EAN.-526775 | F724: #N/A
A725: 001716829002 | B725: BOX LIT.6829 BATT.5 PCS ESSTEELE X SALUTE REST. 051153107320 | C725: cartoni e casse | D725: cartons and boxes | E725: BOX LIT.6829 BATT.5 PCS ESSTEELE X SALUTE REST. 051153107320 | F725: LABL
A726: 001716836004 | B726: BOX LIT.6836 C.2M.F.480 C/C. Ø20 EXP SILVER COLOUR FOXHOME | C726: cartoni e casse | D726: cartons and boxes | E726: BOX LIT.6836 C.2M.F.480 W/LID. Ø20 EXP SILVER COLOUR FOXHOME | F726: BOX-
A727: 001716838003 | B727: BOX LIT.6838 C.2M.F.474 C/C. Ø28 EXP SILVER COLOUR FOXHOME | C727: cartoni e casse | D727: cartons and boxes | E727: BOX LIT.6838 C.2M.F.474 C/C. Ø28 EXP SILVER COLOUR FOXHOME | F727: LABL
A728: 001716905002 | B728: BOX LIT.6905 CO.SAUTE 28 ESSTEELE X SALUTE REST 051153107023 | C728: cartoni e casse | D728: cartons and boxes | E728: BOX LIT.6905 CO.SAUTE 28 ESSTEELE X SALUTE REST 051153107023 | F728: LABL
A729: 001716915002 | B729: BOX LIT.6915 VESUVIO INDUCTION CASS.474Ø24 C/COP.B.SILIC. | C729: cartoni e casse | D729: cartons and boxes | E729: BOX LIT.6915 VESUVIO INDUCTION CASS.474Ø24 C/COP.B.SILIC. | F729: BOX-
A730: 001716926003 | B730: BOX LIT.6926 WPRO INTERF.REST 2025 DISC FOR IND.Ø22 E.475944 | C730: cartoni e casse | D730: cartons and boxes | E730: BOX LIT.6926 WPRO INTERF.REST 2025 DISC FOR IND.Ø22 E.475944 | F730: uncl
A731: 001716926002 | B731: BOX LIT.6926 WPRO INTERF.REST DISC FOR IND.Ø22 8015250475944 | C731: cartoni e casse | D731: cartons and boxes | E731: BOX LIT.6926 WPRO INTERF.REST DISC FOR IND.Ø22 8015250475944 | F731: BOX-
A732: 001716931002 | B732: BOX LIT.6931 CASS.1MØ20 C/C.MEYER AUS.ESSTEELE X DOMANI REST | C732: cartoni e casse | D732: cartons and boxes | E732: BOX LIT.6931 CASS.1MØ20 C/C.MEYER AUS.ESSTEELE X DOMANI REST | F732: BOX-
A733: 001716932002 | B733: BOX LIT.6932 CASS.2MØ28 C/COP.MEYER AUS.ESSTEELE DOMANI REST | C733: cartoni e casse | D733: cartons and boxes | E733: BOX LIT.6932 CASS.2MØ28 C/COP.MEYER AUS.ESSTEELE DOMANI REST | F733: LABL
A734: 001716933002 | B734: BOX LIT.6933 TEG.2MØ30 C/C.MEYER AUS.ESSTEELE X DOMAN REST. | C734: cartoni e casse | D734: cartons and boxes | E734: BOX LIT.6933 TEG.2MØ30 C/C.MEYER AUS.ESSTEELE X DOMAN REST. | F734: BOX-
A735: 001716946003 | B735: BOX LIT.6946 ECO GEN || 3 PC COV SAUCEPAN SET 5000263150905 | C735: cartoni e casse | D735: cartons and boxes | E735: BOX LIT.6946 ECO GEN || 3 PC COV SAUCEPAN SET 5000263150905 | F735: BOX-
A736: 001716953002 | B736: BOX LIT.6953 31X23+35X27 CM MEYER AUS.ESSTEELE ACC.RESTYLING | C736: cartoni e casse | D736: cartons and boxes | E736: BOX LIT.6953 31X23+35X27 CM MEYER AUS.ESSTEELE ACC.RESTYLING | F736: BOX-
... A740: 001717037002 | B740: BOX LIT.7037 SKILLE 30 ESSTEELE X DOMANI REST.051153141041 | C740: cartoni e casse | D740: cartons and boxes | E740: BOX LIT.7037 SKILLET 30 ESSTEELE X DOMANI REST. | F740: BOX-
A741: 001717058008 | B741: BOX LIT.7058 MIGROS FONDUE Ø22CM 9 PZ 7033.360-7621361526799 | C741: cartoni e casse | D741: cartons and boxes | E741: BOX LIT.7058 MIGROS FONDUE Ø22CM 9 PZ 7033.360-7621361526799 | F741: #N/A
A742: 001717058007 | B742: BOX LIT.7058 MIGROS FONDUE Ø22CM 9 PZ 7033.361-7621361527130 | C742: cartoni e casse | D742: cartons and boxes | E742: BOX LIT.7058 MIGROS FONDUE Ø22CM 9 PZ 7033.361-7621361527130 | F742: #N/A
A743: 001717077002 | B743: BOX LIT.7077 COV.CAS.+C.24 ESSTEELE SALUTE REST.051153161087 | C743: cartoni e casse | D743: cartons and boxes | E743: BOX LIT.7077 COV.CAS.+C.24 ESSTEELE SALUTE REST.051153161087 | F743: BOX-
A744: 001717078005 | B744: BOX LIT.7078 6PC COOKWARE SET ESSTEELE x SILVIA 051153166983 | C744: cartoni e casse | D744: cartons and boxes | E744: BOX LIT.7078 6PC COOKWARE SET ESSTEELE x SILVIA 051153166983 | F744: BOX-
A745: 001717720004 | B745: BOX LIT.7720 DOMEDIA MANCHE AMOVIBLE 2024 NEW 3250392347086 | C745: cartoni e casse | D745: cartons and boxes | E745: BOX LIT.7720 DOMEDIA REMOVABLE HANDLE 2024 NEW | F745: BOX-
A746: 001717720001 | B746: BOX LIT.7720 HOMESIDE MANCHE AMOVIBLE 2023 3601029849624 | C746: cartoni e casse | D746: cartons and boxes | E746: BOX LIT.7720 HOMESIDE REMOVABLE HANDLE 2023 3601029849624 | F746: BOX-
A747: 001717724001 | B747: BOX LIT.7724 T.5742M Ø32 C/C.ESSTEELE BENESSERE 051153161346 | C747: cartoni e casse | D747: cartons and boxes | E747: BOX LIT.7724 T.5742M Ø32 C/C.ESSTEELE BENESSERE 051153161346 | F747: BOX-
A748: 001717725001 | B748: BOX LIT.7725 WOK.32 C/CO ESSTEELE PER BENESSERE 051153161377 | C748: cartoni e casse | D748: cartons and boxes | E748: BOX LIT.7725 WOK.32 C/CO ESSTEELE PER BENESSERE 051153161377 | F748: BOX-
A749: 001717730001 | B749: BOX LIT.7730 WOK 793 30 CM TITAN DUO 8000807072677 | C749: cartoni e casse | D749: cartons and boxes | E749: BOX LIT.7730 WOK 793 30 CM TITAN DUO | F749: BOX-
A750: 001717735001 | B750: BOX LIT.7735 BATTERIA ESSTEELE PER CUCINARE 051153186097 | C750: cartoni e casse | D750: cartons and boxes | E750: BOX LIT.7735 BATTERIA ESSTEELE PER CUCINARE 051153186097 | F750: BOX-
A751: 001717741001 | B751: BOX LIT.7741 100 24 +100 28+ MNC AMO.CLICK & COOK | C751: cartoni e casse | D751: cartons and boxes | E751: BOX LIT.7741 100 24 +100 28+ MNC AMO.CLICK & COOK | F751: LABL
A752: 001717743001 | B752: BOX LIT.7743 T.2M.F.574 C/C. Ø32 EXP SILVER COLOUR FOXHOME | C752: cartoni e casse | D752: cartons and boxes | E752: BOX LIT.7743 T.2M.F.574 C/C. Ø32 EXP SILVER COLOUR FOXHOME | F752: LABL
A753: 001717746001 | B753: BOX LIT.7746 C.2M.F.480 C/C. Ø24 EXP SILVER COLOUR FOXHOME | C753: cartoni e casse | D753: cartons and boxes | E753: BOX LIT.7746 C.2M.F.480 C/C. Ø24 EXP SILVER COLOUR FOXHOME | F753: LABL
...

Sheet Foglio8
A1: Item Code | B1: Part Description (English) | C1: UCC Category | D1: SHTS Code
A2: 660202007 | B2: Die-cast Grill Pan Greblon Black 26x17 | C2: ALM- | D2: 7615.10.7100
A3: 660202008 | B3: Die-cast Grill Pan Greblon Black 42x27 | C3: ALM- | D3: 7615.10.7100
A4: 660202009 | B4: Die-cast Pan w/ Ceramic Housing 35x22 | C4: ALM- | D4: 7615.10.7100
A5: 00010315014R | B5: Recycled Aluminum Disc 99.5 315/14 | C5: ALM- | D5: 7606.91.0000
A6: 000040300029R | B6: Recycled Aluminum Disc 4006 300/29 | C6: ALM- | D6: 7606.91.0000
A7: 288000051 | B7: SI Handle PVD Gold 16cm Saucepan | C7: HDL- | D7: 7323.93.0030
A8: 289000051 | B8: SI Side Handle PVD Gold 20cm Saucepan | C8: SHDL | D8: 7323.93.0030
A9: 250517107 | B9: Titano/2 Handle Wood Effect V.0013 | C9: HDL- | D9: 3924.10.4000
A10: 250003001 | B10: Victory/2 Handle - Satin Black | C10: HDL- | D10: 3924.10.4000
A11: 320471001 | B11: Polished Ice Investment Cast Steel Knob | C11: KNOB | D11: 7323.93.0030
A12: 283409001 | B12: Cast Steel Handle for Casserole/Skillet | C12: HDL- | D12: 7323.93.0030
A13: 1717797001 | B13: Flexo Box 7797 + Divider Kit | C13: BOX- | D13: 4819.10.0040
A14: 1761052030 | B14: Litho Band TVS Segno Induction | C14: PAP- | D14: 4821.10.0000
A15: 800017068 | B15: Satin "Made In" Label 60x24 | C15: LABL | D15: 4821.10.0000
A16: 1761150350 | B16: Litho Band Ugnar 472 + Glass Lid | C16: PAP- | D16: 4821.10.0000
A17: 2300004001 | B17: Die-cut Divider Flexo Box 7804-7805 | C17: PAP- | D17: 4819.10.0040
A18: 1880103072 | B18: Paper Divider 103x72cm | C18: PAP- | D18: 4819.10.0040
... A28: 200160004 | B28: Stud Bolt 10x10x17 80° 5MA Thread | C28: STUD | D28: 7318.15.2000
A29: 0001A0140005 | B29: Steel Disc 140/05 AISI430 Smooth/Satin | C29: SM-- | D29: 7210.70.6030

Sheet Foglio4
A1: Purchase Order Date | B1: (più elementi)
A2: Invoice Date | B2: (Tutto)
A4: Commodity English | B4: VendorName | C4: Somma di Total_PO_Price_PO CUR
A5: aluminium | B5: PROFILGLASS SPA | C5: 5499548.8
B6: ALMESAN ALUMINYUM SAN.VE TIC. A.S | C6: 2155038
B7: ARCONIC- KOFEM MILL PRODUCTS HUNGARY KFT. | C7: 583340.65
B8: ZHEJIANG CHICHENG iNDUSTRY & TRADE CO.LTD. | C8: 12372.58
A9: aluminium Totale | C9: 8250300.1
A10: chemical products | B10: WHITFORD SRL | C10: 748582.21
B11: KOREA FINE CERAMIC CO., LTD | C11: 452919.74
B12: EVONIK OPERATIONS GMBH | C12: 244204.5
B13: ILAG INDUSTRIELACK AG | C13: 151565.94
B14: GUJARAT FLUOROCHEMICALS GMBH | C14: 149486.4
B15: CHEMOURS BELGIUM BVBA | C15: 86073
B16: DN CHEMICALS SRL | C16: 37065.09
B17: GENERAL ABRASIVI SRL | C17: 35222.5
B18: ELANTAS EUROPE GMBH | C18: 32589
B19: KRAHN ITALIA SPA | C19: 27680.75
B20: EIGENMANN & VERONELLI SPA | C20: 23439.5
B21: VIBRANTZ ITALY SRL | C21: 23054.88
B22: MERCK SRL | C22: 19490
... B36: MERCK LIFE SCIENCE SRL | C36: 705
A37: chemical products Totale | C37: 2119512.8
A38: handles | B38: LA TERMOPLASTIC-F.B.M. SRL | C38: 651035.31
B39: SIPEX CAVAGNA S.P.A. | C39: 234160.63
B40: YUHUAN SUNNAR RUBBER&PLASTIC PRODUCTS CO.LTD | C40: 203986.17
B41: A&C SRL | C41: 176784.83
B42: SANMIRO SRL | C42: 141145.28
B43: TVS MED S.A.R.L. | C43: 139187.8
B44: MEYER MANUFACTURING COMPANY LIMITED | C44: 135719.95
B45: GULBAK BAKALIT METAL VE TEKSTIL SAN. ve TIC. LTD. STI | C45: 91983
B46: TEKNIKEL MAKINA KALIP IMALAT SAN. VE TIC. LTD STI. | C46: 79476.3
B47: MUTLU METAL DIS TICARET LTD.STI | C47: 78283.93
B48: TECNORESIN SRL | C48: 53880.26
B49: DOLCI EGIDIO SNC DI DOLCI MATTIA E PAOLA | C49: 18898.16
B50: BAUMGARTEN HANDLE SYSTEM KG | C50: 15283.28
... B60: FISCALETTI FAUSTO | C60: 1600
A61: handles Totale | C61: 2104241
A62: cartons and boxes | B62: BOX MARCHE SPA | C62: 898166.33
B63: SCATOLIFICIO I.S.A. SRL | C63: 247749.43
B64: F.LLI GIOVANNINI SRL | C64: 216389.83
B65: LAMPA PACKAGING S.R.L. | C65: 152433.97
B66: SCATOLIFICIO VEC SRL | C66: 142228.5
B67: EL.MA SNC | C67: 10297.77
B68: SAICO S.r.l. | C68: 6122.49
B69: B.GROUP SRL | C69: 5700
B70: ONDULATI ED IMBALLAGGI DEL FRIULI | C70: 5017.15
B71: PACART srl | C71: 3340
A72: cartons and boxes Totale | C72: 1687445.5
A73: steel | B73: IMF INDUSTRIE MARCHIGIANE FILTRI SRL | C73: 521157
B74: EUROACCIAI SPA | C74: 301317.25
B75: NINGBO CITY BEILUN HECHENG METAL PRODUCTS CO.LTD | C75: 96864.61
B76: INOX HOUSE SRL | C76: 365.4
A77: steel Totale | C77: 919704.26
A78: consumable materials | B78: Q.S.ABRASIVI MARENGO SRL | C78: 283550
B79: BURIONI TRADE S.r.l. | C79: 150778
B80: ECOPROJECT TECHNOLOGIES SRL | C80: 72600
B81: CHEMITECH S.r.l. | C81: 42640
B82: UNITEK SRL | C82: 40560
B83: WÜRTH SRL | C83: 24197.24
B84: DN CHEMICALS SRL | C84: 22424.9
B85: DLG SRLS | C85: 16632
B86: TALLEGNO SNC | C86: 16020.9
B87: SACS SPA | C87: 7692.8
B88: INDUSTRIAL SERVICE Srl | C88: 6648.53
B89: TECHMA SRL | C89: 4770
B90: BRENNTAG SPA | C90: 3770
... B99: ESSELUNGA SPA | C99: 114.92
A100: consumable materials Totale | C100: 706011.83
A101: accessories for handles | B101: F.LLI BERNABE'S.N.C.DI BERNABE' MARCO,MONICA E DANIELA | C101: 196960
B102: COOPERATIVA ALBANESI SCRL | C102: 123434.53
B103: MEYER MARKETING COMPANY LIMITED | C103: 11151.47
B104: P.R.P. DI PIEVANI S.& C. SNC | C104: 10400
B105: VITINOX SAS DI GUGLIELMELLI R.& C. | C105: 7454.1
B106: BONTEMPI S.R.L. | C106: 6594.06
B107: ITALVITINOX SRL | C107: 4132.44
B108: HEBEI BOZHENG GLASSWORK CO.LTD. | C108: 2621.23
B109: F.C.F. SRL | C109: 999.9
B110: XIANGSHAN JIUHUI MOULD CO.LTD. | C110: 399.66
A111: accessories for handles Totale | C111: 364147.39
A112: finished accessories | B112: HEBEI BOZHENG GLASSWORK CO.LTD. | C112: 151077.74
B113: INTERNATIONAL COOKWARE S.A.S. | C113: 58443.22
B114: MEYER MARKETING COMPANY LIMITED | C114: 54482.56
B115: MEYER MANUFACTURING COMPANY LIMITED | C115: 37560.03
B116: METALWELL ENTERPRISE CO.LTD. | C116: 20563.28
B117: KAVALIERGLASS A.S. | C117: 18012.24
B118: IPAC SPA | C118: 3040
B119: CALDER SNC DI LEGNAZZI MARCO & C. | C119: 3015
A120: finished accessories Totale | C120: 346194.07
A121: multilayer steel (5PLY) | B121: EDENTECH CO.LTD. | C121: 223166.12
B122: MEYER EUROPE SRL | C122: 44430
A123: multilayer steel (5PLY) Totale | C123: 267596.12
A124: packaging accessories | B124: BBC PLASTIK SRL | C124: 140041.23
B125: SAMAPLAST SRL | C125: 19047.37
B126: CARTON SRL | C126: 14056.25
B127: SLEEVER INTERNATIONAL | C127: 2660.58
B128: PACART srl | C128: 2346.1
A129: packaging accessories Totale | C129: 178151.53
A130: packaging material | B130: TIPOLITOGRAFIA ROTOGRAF SRL | C130: 78309.62
B131: TECNOSTAMPA SRL | C131: 59146.45
...
